Workbook
Name solver_adj: 'OTIMIZA ROTA'!$L$68:$Q$73,'OTIMIZA ROTA'!$L$78:$Q$83,'OTIMIZA ROTA'!$L$88:$Q$93
Name solver_cvg: 0.0001
Name solver_cvg: 0.0001
Name solver_drv: 1
Name solver_drv: 1
Name solver_eng: 2
Name solver_eng: 3
Name solver_est: 1
Name solver_est: 1
Name solver_itr: 2147483647
Name solver_itr: 2147483647
Name solver_mip: 2147483647
Name solver_mip: 2147483647
Name solver_mni: 30
Name solver_mni: 30
Name solver_mrt: 0.075
Name solver_mrt: 0.075
Name solver_msl: 2
Name solver_msl: 2
Name solver_neg: 1
Name solver_neg: 2
Name solver_nod: 2147483647
Name solver_nod: 2147483647
Name solver_num: 29
Name solver_num: 4
Name solver_nwt: 1
Name solver_nwt: 1
Name solver_pre: 0.000001
Name solver_pre: 0.000001
Name solver_rbv: 1
Name solver_rbv: 1
Name solver_rel1: 3
Name solver_rel1: 3
Name solver_rel10: 3
Name solver_rel11: 3
Name solver_rel12: 3
Name solver_rel13: 3
Name solver_rel14: 1
Name solver_rel15: 1
Name solver_rel16: 1
Name solver_rel17: 1
Name solver_rel18: 1
Name solver_rel19: 2
Name solver_rel2: 3
Name solver_rel2: 1
Name solver_rel20: 2
Name solver_rel21: 2
Name solver_rel22: 2
Name solver_rel23: 2
Name solver_rel24: 2
Name solver_rel25: 2
Name solver_rel26: 2
Name solver_rel27: 2
Name solver_rel28: 3
Name solver_rel29: 3
Name solver_rel3: 3
Name solver_rel3: 1
Name solver_rel30: 1
Name solver_rel31: 1
Name solver_rel32: 1

Sheet ANTAQ 2022 Container
B2: Month | C2: Type | D2: UF Origin | E2: UF Destination | F2: TEU | G2: Unit
B3: jan | C3: 40HC | D3: SP | E3: PE | F3: 3468 | G3: 1734
B4: jan | C4: 40HC | D4: RJ | E4: ES | F4: 3400 | G4: 1700
B5: jan | C5: 40HC | D5: SP | E5: PR | F5: 3106 | G5: 1553
B6: jan | C6: 40HC | D6: SP | E6: ES | F6: 2858 | G6: 1429
B7: jan | C7: 40HC | D7: SP | E7: AM | F7: 2776 | G7: 1388
B8: jan | C8: 40HC | D8: PE | E8: AM | F8: 2770 | G8: 1385 | J8: Mês | K8: jan | L8: fev | M8: mar | N8: abr | O8: mai | P8: jun | Q8: jul | R8: ago | S8: set | T8: out | U8: nov | V8: dez | W8: Total Geral
B9: jan | C9: 40HC | D9: AM | E9: SP | F9: 2714 | G9: 1357 | J9: TEU | K9: 81649 | L9: 83841 | M9: 102020 | N9: 91011 | O9: 104467 | P9: 97384 | Q9: 105192 | R9: 100343 | S9: 99251 | T9: 99655 | U9: 86179 | V9: 87708 | W9: 1138700
B10: jan | C10: 40HC | D10: AM | E10: SP | F10: 2414 | G10: 1207
B11: jan | C11: 40HC | D11: SP | E11: CE | F11: 2364 | G11: 1182
B12: jan | C12: 20DC | D12: ES | E12: RJ | F12: 2297 | G12: 2297
B13: jan | C13: 40HC | D13: AM | E13: PE | F13: 1802 | G13: 901
B14: jan | C14: 40HC | D14: CE | E14: AM | F14: 1628 | G14: 814
B15: jan | C15: 40RH | D15: SC | E15: AM | F15: 1328 | G15: 664
B16: jan | C16: 40HC | D16: SC | E16: CE | F16: 1318 | G16: 659
B17: jan | C17: 40HC | D17: SC | E17: AM | F17: 1316 | G17: 658
B18: jan | C18: 40HC | D18: SC | E18: PE | F18: 1214 | G18: 607
B19: jan | C19: 40HC | D19: PE | E19: SP | F19: 1208 | G19: 604
B20: jan | C20: 20DC | D20: SP | E20: PR | F20: 1002 | G20: 1002
B21: jan | C21: 40HC | D21: PE | E21: RJ | F21: 970 | G21: 485
... B5374: dez | C5374: 20DC | D5374: SP | E5374: SC | F5374: 1 | G5374: 1

Sheet Pivot Container
O2: Movimentação de Contêineres na Cabotagem em 2022 - 20DC | AD2: Imbalance 20DC
O3: Origem/Destino | P3: AM | Q3: PA | R3: MA | S3: CE | T3: PE | U3: BA | V3: ES | W3: RJ | X3: SP | Y3: PR | Z3: SC | AA3: RS | AB3: Total Origem | AD3: Porto | AE3: In | AF3: Out | AG3: IMB
O4: AM | R4: 1 | S4: 1747 | T4: 313 | U4: 329 | W4: 1002 | X4: 2513 | Z4: 475 | AA4: 19 | AB4: =SUM(P4:AA4) -> 6399 | AD4: AM | AE4: =P16 -> 13472 | AF4: =AB4 -> 6399 | AG4: =AE4-AF4 -> 7073
O5: PA | S5: 3833 | U5: 50 | X5: 3453 | Z5: 33 | AA5: 25 | AB5: =SUM(P5:AA5) -> 7394 | AD5: PA | AE5: =Q16 -> 327 | AF5: =AB5 -> 7394 | AG5: =AE5-AF5 -> -7067
O6: MA | S6: 9 | AA6: 9 | AB6: =SUM(P6:AA6) -> 18 | AD6: MA | AE6: =R16 -> 1601 | AF6: =AB6 -> 18 | AG6: =AE6-AF6 -> 1583
O7: CE | P7: 2926 | Q7: 327 | R7: 22 | T7: 282 | U7: 491 | W7: 1239 | X7: 9135 | Z7: 4055 | AA7: 432 | AB7: =SUM(P7:AA7) -> 18909 | AD7: CE | AE7: =S16 -> 34483 | AF7: =AB7 -> 18909 | AG7: =AE7-AF7 -> 15574
O8: PE | P8: 2039 | R8: 1 | S8: 1481 | U8: 2967 | V8: 17 | W8: 1887 | X8: 8519 | Y8: 1 | Z8: 827 | AA8: 264 | AB8: =SUM(P8:AA8) -> 18003 | AD8: PE | AE8: =T16 -> 27865 | AF8: =AB8 -> 18003 | AG8: =AE8-AF8 -> 9862
O9: BA | P9: 407 | S9: 779 | T9: 670 | V9: 11 | W9: 565 | X9: 10907 | Y9: 56 | Z9: 289 | AA9: 145 | AB9: =SUM(P9:AA9) -> 13829 | AD9: BA | AE9: =U16 -> 14720 | AF9: =AB9 -> 13829 | AG9: =AE9-AF9 -> 891
O10: ES | P10: 652 | T10: 39 | W10: 38075 | X10: 5566 | Z10: 55 | AA10: 2 | AB10: =SUM(P10:AA10) -> 44389 | AD10: ES | AE10: =V16 -> 14162 | AF10: =AB10 -> 44389 | AG10: =AE10-AF10 -> -30227
O11: RJ | P11: 1770 | S11: 322 | T11: 517 | U11: 663 | V11: 9148 | X11: 1315 | Y11: 95 | Z11: 761 | AB11: =SUM(P11:AA11) -> 14591 | AD11: RJ | AE11: =W16 -> 47784 | AF11: =AB11 -> 14591 | AG11: =AE11-AF11 -> 33193
O12: SP | P12: 4058 | R12: 31 | S12: 6369 | T12: 6570 | U12: 2077 | V12: 4986 | W12: 4217 | Y12: 8785 | Z12: 4563 | AB12: =SUM(P12:AA12) -> 41656 | AD12: SP | AE12: =X16 -> 42126 | AF12: =AB12 -> 41656 | AG12: =AE12-AF12 -> 470
O13: PR | S13: 11 | U13: 11 | W13: 3 | X13: 1 | Z13: 455 | AB13: =SUM(P13:AA13) -> 481 | AD13: PR | AE13: =Y16 -> 10534 | AF13: =AB13 -> 481 | AG13: =AE13-AF13 -> 10053
O14: SC | P14: 1452 | R14: 346 | S14: 11836 | T14: 13601 | U14: 4203 | W14: 778 | X14: 256 | Y14: 1573 | Z14: 803 | AA14: 6 | AB14: =SUM(P14:AA14) -> 34854 | AD14: SC | AE14: =Z16 -> 12703 | AF14: =AB14 -> 34854 | AG14: =AE14-AF14 -> -22151
O15: RS | P15: 168 | R15: 1200 | S15: 8096 | T15: 5873 | U15: 3929 | W15: 18 | X15: 461 | Y15: 24 | Z15: 387 | AB15: =SUM(P15:AA15) -> 20156 | AD15: RS | AE15: =AA16 -> 902 | AF15: =AB15 -> 20156 | AG15: =AE15-AF15 -> -19254
O16: Total Destino | P16: =SUM(P4:P15) -> 13472 | Q16: =SUM(Q4:Q15) -> 327 | R16: =SUM(R4:R15) -> 1601 | S16: =SUM(S4:S15) -> 34483 | T16: =SUM(T4:T15) -> 27865 | U16: =SUM(U4:U15) -> 14720 | V16: =SUM(V4:V15) -> 14162 | W16: =SUM(W4:W15) -> 47784 | ... AB16: =SUM(AB4:AB15) -> 220679 | AD16: Total | AE16: =SUM(AE4:AE15) -> 220679 | AF16: =SUM(AF4:AF15) -> 220679 | AG16: =ABS(AG4)+ABS(AG5)+ABS(AG6)+ABS(AG7)+ABS(AG8)+ABS(AG9)+ABS(AG10)+ABS(AG11)+ABS(AG12)+ABS(AG13)+ABS(AG14)+ABS(AG15) -> 157398
O18: Movimentação de Contêineres na Cabotagem em 2022 - 20RF | AD18: Imbalance 20RF
O19: Origem/Destino | P19: AM | Q19: PA | R19: MA | S19: CE | T19: PE | U19: BA | V19: ES | W19: RJ | X19: SP | Y19: PR | Z19: SC | AA19: RS | AB19: Total Origem | AD19: Porto | AE19: In | AF19: Out | AG19: IMB
O20: AM | T20: 1 | U20: 2 | AB20: =SUM(P20:AA20) -> 3 | AD20: AM | AE20: =P32 -> 0 | AF20: =AB20 -> 3 | AG20: =AE20-AF20 -> -3
O21: PA | AB21: =SUM(P21:AA21) -> 0 | AD21: PA | AE21: =Q32 -> 0 | AF21: =AB21 -> 0 | AG21: =AE21-AF21 -> 0
O22: MA | AB22: =SUM(P22:AA22) -> 0 | AD22: MA | AE22: =R32 -> 0 | AF22: =AB22 -> 0 | AG22: =AE22-AF22 -> 0
O23: CE | AB23: =SUM(P23:AA23) -> 0 | AD23: CE | AE23: =S32 -> 33 | AF23: =AB23 -> 0 | AG23: =AE23-AF23 -> 33
O24: PE | S24: 3 | X24: 1 | Z24: 4 | AB24: =SUM(P24:AA24) -> 8 | AD24: PE | AE24: =T32 -> 29 | AF24: =AB24 -> 8 | AG24: =AE24-AF24 -> 21
O25: BA | S25: 4 | T25: 2 | X25: 2 | Z25: 2 | AB25: =SUM(P25:AA25) -> 10 | AD25: BA | AE25: =U32 -> 4 | AF25: =AB25 -> 10 | AG25: =AE25-AF25 -> -6
O26: ES | W26: 2 | X26: 9 | Z26: 1 | AB26: =SUM(P26:AA26) -> 12 | AD26: ES | AE26: =V32 -> 0 | AF26: =AB26 -> 12 | AG26: =AE26-AF26 -> -12
O27: RJ | S27: 1 | X27: 1 | Y27: 1 | Z27: 1 | AB27: =SUM(P27:AA27) -> 4 | AD27: RJ | AE27: =W32 -> 8 | AF27: =AB27 -> 4 | AG27: =AE27-AF27 -> 4
O28: SP | S28: 17 | T28: 16 | U28: 2 | W28: 5 | Y28: 24 | Z28: 6 | AB28: =SUM(P28:AA28) -> 70 | AD28: SP | AE28: =X32 -> 13 | AF28: =AB28 -> 70 | AG28: =AE28-AF28 -> -57
O29: PR | AB29: =SUM(P29:AA29) -> 0 | AD29: PR | AE29: =Y32 -> 35 | AF29: =AB29 -> 0 | AG29: =AE29-AF29 -> 35
O30: SC | S30: 7 | T30: 9 | W30: 1 | Y30: 10 | Z30: 1 | AB30: =SUM(P30:AA30) -> 28 | AD30: SC | AE30: =Z32 -> 16 | AF30: =AB30 -> 28 | AG30: =AE30-AF30 -> -12
O31: RS | S31: 1 | T31: 1 | Z31: 1 | AB31: =SUM(P31:AA31) -> 3 | AD31: RS | AE31: =AA32 -> 0 | AF31: =AB31 -> 3 | AG31: =AE31-AF31 -> -3
O32: Total Destino | P32: =SUM(P20:P31) -> 0 | Q32: =SUM(Q20:Q31) -> 0 | R32: =SUM(R20:R31) -> 0 | S32: =SUM(S20:S31) -> 33 | T32: =SUM(T20:T31) -> 29 | U32: =SUM(U20:U31) -> 4 | V32: =SUM(V20:V31) -> 0 | W32: =SUM(W20:W31) -> 8 | ... AB32: =SUM(AB20:AB31) -> 138 | AD32: Total | AE32: =SUM(AE20:AE31) -> 138 | AF32: =SUM(AF20:AF31) -> 138 | AG32: =ABS(AG20)+ABS(AG21)+ABS(AG22)+ABS(AG23)+ABS(AG24)+ABS(AG25)+ABS(AG26)+ABS(AG27)+ABS(AG28)+ABS(AG29)+ABS(AG30)+ABS(AG31) -> 186
O34: Movimentação de Contêineres na Cabotagem em 2022 - 40HC | AD34: Imbalance 40HC
O35: Origem/Destino | P35: AM | Q35: PA | R35: MA | S35: CE | T35: PE | U35: BA | V35: ES | W35: RJ | X35: SP | Y35: PR | Z35: SC | AA35: RS | AB35: Total Origem | AD35: Porto | AE35: In | AF35: Out | AG35: IMB
O36: AM | R36: 9 | S36: 6066 | T36: 8232 | U36: 3166 | W36: 7014 | X36: 54983 | Y36: 3 | Z36: 5501 | AA36: 699 | AB36: =SUM(P36:AA36) -> 85673 | AD36: AM | AE36: =P48 -> 66942 | AF36: =AB36 -> 85673 | AG36: =AE36-AF36 -> -18731
O37: PA | S37: 1805 | U37: 4 | X37: 704 | Z37: 92 | AA37: 6 | AB37: =SUM(P37:AA37) -> 2611 | AD37: PA | AE37: =Q48 -> 986 | AF37: =AB37 -> 2611 | AG37: =AE37-AF37 -> -1625
O38: MA | S38: 51 | X38: 52 | AA38: 3 | AB38: =SUM(P38:AA38) -> 106 | AD38: MA | AE38: =R48 -> 2511 | AF38: =AB38 -> 106 | AG38: =AE38-AF38 -> 2405
O39: CE | P39: 10303 | Q39: 985 | R39: 157 | T39: 2481 | U39: 101 | W39: 462 | X39: 7856 | Z39: 3188 | AA39: 366 | AB39: =SUM(P39:AA39) -> 25899 | AD39: CE | AE39: =S48 -> 57391 | AF39: =AB39 -> 25899 | AG39: =AE39-AF39 -> 31492
O40: PE | P40: 17515 | R40: 405 | S40: 5046 | U40: 652 | V40: 103 | W40: 1554 | X40: 9764 | Z40: 4287 | AA40: 963 | AB40: =SUM(P40:AA40) -> 40289 | AD40: PE | AE40: =T48 -> 70371 | AF40: =AB40 -> 40289 | AG40: =AE40-AF40 -> 30082
O41: BA | P41: 3252 | R41: 82 | S41: 2029 | T41: 1364 | V41: 58 | W41: 1612 | X41: 10648 | Y41: 100 | Z41: 2531 | AA41: 490 | AB41: =SUM(P41:AA41) -> 22166 | AD41: BA | AE41: =U48 -> 16952 | AF41: =AB41 -> 22166 | AG41: =AE41-AF41 -> -5214
O42: ES | P42: 933 | T42: 11 | W42: 3802 | X42: 2419 | Z42: 31 | AA42: 8 | AB42: =SUM(P42:AA42) -> 7204 | AD42: ES | AE42: =V48 -> 30266 | AF42: =AB42 -> 7204 | AG42: =AE42-AF42 -> 23062
O43: RJ | P43: 3272 | R43: 10 | S43: 1358 | T43: 5765 | U43: 3757 | V43: 17898 | X43: 2957 | Y43: 102 | Z43: 1095 | AA43: 2 | AB43: =SUM(P43:AA43) -> 36216 | AD43: RJ | AE43: =W48 -> 22587 | AF43: =AB43 -> 36216 | AG43: =AE43-AF43 -> -13629
O44: SP | P44: 18041 | Q44: 1 | R44: 1087 | S44: 22859 | T44: 29225 | U44: 4383 | V44: 12207 | W44: 7382 | Y44: 20877 | Z44: 14334 | AA44: 8 | AB44: =SUM(P44:AA44) -> 130404 | AD44: SP | AE44: =X48 -> 90993 | AF44: =AB44 -> 130404 | AG44: =AE44-AF44 -> -39411
O45: PR | S45: 4 | W45: 27 | X45: 49 | Z45: 957 | AB45: =SUM(P45:AA45) -> 1037 | AD45: PR | AE45: =Y48 -> 23971 | AF45: =AB45 -> 1037 | AG45: =AE45-AF45 -> 22934
O46: SC | P46: 11210 | R46: 617 | S46: 13198 | T46: 20046 | U46: 2406 | W46: 730 | X46: 396 | Y46: 2809 | Z46: 1592 | AA46: 7 | AB46: =SUM(P46:AA46) -> 53011 | AD46: SC | AE46: =Z48 -> 35220 | AF46: =AB46 -> 53011 | AG46: =AE46-AF46 -> -17791
O47: RS | P47: 2416 | R47: 144 | S47: 4975 | T47: 3247 | U47: 2483 | W47: 4 | X47: 1165 | Y47: 80 | Z47: 1612 | AB47: =SUM(P47:AA47) -> 16126 | AD47: RS | AE47: =AA48 -> 2552 | AF47: =AB47 -> 16126 | AG47: =AE47-AF47 -> -13574
O48: Total Destino | P48: =SUM(P36:P47) -> 66942 | Q48: =SUM(Q36:Q47) -> 986 | R48: =SUM(R36:R47) -> 2511 | S48: =SUM(S36:S47) -> 57391 | T48: =SUM(T36:T47) -> 70371 | U48: =SUM(U36:U47) -> 16952 | V48: =SUM(V36:V47) -> 30266 | W48: =SUM(W36:W47) -> 22587 | ... AB48: =SUM(AB36:AB47) -> 420742 | AD48: Total | AE48: =SUM(AE36:AE47) -> 420742 | AF48: =SUM(AF36:AF47) -> 420742 | AG48: =ABS(AG36)+ABS(AG37)+ABS(AG38)+ABS(AG39)+ABS(AG40)+ABS(AG41)+ABS(AG42)+ABS(AG43)+ABS(AG44)+ABS(AG45)+ABS(AG46)+ABS(AG47) -> 219950
O50: Movimentação de Contêineres na Cabotagem em 2022 - 40RH | AD50: Imbalance 40RH
O51: Origem/Destino | P51: AM | Q51: PA | R51: MA | S51: CE | T51: PE | U51: BA | V51: ES | W51: RJ | X51: SP | Y51: PR | Z51: SC | AA51: RS | AB51: Total Origem | AD51: Porto | AE51: In | AF51: Out | AG51: IMB
O52: AM | S52: 12 | T52: 6 | U52: 1 | W52: 35 | X52: 58 | Z52: 46 | AB52: =SUM(P52:AA52) -> 158 | AD52: AM | AE52: =P64 -> 10569 | AF52: =AB52 -> 158 | AG52: =AE52-AF52 -> 10411
O53: PA | S53: 368 | U53: 12 | X53: 122 | AA53: 1 | AB53: =SUM(P53:AA53) -> 503 | AD53: PA | AE53: =Q64 -> 88 | AF53: =AB53 -> 503 | AG53: =AE53-AF53 -> -415
O54: MA | AB54: =SUM(P54:AA54) -> 0 | AD54: MA | AE54: =R64 -> 153 | AF54: =AB54 -> 0 | AG54: =AE54-AF54 -> 153
O55: CE | P55: 155 | Q55: 88 | R55: 24 | T55: 17 | U55: 2 | W55: 86 | X55: 215 | Z55: 78 | AB55: =SUM(P55:AA55) -> 665 | AD55: CE | AE55: =S64 -> 7083 | AF55: =AB55 -> 665 | AG55: =AE55-AF55 -> 6418
O56: PE | P56: 1593 | R56: 37 | S56: 407 | U56: 1 | W56: 13 | X56: 40 | Y56: 4 | Z56: 9 | AB56: =SUM(P56:AA56) -> 2104 | AD56: PE | AE56: =T64 -> 7955 | AF56: =AB56 -> 2104 | AG56: =AE56-AF56 -> 5851
O57: BA | P57: 214 | S57: 327 | T57: 339 | W57: 60 | X57: 644 | Y57: 9 | Z57: 24 | AB57: =SUM(P57:AA57) -> 1617 | AD57: BA | AE57: =U64 -> 1535 | AF57: =AB57 -> 1617 | AG57: =AE57-AF57 -> -82
O58: ES | P58: 1 | W58: 38 | X58: 29 | Z58: 5 | AB58: =SUM(P58:AA58) -> 73 | AD58: ES | AE58: =V64 -> 0 | AF58: =AB58 -> 73 | AG58: =AE58-AF58 -> -73
O59: RJ | P59: 60 | S59: 59 | T59: 138 | U59: 51 | X59: 145 | Y59: 11 | Z59: 170 | AB59: =SUM(P59:AA59) -> 634 | AD59: RJ | AE59: =W64 -> 1913 | AF59: =AB59 -> 634 | AG59: =AE59-AF59 -> 1279
O60: SP | P60: 2308 | R60: 49 | S60: 2321 | T60: 2268 | U60: 331 | W60: 988 | Y60: 2882 | Z60: 3237 | AA60: 1 | AB60: =SUM(P60:AA60) -> 14385 | AD60: SP | AE60: =X64 -> 1583 | AF60: =AB60 -> 14385 | AG60: =AE60-AF60 -> -12802
O61: PR | S61: 5 | W61: 35 | X61: 46 | Z61: 271 | AB61: =SUM(P61:AA61) -> 357 | AD61: PR | AE61: =Y64 -> 3244 | AF61: =AB61 -> 357 | AG61: =AE61-AF61 -> 2887
O62: SC | P62: 6226 | R62: 43 | S62: 3479 | T62: 5045 | U62: 1134 | W62: 654 | X62: 53 | Y62: 326 | Z62: 835 | AA62: 1 | AB62: =SUM(P62:AA62) -> 17796 | AD62: SC | AE62: =Z64 -> 5149 | AF62: =AB62 -> 17796 | AG62: =AE62-AF62 -> -12647
O63: RS | P63: 12 | S63: 105 | T63: 142 | U63: 3 | W63: 4 | X63: 231 | Y63: 12 | Z63: 474 | AB63: =SUM(P63:AA63) -> 983 | AD63: RS | AE63: =AA64 -> 3 | AF63: =AB63 -> 983 | AG63: =AE63-AF63 -> -980
O64: Total Destino | P64: =SUM(P52:P63) -> 10569 | Q64: =SUM(Q52:Q63) -> 88 | R64: =SUM(R52:R63) -> 153 | S64: =SUM(S52:S63) -> 7083 | T64: =SUM(T52:T63) -> 7955 | U64: =SUM(U52:U63) -> 1535 | V64: =SUM(V52:V63) -> 0 | W64: =SUM(W52:W63) -> 1913 | ... AB64: =SUM(AB52:AB63) -> 39275 | AD64: Total | AE64: =SUM(AE52:AE63) -> 39275 | AF64: =SUM(AF52:AF63) -> 39275 | AG64: =ABS(AG52)+ABS(AG53)+ABS(AG54)+ABS(AG55)+ABS(AG56)+ABS(AG57)+ABS(AG58)+ABS(AG59)+ABS(AG60)+ABS(AG61)+ABS(AG62)+ABS(AG63) -> 53998
O66: Movimentação de Contêineres na Cabotagem em 2022 - unidades | AD66: Imbalance Unidades
O67: Origem/Destino | P67: AM | Q67: PA | R67: MA | S67: CE | T67: PE | U67: BA | V67: ES | W67: RJ | X67: SP | Y67: PR | Z67: SC | AA67: RS | AB67: Total Origem | AD67: Porto | AE67: In | AF67: Out | AG67: IMB
O68: AM | P68: =P4+P20+P36+P52 -> 0 | Q68: =Q4+Q20+Q36+Q52 -> 0 | R68: =R4+R20+R36+R52 -> 10 | S68: =S4+S20+S36+S52 -> 7825 | T68: =T4+T20+T36+T52 -> 8552 | U68: =U4+U20+U36+U52 -> 3498 | V68: =V4+V20+V36+V52 -> 0 | W68: =W4+W20+W36+W52 -> 8051 | ... AA68: =AA4+AA20+AA36+AA52 -> 718 | AB68: =SUM(P68:AA68) -> 92233 | AD68: AM | AE68: =P80 -> 90983 | AF68: =AB68 -> 92233 | AG68: =AE68-AF68 -> -1250
O69: PA | P69: =P5+P21+P37+P53 -> 0 | Q69: =Q5+Q21+Q37+Q53 -> 0 | R69: =R5+R21+R37+R53 -> 0 | S69: =S5+S21+S37+S53 -> 6006 | T69: =T5+T21+T37+T53 -> 0 | U69: =U5+U21+U37+U53 -> 66 | V69: =V5+V21+V37+V53 -> 0 | W69: =W5+W21+W37+W53 -> 0 | ... AA69: =AA5+AA21+AA37+AA53 -> 32 | AB69: =SUM(P69:AA69) -> 10508 | AD69: PA | AE69: =Q80 -> 1401 | AF69: =AB69 -> 10508 | AG69: =AE69-AF69 -> -9107
O70: MA | P70: =P6+P22+P38+P54 -> 0 | Q70: =Q6+Q22+Q38+Q54 -> 0 | R70: =R6+R22+R38+R54 -> 0 | S70: =S6+S22+S38+S54 -> 60 | T70: =T6+T22+T38+T54 -> 0 | U70: =U6+U22+U38+U54 -> 0 | V70: =V6+V22+V38+V54 -> 0 | W70: =W6+W22+W38+W54 -> 0 | ... AA70: =AA6+AA22+AA38+AA54 -> 12 | AB70: =SUM(P70:AA70) -> 124 | AD70: MA | AE70: =R80 -> 4265 | AF70: =AB70 -> 124 | AG70: =AE70-AF70 -> 4141
O71: CE | P71: =P7+P23+P39+P55 -> 13384 | Q71: =Q7+Q23+Q39+Q55 -> 1400 | R71: =R7+R23+R39+R55 -> 203 | S71: =S7+S23+S39+S55 -> 0 | T71: =T7+T23+T39+T55 -> 2780 | U71: =U7+U23+U39+U55 -> 594 | V71: =V7+V23+V39+V55 -> 0 | W71: =W7+W23+W39+W55 -> 1787 | ... AA71: =AA7+AA23+AA39+AA55 -> 798 | AB71: =SUM(P71:AA71) -> 45473 | AD71: CE | AE71: =S80 -> 98990 | AF71: =AB71 -> 45473 | AG71: =AE71-AF71 -> 53517
O72: PE | P72: =P8+P24+P40+P56 -> 21147 | Q72: =Q8+Q24+Q40+Q56 -> 0 | R72: =R8+R24+R40+R56 -> 443 | S72: =S8+S24+S40+S56 -> 6937 | T72: =T8+T24+T40+T56 -> 0 | U72: =U8+U24+U40+U56 -> 3620 | V72: =V8+V24+V40+V56 -> 120 | W72: =W8+W24+W40+W56 -> 3454 | ... AA72: =AA8+AA24+AA40+AA56 -> 1227 | AB72: =SUM(P72:AA72) -> 60404 | AD72: PE | AE72: =T80 -> 106220 | AF72: =AB72 -> 60404 | AG72: =AE72-AF72 -> 45816
O73: BA | P73: =P9+P25+P41+P57 -> 3873 | Q73: =Q9+Q25+Q41+Q57 -> 0 | R73: =R9+R25+R41+R57 -> 82 | S73: =S9+S25+S41+S57 -> 3139 | T73: =T9+T25+T41+T57 -> 2375 | U73: =U9+U25+U41+U57 -> 0 | V73: =V9+V25+V41+V57 -> 69 | W73: =W9+W25+W41+W57 -> 2237 | ... AA73: =AA9+AA25+AA41+AA57 -> 635 | AB73: =SUM(P73:AA73) -> 37622 | AD73: BA | AE73: =U80 -> 33211 | AF73: =AB73 -> 37622 | AG73: =AE73-AF73 -> -4411
O74: ES | P74: =P10+P26+P42+P58 -> 1586 | Q74: =Q10+Q26+Q42+Q58 -> 0 | R74: =R10+R26+R42+R58 -> 0 | S74: =S10+S26+S42+S58 -> 0 | T74: =T10+T26+T42+T58 -> 50 | U74: =U10+U26+U42+U58 -> 0 | V74: =V10+V26+V42+V58 -> 0 | W74: =W10+W26+W42+W58 -> 41917 | ... AA74: =AA10+AA26+AA42+AA58 -> 10 | AB74: =SUM(P74:AA74) -> 51678 | AD74: ES | AE74: =V80 -> 44428 | AF74: =AB74 -> 51678 | AG74: =AE74-AF74 -> -7250
O75: RJ | P75: =P11+P27+P43+P59 -> 5102 | Q75: =Q11+Q27+Q43+Q59 -> 0 | R75: =R11+R27+R43+R59 -> 10 | S75: =S11+S27+S43+S59 -> 1740 | T75: =T11+T27+T43+T59 -> 6420 | U75: =U11+U27+U43+U59 -> 4471 | V75: =V11+V27+V43+V59 -> 27046 | W75: =W11+W27+W43+W59 -> 0 | ... AA75: =AA11+AA27+AA43+AA59 -> 2 | AB75: =SUM(P75:AA75) -> 51445 | AD75: RJ | AE75: =W80 -> 72292 | AF75: =AB75 -> 51445 | AG75: =AE75-AF75 -> 20847
O76: SP | P76: =P12+P28+P44+P60 -> 24407 | Q76: =Q12+Q28+Q44+Q60 -> 1 | R76: =R12+R28+R44+R60 -> 1167 | S76: =S12+S28+S44+S60 -> 31566 | T76: =T12+T28+T44+T60 -> 38079 | U76: =U12+U28+U44+U60 -> 6793 | V76: =V12+V28+V44+V60 -> 17193 | W76: =W12+W28+W44+W60 -> 12592 | ... AA76: =AA12+AA28+AA44+AA60 -> 9 | AB76: =SUM(P76:AA76) -> 186515 | AD76: SP | AE76: =X80 -> 134715 | AF76: =AB76 -> 186515 | AG76: =AE76-AF76 -> -51800
O77: PR | P77: =P13+P29+P45+P61 -> 0 | Q77: =Q13+Q29+Q45+Q61 -> 0 | R77: =R13+R29+R45+R61 -> 0 | S77: =S13+S29+S45+S61 -> 20 | T77: =T13+T29+T45+T61 -> 0 | U77: =U13+U29+U45+U61 -> 11 | V77: =V13+V29+V45+V61 -> 0 | W77: =W13+W29+W45+W61 -> 65 | ... AA77: =AA13+AA29+AA45+AA61 -> 0 | AB77: =SUM(P77:AA77) -> 1875 | AD77: PR | AE77: =Y80 -> 37784 | AF77: =AB77 -> 1875 | AG77: =AE77-AF77 -> 35909
O78: SC | P78: =P14+P30+P46+P62 -> 18888 | Q78: =Q14+Q30+Q46+Q62 -> 0 | R78: =R14+R30+R46+R62 -> 1006 | S78: =S14+S30+S46+S62 -> 28520 | T78: =T14+T30+T46+T62 -> 38701 | U78: =U14+U30+U46+U62 -> 7743 | V78: =V14+V30+V46+V62 -> 0 | W78: =W14+W30+W46+W62 -> 2163 | ... AA78: =AA14+AA30+AA46+AA62 -> 14 | AB78: =SUM(P78:AA78) -> 105689 | AD78: SC | AE78: =Z80 -> 53088 | AF78: =AB78 -> 105689 | AG78: =AE78-AF78 -> -52601
O79: RS | P79: =P15+P31+P47+P63 -> 2596 | Q79: =Q15+Q31+Q47+Q63 -> 0 | R79: =R15+R31+R47+R63 -> 1344 | S79: =S15+S31+S47+S63 -> 13177 | T79: =T15+T31+T47+T63 -> 9263 | U79: =U15+U31+U47+U63 -> 6415 | V79: =V15+V31+V47+V63 -> 0 | W79: =W15+W31+W47+W63 -> 26 | ... AA79: =AA15+AA31+AA47+AA63 -> 0 | AB79: =SUM(P79:AA79) -> 37268 | AD79: RS | AE79: =AA80 -> 3457 | AF79: =AB79 -> 37268 | AG79: =AE79-AF79 -> -33811
O80: Total Destino | P80: =SUM(P68:P79) -> 90983 | Q80: =SUM(Q68:Q79) -> 1401 | R80: =SUM(R68:R79) -> 4265 | S80: =SUM(S68:S79) -> 98990 | T80: =SUM(T68:T79) -> 106220 | U80: =SUM(U68:U79) -> 33211 | V80: =SUM(V68:V79) -> 44428 | W80: =SUM(W68:W79) -> 72292 | ... AB80: =SUM(AB68:AB79) -> 680834 | AD80: Total | AE80: =SUM(AE68:AE79) -> 680834 | AF80: =SUM(AF68:AF79) -> 680834 | AG80: =ABS(AG68)+ABS(AG69)+ABS(AG70)+ABS(AG71)+ABS(AG72)+ABS(AG73)+ABS(AG74)+ABS(AG75)+ABS(AG76)+ABS(AG77)+ABS(AG78)+ABS(AG79) -> 320460 | AI80: =AG98-AG80 -> 111072
O82: Movimentação de Contêineres na Cabotagem em 2022 - TEU | AD82: Imbalance TEU
O83: Origem/Destino | P83: AM | Q83: PA | R83: MA | S83: CE | T83: PE | U83: BA | V83: ES | W83: RJ | X83: SP | Y83: PR | Z83: SC | AA83: RS | AB83: Total Origem | AD83: Porto | AE83: In | AF83: Out | AG83: IMB
O84: AM | P84: =P68+P36+P52 -> 0 | Q84: =Q68+Q36+Q52 -> 0 | R84: =R68+R36+R52 -> 19 | S84: =S68+S36+S52 -> 13903 | T84: =T68+T36+T52 -> 16790 | U84: =U68+U36+U52 -> 6665 | V84: =V68+V36+V52 -> 0 | W84: =W68+W36+W52 -> 15100 | ... AA84: =AA68+AA36+AA52 -> 1417 | AB84: =SUM(P84:AA84) -> 178064 | AD84: AM | AE84: =P96 -> 168494 | AF84: =AB84 -> 178064 | AG84: =AE84-AF84 -> -9570
O85: PA | P85: =P69+P37+P53 -> 0 | Q85: =Q69+Q37+Q53 -> 0 | R85: =R69+R37+R53 -> 0 | S85: =S69+S37+S53 -> 8179 | T85: =T69+T37+T53 -> 0 | U85: =U69+U37+U53 -> 82 | V85: =V69+V37+V53 -> 0 | W85: =W69+W37+W53 -> 0 | ... AA85: =AA69+AA37+AA53 -> 39 | AB85: =SUM(P85:AA85) -> 13622 | AD85: PA | AE85: =Q96 -> 2475 | AF85: =AB85 -> 13622 | AG85: =AE85-AF85 -> -11147
O86: MA | P86: =P70+P38+P54 -> 0 | Q86: =Q70+Q38+Q54 -> 0 | R86: =R70+R38+R54 -> 0 | S86: =S70+S38+S54 -> 111 | T86: =T70+T38+T54 -> 0 | U86: =U70+U38+U54 -> 0 | V86: =V70+V38+V54 -> 0 | W86: =W70+W38+W54 -> 0 | ... AA86: =AA70+AA38+AA54 -> 15 | AB86: =SUM(P86:AA86) -> 230 | AD86: MA | AE86: =R96 -> 6929 | AF86: =AB86 -> 230 | AG86: =AE86-AF86 -> 6699
O87: CE | P87: =P71+P39+P55 -> 23842 | Q87: =Q71+Q39+Q55 -> 2473 | R87: =R71+R39+R55 -> 384 | S87: =S71+S39+S55 -> 0 | T87: =T71+T39+T55 -> 5278 | U87: =U71+U39+U55 -> 697 | V87: =V71+V39+V55 -> 0 | W87: =W71+W39+W55 -> 2335 | ... AA87: =AA71+AA39+AA55 -> 1164 | AB87: =SUM(P87:AA87) -> 72037 | AD87: CE | AE87: =S96 -> 163464 | AF87: =AB87 -> 72037 | AG87: =AE87-AF87 -> 91427
O88: PE | P88: =P72+P40+P56 -> 40255 | Q88: =Q72+Q40+Q56 -> 0 | R88: =R72+R40+R56 -> 885 | S88: =S72+S40+S56 -> 12390 | T88: =T72+T40+T56 -> 0 | U88: =U72+U40+U56 -> 4273 | V88: =V72+V40+V56 -> 223 | W88: =W72+W40+W56 -> 5021 | ... AA88: =AA72+AA40+AA56 -> 2190 | AB88: =SUM(P88:AA88) -> 102797 | AD88: PE | AE88: =T96 -> 184546 | AF88: =AB88 -> 102797 | AG88: =AE88-AF88 -> 81749
O89: BA | P89: =P73+P41+P57 -> 7339 | Q89: =Q73+Q41+Q57 -> 0 | R89: =R73+R41+R57 -> 164 | S89: =S73+S41+S57 -> 5495 | T89: =T73+T41+T57 -> 4078 | U89: =U73+U41+U57 -> 0 | V89: =V73+V41+V57 -> 127 | W89: =W73+W41+W57 -> 3909 | ... AA89: =AA73+AA41+AA57 -> 1125 | AB89: =SUM(P89:AA89) -> 61405 | AD89: BA | AE89: =U96 -> 51698 | AF89: =AB89 -> 61405 | AG89: =AE89-AF89 -> -9707
O90: ES | P90: =P74+P42+P58 -> 2520 | Q90: =Q74+Q42+Q58 -> 0 | R90: =R74+R42+R58 -> 0 | S90: =S74+S42+S58 -> 0 | T90: =T74+T42+T58 -> 61 | U90: =U74+U42+U58 -> 0 | V90: =V74+V42+V58 -> 0 | W90: =W74+W42+W58 -> 45757 | ... AA90: =AA74+AA42+AA58 -> 18 | AB90: =SUM(P90:AA90) -> 58955 | AD90: ES | AE90: =V96 -> 74694 | AF90: =AB90 -> 58955 | AG90: =AE90-AF90 -> 15739
O91: RJ | P91: =P75+P43+P59 -> 8434 | Q91: =Q75+Q43+Q59 -> 0 | R91: =R75+R43+R59 -> 20 | S91: =S75+S43+S59 -> 3157 | T91: =T75+T43+T59 -> 12323 | U91: =U75+U43+U59 -> 8279 | V91: =V75+V43+V59 -> 44944 | W91: =W75+W43+W59 -> 0 | ... AA91: =AA75+AA43+AA59 -> 4 | AB91: =SUM(P91:AA91) -> 88295 | AD91: RJ | AE91: =W96 -> 96792 | AF91: =AB91 -> 88295 | AG91: =AE91-AF91 -> 8497
O92: SP | P92: =P76+P44+P60 -> 44756 | Q92: =Q76+Q44+Q60 -> 2 | R92: =R76+R44+R60 -> 2303 | S92: =S76+S44+S60 -> 56746 | T92: =T76+T44+T60 -> 69572 | U92: =U76+U44+U60 -> 11507 | V92: =V76+V44+V60 -> 29400 | W92: =W76+W44+W60 -> 20962 | ... AA92: =AA76+AA44+AA60 -> 18 | AB92: =SUM(P92:AA92) -> 331304 | AD92: SP | AE92: =X96 -> 227291 | AF92: =AB92 -> 331304 | AG92: =AE92-AF92 -> -104013
O93: PR | P93: =P77+P45+P61 -> 0 | Q93: =Q77+Q45+Q61 -> 0 | R93: =R77+R45+R61 -> 0 | S93: =S77+S45+S61 -> 29 | T93: =T77+T45+T61 -> 0 | U93: =U77+U45+U61 -> 11 | V93: =V77+V45+V61 -> 0 | W93: =W77+W45+W61 -> 127 | ... AA93: =AA77+AA45+AA61 -> 0 | AB93: =SUM(P93:AA93) -> 3269 | AD93: PR | AE93: =Y96 -> 64999 | AF93: =AB93 -> 3269 | AG93: =AE93-AF93 -> 61730
O94: SC | P94: =P78+P46+P62 -> 36324 | Q94: =Q78+Q46+Q62 -> 0 | R94: =R78+R46+R62 -> 1666 | S94: =S78+S46+S62 -> 45197 | T94: =T78+T46+T62 -> 63792 | U94: =U78+U46+U62 -> 11283 | V94: =V78+V46+V62 -> 0 | W94: =W78+W46+W62 -> 3547 | ... AA94: =AA78+AA46+AA62 -> 22 | AB94: =SUM(P94:AA94) -> 176496 | AD94: SC | AE94: =Z96 -> 93457 | AF94: =AB94 -> 176496 | AG94: =AE94-AF94 -> -83039
O95: RS | P95: =P79+P47+P63 -> 5024 | Q95: =Q79+Q47+Q63 -> 0 | R95: =R79+R47+R63 -> 1488 | S95: =S79+S47+S63 -> 18257 | T95: =T79+T47+T63 -> 12652 | U95: =U79+U47+U63 -> 8901 | V95: =V79+V47+V63 -> 0 | W95: =W79+W47+W63 -> 34 | ... AA95: =AA79+AA47+AA63 -> 0 | AB95: =SUM(P95:AA95) -> 54377 | AD95: RS | AE95: =AA96 -> 6012 | AF95: =AB95 -> 54377 | AG95: =AE95-AF95 -> -48365
O96: Total Destino | P96: =SUM(P84:P95) -> 168494 | Q96: =SUM(Q84:Q95) -> 2475 | R96: =SUM(R84:R95) -> 6929 | S96: =SUM(S84:S95) -> 163464 | T96: =SUM(T84:T95) -> 184546 | U96: =SUM(U84:U95) -> 51698 | V96: =SUM(V84:V95) -> 74694 | W96: =SUM(W84:W95) -> 96792 | ... AB96: =SUM(AB84:AB95) -> 1140851 | AD96: Total | AE96: =SUM(AE84:AE95) -> 1140851 | AF96: =SUM(AF84:AF95) -> 1140851 | AG96: =ABS(AG84)+ABS(AG85)+ABS(AG86)+ABS(AG87)+ABS(AG88)+ABS(AG89)+ABS(AG90)+ABS(AG91)+ABS(AG92)+ABS(AG93)+ABS(AG94)+ABS(AG95) -> 531682
AA98: ABAC | AB98: 1251300 | AF98: Imbalance | AG98: =AG16+AG32+AG48+AG64 -> 431532
AA99: ANTAQ | AB99: =AB96 -> 1140851
AA100: Dif | AB100: =AB99-AB98 -> -110449
AA101: Dif % | AB101: =AB99/AB98-1 -> -0.088267402

Sheet PROSPECÇÃO VISUAL
B2: Movimentação de Contêineres na Cabotagem em 2022 - 20DC | P2: * feeder desconsiderado
B3: Origem/Destino | C3: AM | D3: PA | E3: MA | F3: CE | G3: PE | H3: BA | I3: ES | J3: RJ | K3: SP | L3: PR | M3: SC | N3: RS | O3: Total Origem | P3: *seleciondas as seis maiores movientações
B4: AM | E4: 1 | F4: 1747 | G4: 313 | H4: 329 | J4: 1002 | K4: 2513 | M4: 475 | N4: 19 | O4: =SUM(C4:N4) -> 6399
B5: PA | F5: 3833 | H5: 50 | K5: 3453 | M5: 33 | N5: 25 | O5: =SUM(C5:N5) -> 7394
B6: MA | F6: 9 | N6: 9 | O6: =SUM(C6:N6) -> 18
B7: CE | C7: 2926 | D7: 327 | E7: 22 | G7: 282 | H7: 491 | J7: 1239 | K7: 9135 | M7: 4055 | N7: 432 | O7: =SUM(C7:N7) -> 18909
B8: PE | C8: 2039 | E8: 1 | F8: 1481 | H8: 2967 | I8: 17 | J8: 1887 | K8: 8519 | L8: 1 | M8: 827 | N8: 264 | O8: =SUM(C8:N8) -> 18003
B9: BA | C9: 407 | F9: 779 | G9: 670 | I9: 11 | J9: 565 | K9: 10907 | L9: 56 | M9: 289 | N9: 145 | O9: =SUM(C9:N9) -> 13829
B10: ES | C10: 652 | G10: 39 | O10: =SUM(C10:N10) -> 691
B11: RJ | C11: 1770 | F11: 322 | G11: 517 | H11: 663 | O11: =SUM(C11:N11) -> 3272
B12: SP | C12: 4058 | E12: 31 | F12: 6369 | G12: 6570 | H12: 2077 | O12: =SUM(C12:N12) -> 19105
B13: PR | F13: 11 | H13: 11 | O13: =SUM(C13:N13) -> 22
B14: SC | C14: 1452 | E14: 346 | F14: 11836 | G14: 13601 | H14: 4203 | O14: =SUM(C14:N14) -> 31438
B15: RS | C15: 168 | E15: 1200 | F15: 8096 | G15: 5873 | H15: 3929 | O15: =SUM(C15:N15) -> 19266
B16: Total Destino | C16: =SUM(C4:C15) -> 13472 | D16: =SUM(D4:D15) -> 327 | E16: =SUM(E4:E15) -> 1601 | F16: =SUM(F4:F15) -> 34483 | G16: =SUM(G4:G15) -> 27865 | H16: =SUM(H4:H15) -> 14720 | I16: =SUM(I4:I15) -> 28 | J16: =SUM(J4:J15) -> 4693 | ... O16: =SUM(O4:O15) -> 138346
B18: Movimentação de Contêineres na Cabotagem em 2022 - 20RF
B19: Origem/Destino | C19: AM | D19: PA | E19: MA | F19: CE | G19: PE | H19: BA | I19: ES | J19: RJ | K19: SP | L19: PR | M19: SC | N19: RS | O19: Total Origem
B20: AM | G20: 1 | H20: 2 | O20: =SUM(C20:N20) -> 3
B21: PA | O21: =SUM(C21:N21) -> 0
B22: MA | O22: =SUM(C22:N22) -> 0
B23: CE | O23: =SUM(C23:N23) -> 0
B24: PE | F24: 3 | K24: 1 | M24: 4 | O24: =SUM(C24:N24) -> 8
B25: BA | F25: 4 | G25: 2 | K25: 2 | M25: 2 | O25: =SUM(C25:N25) -> 10
B26: ES | O26: =SUM(C26:N26) -> 0
B27: RJ | F27: 1 | O27: =SUM(C27:N27) -> 1
B28: SP | F28: 17 | G28: 16 | H28: 2 | O28: =SUM(C28:N28) -> 35
B29: PR | O29: =SUM(C29:N29) -> 0
B30: SC | F30: 7 | G30: 9 | O30: =SUM(C30:N30) -> 16
B31: RS | F31: 1 | G31: 1 | O31: =SUM(C31:N31) -> 2
B32: Total Destino | C32: =SUM(C20:C31) -> 0 | D32: =SUM(D20:D31) -> 0 | E32: =SUM(E20:E31) -> 0 | F32: =SUM(F20:F31) -> 33 | G32: =SUM(G20:G31) -> 29 | H32: =SUM(H20:H31) -> 4 | I32: =SUM(I20:I31) -> 0 | J32: =SUM(J20:J31) -> 0 | ... O32: =SUM(O20:O31) -> 75
B34: Movimentação de Contêineres na Cabotagem em 2022 - 40HC
B35: Origem/Destino | C35: AM | D35: PA | E35: MA | F35: CE | G35: PE | H35: BA | I35: ES | J35: RJ | K35: SP | L35: PR | M35: SC | N35: RS | O35: Total Origem
B36: AM | E36: 9 | F36: 6066 | G36: 8232 | H36: 3166 | J36: 7014 | K36: 54983 | L36: 3 | M36: 5501 | N36: 699 | O36: =SUM(C36:N36) -> 85673
B37: PA | F37: 1805 | H37: 4 | K37: 704 | M37: 92 | N37: 6 | O37: =SUM(C37:N37) -> 2611
B38: MA | F38: 51 | K38: 52 | N38: 3 | O38: =SUM(C38:N38) -> 106
B39: CE | C39: 10303 | D39: 985 | E39: 157 | G39: 2481 | H39: 101 | J39: 462 | K39: 7856 | M39: 3188 | N39: 366 | O39: =SUM(C39:N39) -> 25899
B40: PE | C40: 17515 | E40: 405 | F40: 5046 | H40: 652 | I40: 103 | J40: 1554 | K40: 9764 | M40: 4287 | N40: 963 | O40: =SUM(C40:N40) -> 40289
B41: BA | C41: 3252 | E41: 82 | F41: 2029 | G41: 1364 | I41: 58 | J41: 1612 | K41: 10648 | L41: 100 | M41: 2531 | N41: 490 | O41: =SUM(C41:N41) -> 22166
B42: ES | C42: 933 | G42: 11 | O42: =SUM(C42:N42) -> 944
B43: RJ | C43: 3272 | E43: 10 | F43: 1358 | G43: 5765 | H43: 3757 | O43: =SUM(C43:N43) -> 14162
B44: SP | C44: 18041 | D44: 1 | E44: 1087 | F44: 22859 | G44: 29225 | H44: 4383 | O44: =SUM(C44:N44) -> 75596
B45: PR | F45: 4 | O45: =SUM(C45:N45) -> 4
B46: SC | C46: 11210 | E46: 617 | F46: 13198 | G46: 20046 | H46: 2406 | O46: =SUM(C46:N46) -> 47477
B47: RS | C47: 2416 | E47: 144 | F47: 4975 | G47: 3247 | H47: 2483 | O47: =SUM(C47:N47) -> 13265
B48: Total Destino | C48: =SUM(C36:C47) -> 66942 | D48: =SUM(D36:D47) -> 986 | E48: =SUM(E36:E47) -> 2511 | F48: =SUM(F36:F47) -> 57391 | G48: =SUM(G36:G47) -> 70371 | H48: =SUM(H36:H47) -> 16952 | I48: =SUM(I36:I47) -> 161 | J48: =SUM(J36:J47) -> 10642 | ... O48: =SUM(O36:O47) -> 328192
B50: Movimentação de Contêineres na Cabotagem em 2022 - 40RH
B51: Origem/Destino | C51: AM | D51: PA | E51: MA | F51: CE | G51: PE | H51: BA | I51: ES | J51: RJ | K51: SP | L51: PR | M51: SC | N51: RS | O51: Total Origem
B52: AM | F52: 12 | G52: 6 | H52: 1 | J52: 35 | K52: 58 | M52: 46 | O52: =SUM(C52:N52) -> 158
B53: PA | F53: 368 | H53: 12 | K53: 122 | N53: 1 | O53: =SUM(C53:N53) -> 503
B54: MA | O54: =SUM(C54:N54) -> 0
B55: CE | C55: 155 | D55: 88 | E55: 24 | G55: 17 | H55: 2 | J55: 86 | K55: 215 | M55: 78 | O55: =SUM(C55:N55) -> 665
B56: PE | C56: 1593 | E56: 37 | F56: 407 | H56: 1 | J56: 13 | K56: 40 | L56: 4 | M56: 9 | O56: =SUM(C56:N56) -> 2104
B57: BA | C57: 214 | F57: 327 | G57: 339 | J57: 60 | K57: 644 | L57: 9 | M57: 24 | O57: =SUM(C57:N57) -> 1617
B58: ES | C58: 1 | O58: =SUM(C58:N58) -> 1
B59: RJ | C59: 60 | F59: 59 | G59: 138 | H59: 51 | O59: =SUM(C59:N59) -> 308
B60: SP | C60: 2308 | E60: 49 | F60: 2321 | G60: 2268 | H60: 331 | O60: =SUM(C60:N60) -> 7277
B61: PR | F61: 5 | O61: =SUM(C61:N61) -> 5
B62: SC | C62: 6226 | E62: 43 | F62: 3479 | G62: 5045 | H62: 1134 | O62: =SUM(C62:N62) -> 15927
B63: RS | C63: 12 | F63: 105 | G63: 142 | H63: 3 | O63: =SUM(C63:N63) -> 262
B64: Total Destino | C64: =SUM(C52:C63) -> 10569 | D64: =SUM(D52:D63) -> 88 | E64: =SUM(E52:E63) -> 153 | F64: =SUM(F52:F63) -> 7083 | G64: =SUM(G52:G63) -> 7955 | H64: =SUM(H52:H63) -> 1535 | I64: =SUM(I52:I63) -> 0 | J64: =SUM(J52:J63) -> 194 | ... O64: =SUM(O52:O63) -> 28827
B66: Movimentação de Contêineres na Cabotagem em 2022 - unidades
B67: Origem/Destino | C67: AM | D67: PA | E67: MA | F67: CE | G67: PE | H67: BA | I67: ES | J67: RJ | K67: SP | L67: PR | M67: SC | N67: RS | O67: Total Origem
B68: AM | C68: =C4+C20+C36+C52 -> 0 | D68: =D4+D20+D36+D52 -> 0 | E68: =E4+E20+E36+E52 -> 10 | F68: =F4+F20+F36+F52 -> 7825 | G68: =G4+G20+G36+G52 -> 8552 | H68: =H4+H20+H36+H52 -> 3498 | I68: =I4+I20+I36+I52 -> 0 | J68: =J4+J20+J36+J52 -> 8051 | ... N68: =N4+N20+N36+N52 -> 718 | O68: =SUM(C68:N68) -> 92233
B69: PA | C69: =C5+C21+C37+C53 -> 0 | D69: =D5+D21+D37+D53 -> 0 | E69: =E5+E21+E37+E53 -> 0 | F69: =F5+F21+F37+F53 -> 6006 | G69: =G5+G21+G37+G53 -> 0 | H69: =H5+H21+H37+H53 -> 66 | I69: =I5+I21+I37+I53 -> 0 | J69: =J5+J21+J37+J53 -> 0 | ... N69: =N5+N21+N37+N53 -> 32 | O69: =SUM(C69:N69) -> 10508
B70: MA | C70: =C6+C22+C38+C54 -> 0 | D70: =D6+D22+D38+D54 -> 0 | E70: =E6+E22+E38+E54 -> 0 | F70: =F6+F22+F38+F54 -> 60 | G70: =G6+G22+G38+G54 -> 0 | H70: =H6+H22+H38+H54 -> 0 | I70: =I6+I22+I38+I54 -> 0 | J70: =J6+J22+J38+J54 -> 0 | ... N70: =N6+N22+N38+N54 -> 12 | O70: =SUM(C70:N70) -> 124
B71: CE | C71: =C7+C23+C39+C55 -> 13384 | D71: =D7+D23+D39+D55 -> 1400 | E71: =E7+E23+E39+E55 -> 203 | F71: =F7+F23+F39+F55 -> 0 | G71: =G7+G23+G39+G55 -> 2780 | H71: =H7+H23+H39+H55 -> 594 | I71: =I7+I23+I39+I55 -> 0 | J71: =J7+J23+J39+J55 -> 1787 | ... N71: =N7+N23+N39+N55 -> 798 | O71: =SUM(C71:N71) -> 45473
B72: PE | C72: =C8+C24+C40+C56 -> 21147 | D72: =D8+D24+D40+D56 -> 0 | E72: =E8+E24+E40+E56 -> 443 | F72: =F8+F24+F40+F56 -> 6937 | G72: =G8+G24+G40+G56 -> 0 | H72: =H8+H24+H40+H56 -> 3620 | I72: =I8+I24+I40+I56 -> 120 | J72: =J8+J24+J40+J56 -> 3454 | ... N72: =N8+N24+N40+N56 -> 1227 | O72: =SUM(C72:N72) -> 60404
B73: BA | C73: =C9+C25+C41+C57 -> 3873 | D73: =D9+D25+D41+D57 -> 0 | E73: =E9+E25+E41+E57 -> 82 | F73: =F9+F25+F41+F57 -> 3139 | G73: =G9+G25+G41+G57 -> 2375 | H73: =H9+H25+H41+H57 -> 0 | I73: =I9+I25+I41+I57 -> 69 | J73: =J9+J25+J41+J57 -> 2237 | ... N73: =N9+N25+N41+N57 -> 635 | O73: =SUM(C73:N73) -> 37622
B74: ES | C74: =C10+C26+C42+C58 -> 1586 | D74: =D10+D26+D42+D58 -> 0 | E74: =E10+E26+E42+E58 -> 0 | F74: =F10+F26+F42+F58 -> 0 | G74: =G10+G26+G42+G58 -> 50 | H74: =H10+H26+H42+H58 -> 0 | O74: =SUM(C74:N74) -> 1636
B75: RJ | C75: =C11+C27+C43+C59 -> 5102 | D75: =D11+D27+D43+D59 -> 0 | E75: =E11+E27+E43+E59 -> 10 | F75: =F11+F27+F43+F59 -> 1740 | G75: =G11+G27+G43+G59 -> 6420 | H75: =H11+H27+H43+H59 -> 4471 | O75: =SUM(C75:N75) -> 17743
B76: SP | C76: =C12+C28+C44+C60 -> 24407 | D76: =D12+D28+D44+D60 -> 1 | E76: =E12+E28+E44+E60 -> 1167 | F76: =F12+F28+F44+F60 -> 31566 | G76: =G12+G28+G44+G60 -> 38079 | H76: =H12+H28+H44+H60 -> 6793 | O76: =SUM(C76:N76) -> 102013
B77: PR | C77: =C13+C29+C45+C61 -> 0 | D77: =D13+D29+D45+D61 -> 0 | E77: =E13+E29+E45+E61 -> 0 | F77: =F13+F29+F45+F61 -> 20 | G77: =G13+G29+G45+G61 -> 0 | H77: =H13+H29+H45+H61 -> 11 | O77: =SUM(C77:N77) -> 31
B78: SC | C78: =C14+C30+C46+C62 -> 18888 | D78: =D14+D30+D46+D62 -> 0 | E78: =E14+E30+E46+E62 -> 1006 | F78: =F14+F30+F46+F62 -> 28520 | G78: =G14+G30+G46+G62 -> 38701 | H78: =H14+H30+H46+H62 -> 7743 | O78: =SUM(C78:N78) -> 94858
B79: RS | C79: =C15+C31+C47+C63 -> 2596 | D79: =D15+D31+D47+D63 -> 0 | E79: =E15+E31+E47+E63 -> 1344 | F79: =F15+F31+F47+F63 -> 13177 | G79: =G15+G31+G47+G63 -> 9263 | H79: =H15+H31+H47+H63 -> 6415 | O79: =SUM(C79:N79) -> 32795
B80: Total Destino | C80: =SUM(C68:C79) -> 90983 | D80: =SUM(D68:D79) -> 1401 | E80: =SUM(E68:E79) -> 4265 | F80: =SUM(F68:F79) -> 98990 | G80: =SUM(G68:G79) -> 106220 | H80: =SUM(H68:H79) -> 33211 | I80: =SUM(I68:I79) -> 189 | J80: =SUM(J68:J79) -> 15529 | ... O80: =SUM(O68:O79) -> 495440
B82: Movimentação de Contêineres na Cabotagem em 2022 - TEU
B83: Origem/Destino | C83: AM | D83: PA | E83: MA | F83: CE | G83: PE | H83: BA | I83: ES | J83: RJ | K83: SP | L83: PR | M83: SC | N83: RS | O83: Total Origem
B84: AM | C84: =C68+C36+C52 -> 0 | D84: =D68+D36+D52 -> 0 | E84: =E68+E36+E52 -> 19 | F84: =F68+F36+F52 -> 13903 | G84: =G68+G36+G52 -> 16790 | H84: =H68+H36+H52 -> 6665 | I84: =I68+I36+I52 -> 0 | J84: =J68+J36+J52 -> 15100 | ... N84: =N68+N36+N52 -> 1417 | O84: =SUM(C84:N84) -> 178064
B85: PA | C85: =C69+C37+C53 -> 0 | D85: =D69+D37+D53 -> 0 | E85: =E69+E37+E53 -> 0 | F85: =F69+F37+F53 -> 8179 | G85: =G69+G37+G53 -> 0 | H85: =H69+H37+H53 -> 82 | I85: =I69+I37+I53 -> 0 | J85: =J69+J37+J53 -> 0 | ... N85: =N69+N37+N53 -> 39 | O85: =SUM(C85:N85) -> 13622
B86: MA | C86: =C70+C38+C54 -> 0 | D86: =D70+D38+D54 -> 0 | E86: =E70+E38+E54 -> 0 | F86: =F70+F38+F54 -> 111 | G86: =G70+G38+G54 -> 0 | H86: =H70+H38+H54 -> 0 | I86: =I70+I38+I54 -> 0 | J86: =J70+J38+J54 -> 0 | ... N86: =N70+N38+N54 -> 15 | O86: =SUM(C86:N86) -> 230
B87: CE | C87: =C71+C39+C55 -> 23842 | D87: =D71+D39+D55 -> 2473 | E87: =E71+E39+E55 -> 384 | F87: =F71+F39+F55 -> 0 | G87: =G71+G39+G55 -> 5278 | H87: =H71+H39+H55 -> 697 | I87: =I71+I39+I55 -> 0 | J87: =J71+J39+J55 -> 2335 | ... N87: =N71+N39+N55 -> 1164 | O87: =SUM(C87:N87) -> 72037
B88: PE | C88: =C72+C40+C56 -> 40255 | D88: =D72+D40+D56 -> 0 | E88: =E72+E40+E56 -> 885 | F88: =F72+F40+F56 -> 12390 | G88: =G72+G40+G56 -> 0 | H88: =H72+H40+H56 -> 4273 | I88: =I72+I40+I56 -> 223 | J88: =J72+J40+J56 -> 5021 | ... N88: =N72+N40+N56 -> 2190 | O88: =SUM(C88:N88) -> 102797
B89: BA | C89: =C73+C41+C57 -> 7339 | D89: =D73+D41+D57 -> 0 | E89: =E73+E41+E57 -> 164 | F89: =F73+F41+F57 -> 5495 | G89: =G73+G41+G57 -> 4078 | H89: =H73+H41+H57 -> 0 | I89: =I73+I41+I57 -> 127 | J89: =J73+J41+J57 -> 3909 | ... N89: =N73+N41+N57 -> 1125 | O89: =SUM(C89:N89) -> 61405
B90: ES | C90: =C74+C42+C58 -> 2520 | D90: =D74+D42+D58 -> 0 | E90: =E74+E42+E58 -> 0 | F90: =F74+F42+F58 -> 0 | G90: =G74+G42+G58 -> 61 | H90: =H74+H42+H58 -> 0 | O90: =SUM(C90:N90) -> 2581
B91: RJ | C91: =C75+C43+C59 -> 8434 | D91: =D75+D43+D59 -> 0 | E91: =E75+E43+E59 -> 20 | F91: =F75+F43+F59 -> 3157 | G91: =G75+G43+G59 -> 12323 | H91: =H75+H43+H59 -> 8279 | O91: =SUM(C91:N91) -> 32213
B92: SP | C92: =C76+C44+C60 -> 44756 | D92: =D76+D44+D60 -> 2 | E92: =E76+E44+E60 -> 2303 | F92: =F76+F44+F60 -> 56746 | G92: =G76+G44+G60 -> 69572 | H92: =H76+H44+H60 -> 11507 | O92: =SUM(C92:N92) -> 184886
B93: PR | C93: =C77+C45+C61 -> 0 | D93: =D77+D45+D61 -> 0 | E93: =E77+E45+E61 -> 0 | F93: =F77+F45+F61 -> 29 | G93: =G77+G45+G61 -> 0 | H93: =H77+H45+H61 -> 11 | O93: =SUM(C93:N93) -> 40
B94: SC | C94: =C78+C46+C62 -> 36324 | D94: =D78+D46+D62 -> 0 | E94: =E78+E46+E62 -> 1666 | F94: =F78+F46+F62 -> 45197 | G94: =G78+G46+G62 -> 63792 | H94: =H78+H46+H62 -> 11283 | O94: =SUM(C94:N94) -> 158262
B95: RS | C95: =C79+C47+C63 -> 5024 | D95: =D79+D47+D63 -> 0 | E95: =E79+E47+E63 -> 1488 | F95: =F79+F47+F63 -> 18257 | G95: =G79+G47+G63 -> 12652 | H95: =H79+H47+H63 -> 8901 | O95: =SUM(C95:N95) -> 46322
B96: Total Destino | C96: =SUM(C84:C95) -> 168494 | D96: =SUM(D84:D95) -> 2475 | E96: =SUM(E84:E95) -> 6929 | F96: =SUM(F84:F95) -> 163464 | G96: =SUM(G84:G95) -> 184546 | H96: =SUM(H84:H95) -> 51698 | I96: =SUM(I84:I95) -> 350 | J96: =SUM(J84:J95) -> 26365 | ... O96: =SUM(O84:O95) -> 852459

Sheet OTIMIZAÇÃO ROTA
B2: ANUAL | K2: SEMANAL | T2: OTIMIZAÇÃO SEMANAL
B4: Movimentação de Contêineres na Cabotagem em 2022 - 20DC | K4: Movimentação de Contêineres na Cabotagem em 2022 - 20DC | T4: Movimentação de Contêineres na Cabotagem em 2022 - 20DC | AC4: Imbalance 20DC
B5: Origem/Destino | C5: AM | D5: CE | E5: PE | F5: BA | G5: SP | H5: SC | I5: Total Origem | K5: Origem/Destino | L5: AM | M5: CE | N5: PE | O5: BA | P5: BA | Q5: SC | R5: Total Origem | T5: Origem/Destino | U5: AM | V5: CE | W5: PE | X5: BA | Y5: BA | Z5: SC | AA5: Total Origem | AC5: Porto | AD5: IMB
B6: AM | D6: 1747 | E6: 313 | F6: 329 | G6: 2513 | H6: 475 | I6: =SUM(C6:H6) -> 5377 | K6: AM | L6: =INT(C6/52) -> 0 | M6: =INT(D6/52) -> 33 | N6: =INT(E6/52) -> 6 | O6: =INT(F6/52) -> 6 | P6: =INT(G6/52) -> 48 | Q6: =INT(H6/52) -> 9 | R6: =SUM(L6:Q6) -> 102 | T6: AM | U6: =L6*C108 -> 0 | V6: =M6*D108 -> 0 | W6: =N6*E108 -> 0.81895122 | X6: =O6*F108 -> 2.7849436 | Y6: =P6*G108 -> 44.217729 | Z6: =Q6*H108 -> 9 | AA6: =SUM(U6:Z6) -> 56.821623 | AC6: AM | AD6: =U12-$AA6 -> 37.958645 | AE6: =INT(ABS(AD6)) -> 37
B7: CE | C7: 2926 | E7: 282 | F7: 491 | G7: 9135 | H7: 4055 | I7: =SUM(C7:H7) -> 16889 | K7: CE | L7: =INT(C7/52) -> 56 | M7: =INT(D7/52) -> 0 | N7: =INT(E7/52) -> 5 | O7: =INT(F7/52) -> 9 | P7: =INT(G7/52) -> 175 | Q7: =INT(H7/52) -> 77 | R7: =SUM(L7:Q7) -> 322 | T7: CE | U7: =L7*C109 -> 55.93375 | V7: =M7*D109 -> 0 | W7: =N7*E109 -> 0.043691546 | X7: =O7*F109 -> 0.61850281 | Y7: =P7*G109 -> 60.251994 | Z7: =Q7*H109 -> 8.4569942 | AA7: =SUM(U7:Z7) -> 125.30493 | AC7: CE | AD7: =V12-$AA7 -> 50.574646 | AE7: =INT(ABS(AD7)) -> 50
B8: PE | C8: 2039 | D8: 1481 | F8: 2967 | G8: 8519 | H8: 827 | I8: =SUM(C8:H8) -> 15833 | K8: PE | L8: =INT(C8/52) -> 39 | M8: =INT(D8/52) -> 28 | N8: =INT(E8/52) -> 0 | O8: =INT(F8/52) -> 57 | P8: =INT(G8/52) -> 163 | Q8: =INT(H8/52) -> 15 | R8: =SUM(L8:Q8) -> 302 | T8: PE | U8: =L8*C110 -> 20.577729 | V8: =M8*D110 -> 15.484659 | W8: =N8*E110 -> 0 | X8: =O8*F110 -> 0.15833686 | Y8: =P8*G110 -> 11.965206 | Z8: =Q8*H110 -> 5.6074985 | AA8: =SUM(U8:Z8) -> 53.793429 | AC8: PE | AD8: =W12-$AA8 -> 92.156857 | AE8: =INT(ABS(AD8)) -> 92
B9: BA | C9: 407 | D9: 779 | E9: 670 | G9: 10907 | H9: 289 | I9: =SUM(C9:H9) -> 13052 | K9: BA | L9: =INT(C9/52) -> 7 | M9: =INT(D9/52) -> 14 | N9: =INT(E9/52) -> 12 | O9: =INT(F9/52) -> 0 | P9: =INT(G9/52) -> 209 | Q9: =INT(H9/52) -> 5 | R9: =SUM(L9:Q9) -> 247 | T9: BA | U9: =L9*C111 -> 3.2302311 | V9: =M9*D111 -> 12.869471 | W9: =N9*E111 -> 11.532832 | X9: =O9*F111 -> 0 | Y9: =P9*G111 -> 0.37267313 | Z9: =Q9*H111 -> 1.4489955 | AA9: =SUM(U9:Z9) -> 29.454203 | AC9: BA | AD9: =X12-$AA9 -> 31.832372 | AE9: =INT(ABS(AD9)) -> 31
B10: SP | C10: 4058 | D10: 6369 | E10: 6570 | F10: 2077 | I10: =SUM(C10:H10) -> 19074 | K10: SP | L10: =INT(C10/52) -> 78 | M10: =INT(D10/52) -> 122 | N10: =INT(E10/52) -> 126 | O10: =INT(F10/52) -> 39 | P10: =INT(G10/52) -> 0 | Q10: =INT(H10/52) -> 0 | R10: =SUM(L10:Q10) -> 365 | T10: SP | U10: =L10*C112 -> 9.9234402 | V10: =M10*D112 -> 39.644032 | W10: =N10*E112 -> 40.220281 | X10: =O10*F112 -> 29.406625 | Y10: =P10*G112 -> 0 | Z10: =Q10*H112 -> 0 | AA10: =SUM(U10:Z10) -> 119.19438 | AC10: SP | AD10: =Y12-$AA10 -> -2.3867767 | AE10: =INT(ABS(AD10)) -> 2
B11: SC | C11: 1452 | D11: 11836 | E11: 13601 | F11: 4203 | I11: =SUM(C11:H11) -> 31092 | K11: SC | L11: =INT(C11/52) -> 27 | M11: =INT(D11/52) -> 227 | N11: =INT(E11/52) -> 261 | O11: =INT(F11/52) -> 80 | P11: =INT(G11/52) -> 0 | Q11: =INT(H11/52) -> 0 | R11: =SUM(L11:Q11) -> 595 | T11: SC | U11: =L11*C113 -> 5.1151187 | V11: =M11*D113 -> 107.88142 | W11: =N11*E113 -> 93.33453 | X11: =O11*F113 -> 28.318167 | Y11: =P11*G113 -> 0 | Z11: =Q11*H113 -> 0 | AA11: =SUM(U11:Z11) -> 234.64923 | AC11: SC | AD11: =Z12-$AA11 -> -210.13574 | AE11: =INT(ABS(AD11)) -> 210
B12: Total Destino | C12: =SUM(C6:C11) -> 10882 | D12: =SUM(D6:D11) -> 22212 | E12: =SUM(E6:E11) -> 21436 | F12: =SUM(F6:F11) -> 10067 | G12: =SUM(G6:G11) -> 31074 | H12: =SUM(H6:H11) -> 5646 | I12: =SUM(I6:I11) -> 101317 | K12: Total Destino | L12: =SUM(L6:L11) -> 207 | M12: =SUM(M6:M11) -> 424 | N12: =SUM(N6:N11) -> 410 | O12: =SUM(O6:O11) -> 191 | P12: =SUM(P6:P11) -> 595 | Q12: =SUM(Q6:Q11) -> 106 | R12: =SUM(R6:R11) -> 1933 | T12: Total Destino | U12: =SUM(U6:U11) -> 94.780269 | V12: =SUM(V6:V11) -> 175.87958 | W12: =SUM(W6:W11) -> 145.95029 | X12: =SUM(X6:X11) -> 61.286575 | Y12: =SUM(Y6:Y11) -> 116.8076 | Z12: =SUM(Z6:Z11) -> 24.513488 | AA12: =SUM(AA6:AA11) -> 619.2178 | AC12: Total | AD12: =SUM(AD6:AD11) -> 0
B14: Movimentação de Contêineres na Cabotagem em 2022 - 20RF | K14: Movimentação de Contêineres na Cabotagem em 2022 - 20RF | T14: Movimentação de Contêineres na Cabotagem em 2022 - 20RF | AC14: Imbalance 20RF
B15: Origem/Destino | C15: AM | D15: CE | E15: PE | F15: BA | G15: SP | H15: SC | I15: Total Origem | K15: Origem/Destino | L15: AM | M15: CE | N15: PE | O15: BA | P15: SP | Q15: SC | R15: Total Origem | T15: Origem/Destino | U15: AM | V15: CE | W15: PE | X15: BA | Y15: SP | Z15: SC | AA15: Total Origem | AC15: Porto | AD15: IMB
B16: AM | E16: 1 | F16: 2 | I16: =SUM(C16:H16) -> 3 | K16: AM | L16: =C16/52 -> 0 | M16: =D16/52 -> 0 | N16: =E16/52 -> 0.019230769 | O16: =F16/52 -> 0.038461538 | P16: =G16/52 -> 0 | Q16: =H16/52 -> 0 | R16: =SUM(L16:Q16) -> 0.057692308 | T16: AM | U16: =L16*C108 -> 0 | V16: =M16*D108 -> 0 | W16: =N16*E108 -> 0.0026248436 | X16: =O16*F108 -> 0.017852202 | Y16: =P16*G108 -> 0 | Z16: =Q16*H108 -> 0 | AA16: =SUM(U16:Z16) -> 0.020477046 | AC16: AM | AD16: =U22-$AA16 -> -0.020477046
B17: CE | I17: =SUM(C17:H17) -> 0 | K17: CE | L17: =C17/52 -> 0 | M17: =D17/52 -> 0 | N17: =E17/52 -> 0 | O17: =F17/52 -> 0 | P17: =G17/52 -> 0 | Q17: =H17/52 -> 0 | R17: =SUM(L17:Q17) -> 0 | T17: CE | U17: =L17*C109 -> 0 | V17: =M17*D109 -> 0 | W17: =N17*E109 -> 0 | X17: =O17*F109 -> 0 | Y17: =P17*G109 -> 0 | Z17: =Q17*H109 -> 0 | AA17: =SUM(U17:Z17) -> 0 | AC17: CE | AD17: =V22-$AA17 -> 0.27282636
B18: PE | D18: 3 | G18: 1 | H18: 4 | I18: =SUM(C18:H18) -> 8 | K18: PE | L18: =C18/52 -> 0 | M18: =D18/52 -> 0.057692308 | N18: =E18/52 -> 0 | O18: =F18/52 -> 0 | P18: =G18/52 -> 0.019230769 | Q18: =H18/52 -> 0.076923077 | R18: =SUM(L18:Q18) -> 0.15384615 | T18: PE | U18: =L18*C110 -> 0 | V18: =M18*D110 -> 0.031905204 | W18: =N18*E110 -> 0 | X18: =O18*F110 -> 0 | Y18: =P18*G110 -> 0.0014116572 | Z18: =Q18*H110 -> 0.028756403 | AA18: =SUM(U18:Z18) -> 0.062073264 | AC18: PE | AD18: =W22-$AA18 -> 0.13762674
B19: RJ | D19: 4 | E19: 2 | G19: 2 | H19: 2 | I19: =SUM(C19:H19) -> 10 | K19: BA | L19: =C19/52 -> 0 | M19: =D19/52 -> 0.076923077 | N19: =E19/52 -> 0.038461538 | O19: =F19/52 -> 0 | P19: =G19/52 -> 0.038461538 | Q19: =H19/52 -> 0.038461538 | R19: =SUM(L19:Q19) -> 0.19230769 | T19: BA | U19: =L19*C111 -> 0 | V19: =M19*D111 -> 0.070711381 | W19: =N19*E111 -> 0.036964205 | X19: =O19*F111 -> 0 | Y19: =P19*G111 -> 6.8581732e-05 | Z19: =Q19*H111 -> 0.01114612 | AA19: =SUM(U19:Z19) -> 0.11889029 | AC19: BA | AD19: =X22-$AA19 -> -0.072037469
B20: SP | D20: 17 | E20: 16 | F20: 2 | I20: =SUM(C20:H20) -> 35 | K20: SP | L20: =C20/52 -> 0 | M20: =D20/52 -> 0.32692308 | N20: =E20/52 -> 0.30769231 | O20: =F20/52 -> 0.038461538 | P20: =G20/52 -> 0 | Q20: =H20/52 -> 0 | R20: =SUM(L20:Q20) -> 0.67307692 | T20: SP | U20: =L20*C112 -> 0 | V20: =M20*D112 -> 0.10623401 | W20: =N20*E112 -> 0.098218025 | X20: =O20*F112 -> 0.029000616 | Y20: =P20*G112 -> 0 | Z20: =Q20*H112 -> 0 | AA20: =SUM(U20:Z20) -> 0.23345265 | AC20: SP | AD20: =Y22-$AA20 -> -0.23197241
B21: SC | D21: 7 | E21: 9 | I21: =SUM(C21:H21) -> 16 | K21: SC | L21: =C21/52 -> 0 | M21: =D21/52 -> 0.13461538 | N21: =E21/52 -> 0.17307692 | O21: =F21/52 -> 0 | P21: =G21/52 -> 0 | Q21: =H21/52 -> 0 | R21: =SUM(L21:Q21) -> 0.30769231 | T21: SC | U21: =L21*C113 -> 0 | V21: =M21*D113 -> 0.063975764 | W21: =N21*E113 -> 0.061892925 | X21: =O21*F113 -> 0 | Y21: =P21*G113 -> 0 | Z21: =Q21*H113 -> 0 | AA21: =SUM(U21:Z21) -> 0.12586869 | AC21: SC | AD21: =Z22-$AA21 -> -0.085966166
B22: Total Destino | C22: =SUM(C16:C21) -> 0 | D22: =SUM(D16:D21) -> 31 | E22: =SUM(E16:E21) -> 28 | F22: =SUM(F16:F21) -> 4 | G22: =SUM(G16:G21) -> 3 | H22: =SUM(H16:H21) -> 6 | I22: =SUM(I16:I21) -> 72 | K22: Total Destino | L22: =SUM(L16:L21) -> 0 | M22: =SUM(M16:M21) -> 0.59615385 | N22: =SUM(N16:N21) -> 0.53846154 | O22: =SUM(O16:O21) -> 0.076923077 | P22: =SUM(P16:P21) -> 0.057692308 | Q22: =SUM(Q16:Q21) -> 0.11538462 | R22: =SUM(R16:R21) -> 1.3846154 | T22: Total Destino | U22: =SUM(U16:U21) -> 0 | V22: =SUM(V16:V21) -> 0.27282636 | W22: =SUM(W16:W21) -> 0.1997 | X22: =SUM(X16:X21) -> 0.046852819 | Y22: =SUM(Y16:Y21) -> 0.0014802389 | Z22: =SUM(Z16:Z21) -> 0.039902522 | AA22: =SUM(AA16:AA21) -> 0.56076193 | AC22: Total | AD22: =SUM(AD16:AD21) -> 0
B24: Movimentação de Contêineres na Cabotagem em 2022 - 40HC | K24: Movimentação de Contêineres na Cabotagem em 2022 - 40HC | T24: Movimentação de Contêineres na Cabotagem em 2022 - 40HC | AC24: Imbalance 40HC
B25: Origem/Destino | C25: AM | D25: CE | E25: PE | F25: BA | G25: SP | H25: SC | I25: Total Origem | K25: Origem/Destino | L25: AM | M25: CE | N25: PE | O25: BA | P25: SP | Q25: SC | R25: Total Origem | T25: Origem/Destino | U25: AM | V25: CE | W25: PE | X25: BA | Y25: SP | Z25: SC | AA25: Total Origem | AC25: Porto | AD25: IMB
B26: AM | D26: 6066 | E26: 8232 | F26: 3166 | G26: 54983 | H26: 5501 | I26: =SUM(C26:H26) -> 77948 | K26: AM | L26: =INT(C26/52) -> 0 | M26: =INT(D26/52) -> 116 | N26: =INT(E26/52) -> 158 | O26: =INT(F26/52) -> 60 | P26: =INT(G26/52) -> 1057 | Q26: =INT(H26/52) -> 105 | R26: =SUM(L26:Q26) -> 1496 | T26: AM | U26: =L26*C108 -> 0 | V26: =M26*D108 -> 0 | W26: =N26*E108 -> 21.565715 | X26: =O26*F108 -> 27.849436 | Y26: =P26*G108 -> 973.71123 | Z26: =Q26*H108 -> 105 | AA26: =SUM(U26:Z26) -> 1128.1264 | AC26: AM | AD26: =U32-$AA26 -> -639.71409 | AE26: =INT(ABS(AD26)) -> 639
B27: CE | C27: 10303 | E27: 2481 | F27: 101 | G27: 7856 | H27: 3188 | I27: =SUM(C27:H27) -> 23929 | K27: CE | L27: =INT(C27/52) -> 198 | M27: =INT(D27/52) -> 0 | N27: =INT(E27/52) -> 47 | O27: =INT(F27/52) -> 1 | P27: =INT(G27/52) -> 151 | Q27: =INT(H27/52) -> 61 | R27: =SUM(L27:Q27) -> 458 | T27: CE | U27: =L27*C109 -> 197.76576 | V27: =M27*D109 -> 0 | W27: =N27*E109 -> 0.41070053 | X27: =O27*F109 -> 0.068722534 | Y27: =P27*G109 -> 51.988863 | Z27: =Q27*H109 -> 6.6996967 | AA27: =SUM(U27:Z27) -> 256.93374 | AC27: CE | AD27: =V32-$AA27 -> 95.451613 | AE27: =INT(ABS(AD27)) -> 95
B28: PE | C28: 17515 | D28: 5046 | F28: 652 | G28: 9764 | H28: 4287 | I28: =SUM(C28:H28) -> 37264 | K28: PE | L28: =INT(C28/52) -> 336 | M28: =INT(D28/52) -> 97 | N28: =INT(E28/52) -> 0 | O28: =INT(F28/52) -> 12 | P28: =INT(G28/52) -> 187 | Q28: =INT(H28/52) -> 82 | R28: =SUM(L28:Q28) -> 714 | T28: PE | U28: =L28*C110 -> 177.28505 | V28: =M28*D110 -> 53.643283 | W28: =N28*E110 -> 0 | X28: =O28*F110 -> 0.033334076 | Y28: =P28*G110 -> 13.726955 | Z28: =Q28*H110 -> 30.654325 | AA28: =SUM(U28:Z28) -> 275.34294 | AC28: PE | AD28: =W32-$AA28 -> 88.693871 | AE28: =INT(ABS(AD28)) -> 88
B29: BA | C29: 3252 | D29: 2029 | E29: 1364 | G29: 10648 | H29: 2531 | I29: =SUM(C29:H29) -> 19824 | K29: BA | L29: =INT(C29/52) -> 62 | M29: =INT(D29/52) -> 39 | N29: =INT(E29/52) -> 26 | O29: =INT(F29/52) -> 0 | P29: =INT(G29/52) -> 204 | Q29: =INT(H29/52) -> 48 | R29: =SUM(L29:Q29) -> 379 | T29: BA | U29: =L29*C111 -> 28.610618 | V29: =M29*D111 -> 35.85067 | W29: =N29*E111 -> 24.987803 | X29: =O29*F111 -> 0 | Y29: =P29*G111 -> 0.36375751 | Z29: =Q29*H111 -> 13.910357 | AA29: =SUM(U29:Z29) -> 103.72321 | AC29: BA | AD29: =X32-$AA29 -> 3.8485788 | AE29: =INT(ABS(AD29)) -> 3
B30: SP | C30: 18041 | D30: 22859 | E30: 29225 | F30: 4383 | I30: =SUM(C30:H30) -> 74508 | K30: SP | L30: =INT(C30/52) -> 346 | M30: =INT(D30/52) -> 439 | N30: =INT(E30/52) -> 562 | O30: =INT(F30/52) -> 84 | P30: =INT(G30/52) -> 0 | Q30: =INT(H30/52) -> 0 | R30: =SUM(L30:Q30) -> 1431 | T30: SP | U30: =L30*C112 -> 44.019363 | V30: =M30*D112 -> 142.65352 | W30: =N30*E112 -> 179.39522 | X30: =O30*F112 -> 63.337346 | Y30: =P30*G112 -> 0 | Z30: =Q30*H112 -> 0 | AA30: =SUM(U30:Z30) -> 429.40546 | AC30: SP | AD30: =Y32-$AA30 -> 610.38535 | AE30: =INT(ABS(AD30)) -> 610
B31: SC | C31: 11210 | D31: 13198 | E31: 20046 | F31: 2406 | I31: =SUM(C31:H31) -> 46860 | K31: SC | L31: =INT(C31/52) -> 215 | M31: =INT(D31/52) -> 253 | N31: =INT(E31/52) -> 385 | O31: =INT(F31/52) -> 46 | P31: =INT(G31/52) -> 0 | Q31: =INT(H31/52) -> 0 | R31: =SUM(L31:Q31) -> 899 | T31: SC | U31: =L31*C113 -> 40.731501 | V31: =M31*D113 -> 120.23788 | W31: =N31*E113 -> 137.67737 | X31: =O31*F113 -> 16.282946 | Y31: =P31*G113 -> 0 | Z31: =Q31*H113 -> 0 | AA31: =SUM(U31:Z31) -> 314.9297 | AC31: SC | AD31: =Z32-$AA31 -> -158.66532 | AE31: =INT(ABS(AD31)) -> 158
B32: Total Destino | C32: =SUM(C26:C31) -> 60321 | D32: =SUM(D26:D31) -> 49198 | E32: =SUM(E26:E31) -> 61348 | F32: =SUM(F26:F31) -> 10708 | G32: =SUM(G26:G31) -> 83251 | H32: =SUM(H26:H31) -> 15507 | I32: =SUM(I26:I31) -> 280333 | K32: Total Destino | L32: =SUM(L26:L31) -> 1157 | M32: =SUM(M26:M31) -> 944 | N32: =SUM(N26:N31) -> 1178 | O32: =SUM(O26:O31) -> 203 | P32: =SUM(P26:P31) -> 1599 | Q32: =SUM(Q26:Q31) -> 296 | R32: =SUM(R26:R31) -> 5377 | T32: Total Destino | U32: =SUM(U26:U31) -> 488.41229 | V32: =SUM(V26:V31) -> 352.38536 | W32: =SUM(W26:W31) -> 364.03681 | X32: =SUM(X26:X31) -> 107.57178 | Y32: =SUM(Y26:Y31) -> 1039.7908 | Z32: =SUM(Z26:Z31) -> 156.26438 | AA32: =SUM(AA26:AA31) -> 2508.4614 | AC32: Total | AD32: =SUM(AD26:AD31) -> 0
B34: Movimentação de Contêineres na Cabotagem em 2022 - 40RH | K34: Movimentação de Contêineres na Cabotagem em 2022 - 40RH | T34: Movimentação de Contêineres na Cabotagem em 2022 - 40RH | AC34: Imbalance 40RH
B35: Origem/Destino | C35: AM | D35: CE | E35: PE | F35: BA | G35: SP | H35: SC | I35: Total Origem | K35: Origem/Destino | L35: AM | M35: CE | N35: PE | O35: BA | P35: SP | Q35: SC | R35: Total Origem | T35: Origem/Destino | U35: AM | V35: CE | W35: PE | X35: BA | Y35: SP | Z35: SC | AA35: Total Origem | AC35: Porto | AD35: IMB
B36: AM | D36: 12 | E36: 6 | F36: 1 | G36: 58 | H36: 46 | I36: =SUM(C36:H36) -> 123 | K36: AM | L36: =INT(C36/52) -> 0 | M36: =INT(D36/52) -> 0 | N36: =INT(E36/52) -> 0 | O36: =INT(F36/52) -> 0 | P36: =INT(G36/52) -> 1 | Q36: =INT(H36/52) -> 0 | R36: =SUM(L36:Q36) -> 1 | T36: AM | U36: =L36*C108 -> 0 | V36: =M36*D108 -> 0 | W36: =N36*E108 -> 0 | X36: =O36*F108 -> 0 | Y36: =P36*G108 -> 0.92120268 | Z36: =Q36*H108 -> 0 | AA36: =SUM(U36:Z36) -> 0.92120268 | AC36: AM | AD36: =U42-$AA36 -> 46.89355 | AE36: =INT(ABS(AD36)) -> 46
B37: CE | C37: 155 | E37: 17 | F37: 2 | G37: 215 | H37: 78 | I37: =SUM(C37:H37) -> 467 | K37: CE | L37: =INT(C37/52) -> 2 | M37: =INT(D37/52) -> 0 | N37: =INT(E37/52) -> 0 | O37: =INT(F37/52) -> 0 | P37: =INT(G37/52) -> 4 | Q37: =INT(H37/52) -> 1 | R37: =SUM(L37:Q37) -> 7 | T37: CE | U37: =L37*C109 -> 1.9976339 | V37: =M37*D109 -> 0 | W37: =N37*E109 -> 0 | X37: =O37*F109 -> 0 | Y37: =P37*G109 -> 1.3771884 | Z37: =Q37*H109 -> 0.10983109 | AA37: =SUM(U37:Z37) -> 3.4846534 | AC37: CE | AD37: =V42-$AA37 -> 51.56625 | AE37: =INT(ABS(AD37)) -> 51
B38: PE | C38: 1593 | D38: 407 | F38: 1 | G38: 40 | H38: 9 | I38: =SUM(C38:H38) -> 2050 | K38: PE | L38: =INT(C38/52) -> 30 | M38: =INT(D38/52) -> 7 | N38: =INT(E38/52) -> 0 | O38: =INT(F38/52) -> 0 | P38: =INT(G38/52) -> 0 | Q38: =INT(H38/52) -> 0 | R38: =SUM(L38:Q38) -> 37 | T38: PE | U38: =L38*C110 -> 15.829022 | V38: =M38*D110 -> 3.8711647 | W38: =N38*E110 -> 0 | X38: =O38*F110 -> 0 | Y38: =P38*G110 -> 0 | Z38: =Q38*H110 -> 0 | AA38: =SUM(U38:Z38) -> 19.700187 | AC38: PE | AD38: =W42-$AA38 -> 34.479744 | AE38: =INT(ABS(AD38)) -> 34
B39: BA | C39: 214 | D39: 327 | E39: 339 | G39: 644 | H39: 24 | I39: =SUM(C39:H39) -> 1548 | K39: BA | L39: =INT(C39/52) -> 4 | M39: =INT(D39/52) -> 6 | N39: =INT(E39/52) -> 6 | O39: =INT(F39/52) -> 0 | P39: =INT(G39/52) -> 12 | Q39: =INT(H39/52) -> 0 | R39: =SUM(L39:Q39) -> 28 | T39: BA | U39: =L39*C111 -> 1.8458463 | V39: =M39*D111 -> 5.5154877 | W39: =N39*E111 -> 5.766416 | X39: =O39*F111 -> 0 | Y39: =P39*G111 -> 0.0213975 | Z39: =Q39*H111 -> 0 | AA39: =SUM(U39:Z39) -> 13.149148 | AC39: BA | AD39: =X42-$AA39 -> -1.1915325 | AE39: =INT(ABS(AD39)) -> 1
B40: SP | C40: 2308 | D40: 2321 | E40: 2268 | F40: 331 | I40: =SUM(C40:H40) -> 7228 | K40: SP | L40: =INT(C40/52) -> 44 | M40: =INT(D40/52) -> 44 | N40: =INT(E40/52) -> 43 | O40: =INT(F40/52) -> 6 | P40: =INT(G40/52) -> 0 | Q40: =INT(H40/52) -> 0 | R40: =SUM(L40:Q40) -> 137 | T40: SP | U40: =L40*C112 -> 5.5978381 | V40: =M40*D112 -> 14.297847 | W40: =N40*E112 -> 13.725969 | X40: =O40*F112 -> 4.5240962 | Y40: =P40*G112 -> 0 | Z40: =Q40*H112 -> 0 | AA40: =SUM(U40:Z40) -> 38.145751 | AC40: SP | AD40: =Y42-$AA40 -> -35.825962 | AE40: =INT(ABS(AD40)) -> 35
B41: SC | C41: 6226 | D41: 3479 | E41: 5045 | F41: 1134 | I41: =SUM(C41:H41) -> 15884 | K41: SC | L41: =INT(C41/52) -> 119 | M41: =INT(D41/52) -> 66 | N41: =INT(E41/52) -> 97 | O41: =INT(F41/52) -> 21 | P41: =INT(G41/52) -> 0 | Q41: =INT(H41/52) -> 0 | R41: =SUM(L41:Q41) -> 303 | T41: SC | U41: =L41*C113 -> 22.544412 | V41: =M41*D113 -> 31.366403 | W41: =N41*E113 -> 34.687546 | X41: =O41*F113 -> 7.4335189 | Y41: =P41*G113 -> 0 | Z41: =Q41*H113 -> 0 | AA41: =SUM(U41:Z41) -> 96.03188 | AC41: SC | AD41: =Z42-$AA41 -> -95.922049 | AE41: =INT(ABS(AD41)) -> 95
B42: Total Destino | C42: =SUM(C36:C41) -> 10496 | D42: =SUM(D36:D41) -> 6546 | E42: =SUM(E36:E41) -> 7675 | F42: =SUM(F36:F41) -> 1469 | G42: =SUM(G36:G41) -> 957 | H42: =SUM(H36:H41) -> 157 | I42: =SUM(I36:I41) -> 27300 | K42: Total Destino | L42: =SUM(L36:L41) -> 199 | M42: =SUM(M36:M41) -> 123 | N42: =SUM(N36:N41) -> 146 | O42: =SUM(O36:O41) -> 27 | P42: =SUM(P36:P41) -> 17 | Q42: =SUM(Q36:Q41) -> 1 | R42: =SUM(R36:R41) -> 513 | T42: Total Destino | U42: =SUM(U36:U41) -> 47.814752 | V42: =SUM(V36:V41) -> 55.050903 | W42: =SUM(W36:W41) -> 54.179931 | X42: =SUM(X36:X41) -> 11.957615 | Y42: =SUM(Y36:Y41) -> 2.3197886 | Z42: =SUM(Z36:Z41) -> 0.10983109 | AA42: =SUM(AA36:AA41) -> 171.43282 | AC42: Total | AD42: =SUM(AD36:AD41) -> 0
B44: Movimentação de Contêineres na Cabotagem em 2022 - unidades | K44: Movimentação de Contêineres na Cabotagem em 2022 - unidades
B45: Origem/Destino | C45: AM | D45: CE | E45: PE | F45: BA | G45: SP | H45: SC | I45: Total Origem | K45: Origem/Destino | L45: AM | M45: CE | N45: PE | O45: BA | P45: SP | Q45: SC | R45: Total Origem
B46: AM | C46: =C6+C16+C26+C36 -> 0 | D46: =D6+D16+D26+D36 -> 7825 | E46: =E6+E16+E26+E36 -> 8552 | F46: =F6+F16+F26+F36 -> 3498 | G46: =G6+G16+G26+G36 -> 57554 | H46: =H6+H16+H26+H36 -> 6022 | I46: =SUM(C46:H46) -> 83451 | K46: AM | L46: =INT(C46/52) -> 0 | M46: =INT(D46/52) -> 150 | N46: =INT(E46/52) -> 164 | O46: =INT(F46/52) -> 67 | P46: =INT(G46/52) -> 1106 | Q46: =INT(H46/52) -> 115 | R46: =SUM(L46:Q46) -> 1602
B47: CE | C47: =C7+C17+C27+C37 -> 13384 | D47: =D7+D17+D27+D37 -> 0 | E47: =E7+E17+E27+E37 -> 2780 | F47: =F7+F17+F27+F37 -> 594 | G47: =G7+G17+G27+G37 -> 17206 | H47: =H7+H17+H27+H37 -> 7321 | I47: =SUM(C47:H47) -> 41285 | K47: CE | L47: =INT(C47/52) -> 257 | M47: =INT(D47/52) -> 0 | N47: =INT(E47/52) -> 53 | O47: =INT(F47/52) -> 11 | P47: =INT(G47/52) -> 330 | Q47: =INT(H47/52) -> 140 | R47: =SUM(L47:Q47) -> 791
B48: PE | C48: =C8+C18+C28+C38 -> 21147 | D48: =D8+D18+D28+D38 -> 6937 | E48: =E8+E18+E28+E38 -> 0 | F48: =F8+F18+F28+F38 -> 3620 | G48: =G8+G18+G28+G38 -> 18324 | H48: =H8+H18+H28+H38 -> 5127 | I48: =SUM(C48:H48) -> 55155 | K48: PE | L48: =INT(C48/52) -> 406 | M48: =INT(D48/52) -> 133 | N48: =INT(E48/52) -> 0 | O48: =INT(F48/52) -> 69 | P48: =INT(G48/52) -> 352 | Q48: =INT(H48/52) -> 98 | R48: =SUM(L48:Q48) -> 1058
B49: BA | C49: =C9+C19+C29+C39 -> 3873 | D49: =D9+D19+D29+D39 -> 3139 | E49: =E9+E19+E29+E39 -> 2375 | F49: =F9+F19+F29+F39 -> 0 | G49: =G9+G19+G29+G39 -> 22201 | H49: =H9+H19+H29+H39 -> 2846 | I49: =SUM(C49:H49) -> 34434 | K49: BA | L49: =INT(C49/52) -> 74 | M49: =INT(D49/52) -> 60 | N49: =INT(E49/52) -> 45 | O49: =INT(F49/52) -> 0 | P49: =INT(G49/52) -> 426 | Q49: =INT(H49/52) -> 54 | R49: =SUM(L49:Q49) -> 659
B50: SP | C50: =C10+C20+C30+C40 -> 24407 | D50: =D10+D20+D30+D40 -> 31566 | E50: =E10+E20+E30+E40 -> 38079 | F50: =F10+F20+F30+F40 -> 6793 | G50: =G10+G20+G30+G40 -> 0 | H50: =H10+H20+H30+H40 -> 0 | I50: =SUM(C50:H50) -> 100845 | K50: SP | L50: =INT(C50/52) -> 469 | M50: =INT(D50/52) -> 607 | N50: =INT(E50/52) -> 732 | O50: =INT(F50/52) -> 130 | P50: =INT(G50/52) -> 0 | Q50: =INT(H50/52) -> 0 | R50: =SUM(L50:Q50) -> 1938
B51: SC | C51: =C11+C21+C31+C41 -> 18888 | D51: =D11+D21+D31+D41 -> 28520 | E51: =E11+E21+E31+E41 -> 38701 | F51: =F11+F21+F31+F41 -> 7743 | G51: =G11+G21+G31+G41 -> 0 | H51: =H11+H21+H31+H41 -> 0 | I51: =SUM(C51:H51) -> 93852 | K51: SC | L51: =INT(C51/52) -> 363 | M51: =INT(D51/52) -> 548 | N51: =INT(E51/52) -> 744 | O51: =INT(F51/52) -> 148 | P51: =INT(G51/52) -> 0 | Q51: =INT(H51/52) -> 0 | R51: =SUM(L51:Q51) -> 1803
B52: Total Destino | C52: =SUM(C46:C51) -> 81699 | D52: =SUM(D46:D51) -> 77987 | E52: =SUM(E46:E51) -> 90487 | F52: =SUM(F46:F51) -> 22248 | G52: =SUM(G46:G51) -> 115285 | H52: =SUM(H46:H51) -> 21316 | I52: =SUM(I46:I51) -> 409022 | K52: Total Destino | L52: =SUM(L46:L51) -> 1569 | M52: =SUM(M46:M51) -> 1498 | N52: =SUM(N46:N51) -> 1738 | O52: =SUM(O46:O51) -> 425 | P52: =SUM(P46:P51) -> 2214 | Q52: =SUM(Q46:Q51) -> 407 | R52: =SUM(R46:R51) -> 7851
B54: Movimentação de Contêineres na Cabotagem em 2022 - TEU | K54: Movimentação de Contêineres na Cabotagem em 2022 - TEU
B55: Origem/Destino | C55: AM | D55: CE | E55: PE | F55: BA | G55: SP | H55: SC | I55: Total Origem | K55: Origem/Destino | L55: AM | M55: CE | N55: PE | O55: BA | P55: SP | Q55: SC | R55: Total Origem
B56: AM | C56: =C46+C26+C36 -> 0 | D56: =D46+D26+D36 -> 13903 | E56: =E46+E26+E36 -> 16790 | F56: =F46+F26+F36 -> 6665 | G56: =G46+G26+G36 -> 112595 | H56: =H46+H26+H36 -> 11569 | I56: =SUM(C56:H56) -> 161522 | K56: AM | L56: =INT(C56/52) -> 0 | M56: =INT(D56/52) -> 267 | N56: =INT(E56/52) -> 322 | O56: =INT(F56/52) -> 128 | P56: =INT(G56/52) -> 2165 | Q56: =INT(H56/52) -> 222 | R56: =SUM(L56:Q56) -> 3104
B57: CE | C57: =C47+C27+C37 -> 23842 | D57: =D47+D27+D37 -> 0 | E57: =E47+E27+E37 -> 5278 | F57: =F47+F27+F37 -> 697 | G57: =G47+G27+G37 -> 25277 | H57: =H47+H27+H37 -> 10587 | I57: =SUM(C57:H57) -> 65681 | K57: CE | L57: =INT(C57/52) -> 458 | M57: =INT(D57/52) -> 0 | N57: =INT(E57/52) -> 101 | O57: =INT(F57/52) -> 13 | P57: =INT(G57/52) -> 486 | Q57: =INT(H57/52) -> 203 | R57: =SUM(L57:Q57) -> 1261
B58: PE | C58: =C48+C28+C38 -> 40255 | D58: =D48+D28+D38 -> 12390 | E58: =E48+E28+E38 -> 0 | F58: =F48+F28+F38 -> 4273 | G58: =G48+G28+G38 -> 28128 | H58: =H48+H28+H38 -> 9423 | I58: =SUM(C58:H58) -> 94469 | K58: PE | L58: =INT(C58/52) -> 774 | M58: =INT(D58/52) -> 238 | N58: =INT(E58/52) -> 0 | O58: =INT(F58/52) -> 82 | P58: =INT(G58/52) -> 540 | Q58: =INT(H58/52) -> 181 | R58: =SUM(L58:Q58) -> 1815
B59: BA | C59: =C49+C29+C39 -> 7339 | D59: =D49+D29+D39 -> 5495 | E59: =E49+E29+E39 -> 4078 | F59: =F49+F29+F39 -> 0 | G59: =G49+G29+G39 -> 33493 | H59: =H49+H29+H39 -> 5401 | I59: =SUM(C59:H59) -> 55806 | K59: BA | L59: =INT(C59/52) -> 141 | M59: =INT(D59/52) -> 105 | N59: =INT(E59/52) -> 78 | O59: =INT(F59/52) -> 0 | P59: =INT(G59/52) -> 644 | Q59: =INT(H59/52) -> 103 | R59: =SUM(L59:Q59) -> 1071
B60: SP | C60: =C50+C30+C40 -> 44756 | D60: =D50+D30+D40 -> 56746 | E60: =E50+E30+E40 -> 69572 | F60: =F50+F30+F40 -> 11507 | G60: =G50+G30+G40 -> 0 | H60: =H50+H30+H40 -> 0 | I60: =SUM(C60:H60) -> 182581 | K60: SP | L60: =INT(C60/52) -> 860 | M60: =INT(D60/52) -> 1091 | N60: =INT(E60/52) -> 1337 | O60: =INT(F60/52) -> 221 | P60: =INT(G60/52) -> 0 | Q60: =INT(H60/52) -> 0 | R60: =SUM(L60:Q60) -> 3509
B61: SC | C61: =C51+C31+C41 -> 36324 | D61: =D51+D31+D41 -> 45197 | E61: =E51+E31+E41 -> 63792 | F61: =F51+F31+F41 -> 11283 | G61: =G51+G31+G41 -> 0 | H61: =H51+H31+H41 -> 0 | I61: =SUM(C61:H61) -> 156596 | K61: SC | L61: =INT(C61/52) -> 698 | M61: =INT(D61/52) -> 869 | N61: =INT(E61/52) -> 1226 | O61: =INT(F61/52) -> 216 | P61: =INT(G61/52) -> 0 | Q61: =INT(H61/52) -> 0 | R61: =SUM(L61:Q61) -> 3009
B62: Total Destino | C62: =SUM(C56:C61) -> 152516 | D62: =SUM(D56:D61) -> 133731 | E62: =SUM(E56:E61) -> 159510 | F62: =SUM(F56:F61) -> 34425 | G62: =SUM(G56:G61) -> 199493 | H62: =SUM(H56:H61) -> 36980 | I62: =SUM(I56:I61) -> 716655 | K62: Total Destino | L62: =SUM(L56:L61) -> 2931 | M62: =SUM(M56:M61) -> 2570 | N62: =SUM(N56:N61) -> 3064 | O62: =SUM(O56:O61) -> 660 | P62: =SUM(P56:P61) -> 3835 | Q62: =SUM(Q56:Q61) -> 709 | R62: =SUM(R56:R61) -> 13769
B64: Distâncias RODO
B65: Origem/Destino | C65: MANAUS | D65: FORTALEZA | E65: RECIFE | F65: SALVADOR | G65: SÃO PAULO | H65: FLORIANÓPOLIS
B66: MANAUS | D66: {=_xludf.XLOOKUP($B66,'Distancias Cidades'!$A$3:$A$28,_xludf.XLOOKUP(D$65,'Distancias Cidades'!$B$2:$AB$2,'Distancias Cidades'!$B$3:$AB$28))} -> #NAME? | E66: {=_xludf.XLOOKUP($B66,'Distancias Cidades'!$A$3:$A$28,_xludf.XLOOKUP(E$65,'Distancias Cidades'!$B$2:$AB$2,'Distancias Cidades'!$B$3:$AB$28))} -> #NAME? | F66: {=_xludf.XLOOKUP($B66,'Distancias Cidades'!$A$3:$A$28,_xludf.XLOOKUP(F$65,'Distancias Cidades'!$B$2:$AB$2,'Distancias Cidades'!$B$3:$AB$28))} -> #NAME? | G66: {=_xludf.XLOOKUP($B66,'Distancias Cidades'!$A$3:$A$28,_xludf.XLOOKUP(G$65,'Distancias Cidades'!$B$2:$AB$2,'Distancias Cidades'!$B$3:$AB$28))} -> #NAME? | H66: {=_xludf.XLOOKUP($B66,'Distancias Cidades'!$A$3:$A$28,_xludf.XLOOKUP(H$65,'Distancias Cidades'!$B$2:$AB$2,'Distancias Cidades'!$B$3:$AB$28))} -> #NAME?
B67: FORTALEZA | C67: {=(_xludf.XLOOKUP(B67,'Distancias Cidades'!$A$3:$A$28,_xludf.XLOOKUP("BELÉM",'Distancias Cidades'!$B$2:$AB$2,'Distancias Cidades'!$B$3:$AB$28)))+10} -> #NAME? | D67: {=_xludf.XLOOKUP($B67,'Distancias Cidades'!$A$3:$A$28,_xludf.XLOOKUP(D$65,'Distancias Cidades'!$B$2:$AB$2,'Distancias Cidades'!$B$3:$AB$28))} -> #NAME? | E67: {=_xludf.XLOOKUP($B67,'Distancias Cidades'!$A$3:$A$28,_xludf.XLOOKUP(E$65,'Distancias Cidades'!$B$2:$AB$2,'Distancias Cidades'!$B$3:$AB$28))} -> #NAME? | F67: {=_xludf.XLOOKUP($B67,'Distancias Cidades'!$A$3:$A$28,_xludf.XLOOKUP(F$65,'Distancias Cidades'!$B$2:$AB$2,'Distancias Cidades'!$B$3:$AB$28))} -> #NAME? | G67: {=_xludf.XLOOKUP($B67,'Distancias Cidades'!$A$3:$A$28,_xludf.XLOOKUP(G$65,'Distancias Cidades'!$B$2:$AB$2,'Distancias Cidades'!$B$3:$AB$28))} -> #NAME? | H67: {=_xludf.XLOOKUP($B67,'Distancias Cidades'!$A$3:$A$28,_xludf.XLOOKUP(H$65,'Distancias Cidades'!$B$2:$AB$2,'Distancias Cidades'!$B$3:$AB$28))} -> #NAME?
B68: RECIFE | C68: {=(_xludf.XLOOKUP(B68,'Distancias Cidades'!$A$3:$A$28,_xludf.XLOOKUP("BELÉM",'Distancias Cidades'!$B$2:$AB$2,'Distancias Cidades'!$B$3:$AB$28)))+10} -> #NAME? | D68: {=_xludf.XLOOKUP($B68,'Distancias Cidades'!$A$3:$A$28,_xludf.XLOOKUP(D$65,'Distancias Cidades'!$B$2:$AB$2,'Distancias Cidades'!$B$3:$AB$28))} -> #NAME? | E68: {=_xludf.XLOOKUP($B68,'Distancias Cidades'!$A$3:$A$28,_xludf.XLOOKUP(E$65,'Distancias Cidades'!$B$2:$AB$2,'Distancias Cidades'!$B$3:$AB$28))} -> #NAME? | F68: {=_xludf.XLOOKUP($B68,'Distancias Cidades'!$A$3:$A$28,_xludf.XLOOKUP(F$65,'Distancias Cidades'!$B$2:$AB$2,'Distancias Cidades'!$B$3:$AB$28))} -> #NAME? | G68: {=_xludf.XLOOKUP($B68,'Distancias Cidades'!$A$3:$A$28,_xludf.XLOOKUP(G$65,'Distancias Cidades'!$B$2:$AB$2,'Distancias Cidades'!$B$3:$AB$28))} -> #NAME? | H68: {=_xludf.XLOOKUP($B68,'Distancias Cidades'!$A$3:$A$28,_xludf.XLOOKUP(H$65,'Distancias Cidades'!$B$2:$AB$2,'Distancias Cidades'!$B$3:$AB$28))} -> #NAME?
B69: SALVADOR | C69: {=(_xludf.XLOOKUP(B69,'Distancias Cidades'!$A$3:$A$28,_xludf.XLOOKUP("BELÉM",'Distancias Cidades'!$B$2:$AB$2,'Distancias Cidades'!$B$3:$AB$28)))+10} -> #NAME? | D69: {=_xludf.XLOOKUP($B69,'Distancias Cidades'!$A$3:$A$28,_xludf.XLOOKUP(D$65,'Distancias Cidades'!$B$2:$AB$2,'Distancias Cidades'!$B$3:$AB$28))} -> #NAME? | E69: {=_xludf.XLOOKUP($B69,'Distancias Cidades'!$A$3:$A$28,_xludf.XLOOKUP(E$65,'Distancias Cidades'!$B$2:$AB$2,'Distancias Cidades'!$B$3:$AB$28))} -> #NAME? | F69: {=_xludf.XLOOKUP($B69,'Distancias Cidades'!$A$3:$A$28,_xludf.XLOOKUP(F$65,'Distancias Cidades'!$B$2:$AB$2,'Distancias Cidades'!$B$3:$AB$28))} -> #NAME? | G69: {=_xludf.XLOOKUP($B69,'Distancias Cidades'!$A$3:$A$28,_xludf.XLOOKUP(G$65,'Distancias Cidades'!$B$2:$AB$2,'Distancias Cidades'!$B$3:$AB$28))} -> #NAME? | H69: {=_xludf.XLOOKUP($B69,'Distancias Cidades'!$A$3:$A$28,_xludf.XLOOKUP(H$65,'Distancias Cidades'!$B$2:$AB$2,'Distancias Cidades'!$B$3:$AB$28))} -> #NAME?
B70: SÃO PAULO | C70: {=(_xludf.XLOOKUP(B70,'Distancias Cidades'!$A$3:$A$28,_xludf.XLOOKUP("BELÉM",'Distancias Cidades'!$B$2:$AB$2,'Distancias Cidades'!$B$3:$AB$28)))+10} -> #NAME? | D70: {=_xludf.XLOOKUP($B70,'Distancias Cidades'!$A$3:$A$28,_xludf.XLOOKUP(D$65,'Distancias Cidades'!$B$2:$AB$2,'Distancias Cidades'!$B$3:$AB$28))} -> #NAME? | E70: {=_xludf.XLOOKUP($B70,'Distancias Cidades'!$A$3:$A$28,_xludf.XLOOKUP(E$65,'Distancias Cidades'!$B$2:$AB$2,'Distancias Cidades'!$B$3:$AB$28))} -> #NAME? | F70: {=_xludf.XLOOKUP($B70,'Distancias Cidades'!$A$3:$A$28,_xludf.XLOOKUP(F$65,'Distancias Cidades'!$B$2:$AB$2,'Distancias Cidades'!$B$3:$AB$28))} -> #NAME? | G70: {=_xludf.XLOOKUP($B70,'Distancias Cidades'!$A$3:$A$28,_xludf.XLOOKUP(G$65,'Distancias Cidades'!$B$2:$AB$2,'Distancias Cidades'!$B$3:$AB$28))} -> #NAME? | H70: {=_xludf.XLOOKUP($B70,'Distancias Cidades'!$A$3:$A$28,_xludf.XLOOKUP(H$65,'Distancias Cidades'!$B$2:$AB$2,'Distancias Cidades'!$B$3:$AB$28))} -> #NAME?
B71: FLORIANÓPOLIS | C71: {=(_xludf.XLOOKUP(B71,'Distancias Cidades'!$A$3:$A$28,_xludf.XLOOKUP("BELÉM",'Distancias Cidades'!$B$2:$AB$2,'Distancias Cidades'!$B$3:$AB$28)))+10} -> #NAME? | D71: {=_xludf.XLOOKUP($B71,'Distancias Cidades'!$A$3:$A$28,_xludf.XLOOKUP(D$65,'Distancias Cidades'!$B$2:$AB$2,'Distancias Cidades'!$B$3:$AB$28))} -> #NAME? | E71: {=_xludf.XLOOKUP($B71,'Distancias Cidades'!$A$3:$A$28,_xludf.XLOOKUP(E$65,'Distancias Cidades'!$B$2:$AB$2,'Distancias Cidades'!$B$3:$AB$28))} -> #NAME? | F71: {=_xludf.XLOOKUP($B71,'Distancias Cidades'!$A$3:$A$28,_xludf.XLOOKUP(F$65,'Distancias Cidades'!$B$2:$AB$2,'Distancias Cidades'!$B$3:$AB$28))} -> #NAME? | G71: {=_xludf.XLOOKUP($B71,'Distancias Cidades'!$A$3:$A$28,_xludf.XLOOKUP(G$65,'Distancias Cidades'!$B$2:$AB$2,'Distancias Cidades'!$B$3:$AB$28))} -> #NAME? | H71: {=_xludf.XLOOKUP($B71,'Distancias Cidades'!$A$3:$A$28,_xludf.XLOOKUP(H$65,'Distancias Cidades'!$B$2:$AB$2,'Distancias Cidades'!$B$3:$AB$28))} -> #NAME?
B74: Receita CABOTAGEM | K74: RECEITA POTENCIAL CABOTAGEM SEMANAL
B75: Origem/Destino | C75: AM | D75: CE | E75: PE | F75: BA | G75: SP | H75: SC | K75: Origem/Destino | L75: AM | M75: CE | N75: PE | O75: BA | P75: SP | Q75: SC
B76: AM | D76: =C77 -> #NAME? | E76: =C78 -> #NAME? | F76: =C79 -> #NAME? | G76: =C80 -> #NAME? | H76: =C81 -> #NAME? | K76: AM | L76: =C76*L46 -> 0 | M76: =D76*M46 -> #NAME? | N76: =E76*N46 -> #NAME? | O76: =F76*O46 -> #NAME? | P76: =G76*P46 -> #NAME? | Q76: =H76*Q46 -> #NAME?
B77: CE | C77: =(((C67*5.6748+496.5)*1.3)+7000)*0.7 -> #NAME? | E77: =D78 -> #NAME? | F77: =D79 -> #NAME? | G77: =D80 -> #NAME? | H77: =D81 -> #NAME? | K77: CE | L77: =C77*L47 -> #NAME? | M77: =D77*M47 -> 0 | N77: =E77*N47 -> #NAME? | O77: =F77*O47 -> #NAME? | P77: =G77*P47 -> #NAME? | Q77: =H77*Q47 -> #NAME?
B78: PE | C78: =(((C68*5.6748+496.5)*1.3)+7000)*0.7 -> #NAME? | D78: =(D68*5.6748+496.5)*1.3*0.7 -> #NAME? | F78: =E79 -> #NAME? | G78: =(G68*5.6748+496.5)*1.3*0.7 -> #NAME? | H78: =E81 -> #NAME? | K78: PE | L78: =C78*L48 -> #NAME? | M78: =D78*M48 -> #NAME? | N78: =E78*N48 -> 0 | O78: =F78*O48 -> #NAME? | P78: =G78*P48 -> #NAME? | Q78: =H78*Q48 -> #NAME?
B79: BA | C79: =(((C69*5.6748+496.5)*1.3)+7000)*0.7 -> #NAME? | D79: =(D69*5.6748+496.5)*1.3*0.7 -> #NAME? | E79: =(E69*5.6748+496.5)*1.3*0.7 -> #NAME? | H79: =(H69*5.6748+496.5)*1.3*0.7 -> #NAME? | K79: BA | L79: =C79*L49 -> #NAME? | M79: =D79*M49 -> #NAME? | N79: =E79*N49 -> #NAME? | O79: =F79*O49 -> 0 | P79: =G79*P49 -> 0 | Q79: =H79*Q49 -> #NAME?
B80: SP | C80: =(((C70*5.6748+496.5)*1.3)+7000)*0.7 -> #NAME? | D80: =(D70*5.6748+496.5)*1.3*0.7 -> #NAME? | E80: =(E70*5.6748+496.5)*1.3*0.7 -> #NAME? | F80: =(F70*5.6748+496.5)*1.3*0.7 -> #NAME? | K80: SP | L80: =C80*L50 -> #NAME? | M80: =D80*M50 -> #NAME? | N80: =E80*N50 -> #NAME? | O80: =F80*O50 -> #NAME? | P80: =G80*P50 -> 0 | Q80: =H80*Q50 -> 0
B81: SC | C81: =(((C71*5.6748+496.5)*1.3)+7000)*0.7 -> #NAME? | D81: =(D71*5.6748+496.5)*1.3*0.7 -> #NAME? | E81: =(E71*5.6748+496.5)*1.3*0.7 -> #NAME? | F81: =(F71*5.6748+496.5)*1.3*0.7 -> #NAME? | K81: SC | L81: =C81*L51 -> #NAME? | M81: =D81*M51 -> #NAME? | N81: =E81*N51 -> #NAME? | O81: =F81*O51 -> #NAME? | P81: =G81*P51 -> 0 | Q81: =H81*Q51 -> 0
B82: *CONSIDERAR CAMINHÃO DE SEIS EIXOS | Q82: SEMANAL | R82: =SUM(L76:Q81) -> #NAME?
G83: CABOTAGEM | Q83: ANUAL | R83: =R82*52 -> #NAME?
B85: * nosso serviço é porta porta e não porto porto, considerar o custo do rodo ate o porto e do porto pra porta e depois os 70%
B88: DESTINOS DA CARGA | K88: DESTINOS DA CARGA | T88: DESTINOS DA CARGA
B89: SP(1) -> SC(2) | C89: SC(2) -> BA(3) | D89: BA(3) -> PE(4) | E89: PE(4) -> CE(5) | F89: CE(5) -> AM(6) | G89: AM(6) -> SP(1) | K89: SP(1) -> SC(2) | L89: SC(2) -> BA(3) | M89: BA(3) -> PE(4) | N89: PE(4) -> CE(5) | O89: CE(5) -> AM(6) | P89: AM(6) -> SP(1) | T89: SP(1) -> SC(2) | U89: SC(2) -> BA(3) | V89: BA(3) -> PE(4) | W89: PE(4) -> CE(5) | X89: CE(5) -> AM(6) | Y89: AM(6) -> SP(1)
B90: Embarque SP | C90: Embarque SC | D90: Embarque BA | E90: Embarque PE | F90: Embarque CE | G90: Embarque AM | K90: =R133+AD10*2+AD30*4 -> 20272.768 | L90: =R134 -> 19880 | M90: =R132+AD9*2 -> 5047.6647 | N90: =R131+AD8*2+AD28*4+AD38*4 -> 15853.008 | O90: =R130+AD7*2+AD27*4+AD37*4 -> 17069.221 | P90: =R129+AD6*2+AD36*4 -> 33471.491 | T90: 16212 | U90: 20636 | V90: 4396 | W90: 14252 | X90: 16296 | Y90: 32648
B91: 3 -- 2 | C91: 4 -- 3 | D91: 5 -- 4 | E91: 6 -- 5 | F91: 1 -- 6 | G91: 2 -- 1 | K91: =Q132 -> 420 | L91: =O131 -> 0 | M91: =N130 -> 0 | N91: =M129 -> 0 | O91: =L133 -> 3052 | P91: 0 | T91: 364 | U91: 0 | V91: 0 | W91: 448 | X91: 3976 | Y91: 0
B92: 4 -- 2 | C92: 5 -- 3 | D92: 6 -- 4 | E92: 1 -- 5 | F92: 2 -- 6 | G92: 3 -- 1 | K92: =Q131 -> 1008 | L92: =O130 -> 0 | M92: =N129 -> 616 | N92: =M133 -> 5516 | O92: =L134 -> 3696 | P92: =P132 -> 0 | T92: 1036 | U92: 112 | V92: 1092 | W92: 4592 | X92: 4788 | Y92: 0
B93: 4 -- 3 | C93: 5 -- 4 | D93: 6 -- 5 | E93: 1 -- 6 | F93: 2 -- 1 | G93: 3 -- 2 | K93: =O131 -> 0 | L93: =N130 -> 0 | M93: =M129 -> 0 | N93: =L133 -> 3052 | O93: 0 | P93: =Q132 -> 420 | T93: 0 | U93: 0 | V93: 448 | W93: 3976 | X93: 0 | Y93: 364
B94: 5 -- 2 | C94: 6 -- 3 | D94: 1 -- 4 | E94: 2 -- 5 | F94: 3 -- 6 | G94: 4 -- 1 | K94: =Q130 -> 420 | L94: =O129 -> 868 | M94: =N133 -> 6524 | N94: =M134 -> 7280 | O94: =L132 -> 1820 | P94: =P131 -> 700 | T94: 364 | U94: 700 | V94: 5292 | W94: 7700 | X94: 1484 | Y94: 1456
B95: 5 -- 3 | C95: 6 -- 4 | D95: 1 -- 5 | E95: 2 -- 6 | F95: 3 -- 1 | G95: 4 -- 2 | K95: =O130 -> 0 | L95: =N129 -> 616 | M95: =M133 -> 5516 | N95: =L134 -> 3696 | O95: =P132 -> 0 | P95: =Q131 -> 1008 | T95: 112 | U95: 1092 | V95: 4592 | W95: 4788 | X95: 0 | Y95: 1036
B96: 5 -- 4 | C96: 6 -- 5 | D96: 1 -- 6 | E96: 2 -- 1 | F96: 3 -- 2 | G96: 4 -- 3 | K96: =N130 -> 0 | L96: =M129 -> 0 | M96: =L133 -> 3052 | N96: 0 | O96: =Q132 -> 420 | P96: =O131 -> 0 | T96: 0 | U96: 448 | V96: 3976 | W96: 0 | X96: 364 | Y96: 0
B97: 6 -- 2 | C97: 1 -- 3 | D97: 2 -- 4 | E97: 3 -- 5 | F97: 4 -- 6 | G97: 5 -- 1 | K97: =Q129 -> 3220 | L97: =O133 -> 2744 | M97: =N134 -> 7448 | N97: =M132 -> 1540 | O97: =L131 -> 11424 | P97: =P130 -> 3164 | T97: 3192 | U97: 2352 | V97: 6888 | W97: 1540 | X97: 9744 | Y97: 3192
B98: 6 -- 3 | C98: 1 -- 4 | D98: 2 -- 5 | E98: 3 -- 6 | F98: 4 -- 1 | G98: 5 -- 2 | K98: =O129 -> 868 | L98: =N133 -> 6524 | M98: =M134 -> 7280 | N98: =L132 -> 1820 | O98: =P131 -> 700 | P98: =Q130 -> 420 | T98: 700 | U98: 5292 | V98: 7700 | W98: 1484 | X98: 1456 | Y98: 364
B99: 6 -- 4 | C99: 1 -- 5 | D99: 2 -- 6 | E99: 3 -- 1 | F99: 4 -- 2 | G99: 5 -- 3 | K99: =N129 -> 616 | L99: =M133 -> 5516 | M99: =L134 -> 3696 | N99: =P132 -> 0 | O99: =Q131 -> 1008 | P99: =O130 -> 0 | T99: 1092 | U99: 4592 | V99: 4788 | W99: 0 | X99: 1036 | Y99: 112
B100: 6 -- 5 | C100: 1 -- 6 | D100: 2 -- 1 | E100: 3 -- 2 | F100: 4 -- 3 | G100: 5 -- 4 | K100: =M129 -> 0 | L100: =L133 -> 3052 | M100: 0 | N100: =Q132 -> 420 | O100: =O131 -> 0 | P100: =N130 -> 0 | T100: 448 | U100: 3976 | V100: 0 | W100: 364 | X100: 0 | Y100: 0
K101: =SUM(K90:K100) -> 26824.768 | L101: =SUM(L90:L100) -> 39200 | M101: =SUM(M90:M100) -> 39179.665 | N101: =SUM(N90:N100) -> 39177.008 | O101: =SUM(O90:O100) -> 39189.221 | P101: =SUM(P90:P100) -> 39183.491 | T101: 23520 | U101: 39200 | V101: 39172 | W101: 39144 | X101: 39144 | Y101: 39172
K102: TONELAGEM E DESTINOS | T102: TONELAGEM E DESTINOS
K105: MOVIMENTAÇÃO POTENCIAL UNIDADES
B106: PORCENTAGEM LEVADA | K106: Origem/Destino | L106: AM | M106: CE | N106: PE | O106: BA | P106: SP | Q106: SC | R106: Total Origem
B107: Origem/Destino | C107: AM | D107: CE | E107: PE | F107: BA | G107: SP | H107: SC | K107: AM | L107: =L56 -> 0 | M107: =M46 -> 150 | N107: =N46 -> 164 | O107: =O46 -> 67 | P107: =P46 -> 1106 | Q107: =Q46 -> 115 | R107: =SUM(L107:Q107) -> 1602
B108: AM | C108: 0 | D108: 0 | E108: 0.13649187 | F108: 0.46415726 | G108: 0.92120268 | H108: 1 | K108: CE | L108: =L57 -> 458 | M108: =M47 -> 0 | N108: =N47 -> 53 | O108: =O47 -> 11 | P108: =P47 -> 330 | Q108: =Q47 -> 140 | R108: =SUM(L108:Q108) -> 992
B109: CE | C109: 0.99881697 | D109: 0 | E109: 0.0087383091 | F109: 0.068722534 | G109: 0.34429711 | H109: 0.10983109 | K109: PE | L109: =L58 -> 774 | M109: =M48 -> 133 | N109: =N48 -> 0 | O109: =O48 -> 69 | P109: =P48 -> 352 | Q109: =Q48 -> 98 | R109: =SUM(L109:Q109) -> 1426
B110: PE | C110: 0.52763407 | D110: 0.55302353 | E110: 0 | F110: 0.0027778396 | G110: 0.073406174 | H110: 0.37383324 | K110: BA | L110: =L59 -> 141 | M110: =M49 -> 60 | N110: =N49 -> 45 | O110: =O49 -> 0 | P110: =P49 -> 426 | Q110: =Q49 -> 54 | R110: =SUM(L110:Q110) -> 726
B111: BA | C111: 0.46146159 | D111: 0.91924795 | E111: 0.96106934 | F111: 0 | G111: 0.001783125 | H111: 0.28979911 | K111: SP | L111: =L60 -> 860 | M111: =M50 -> 607 | N111: =N50 -> 732 | O111: =O50 -> 130 | P111: =P50 -> 0 | Q111: =Q50 -> 0 | R111: =SUM(L111:Q111) -> 2329
B112: SP | C112: 0.12722359 | D112: 0.32495108 | E112: 0.31920858 | F112: 0.75401603 | G112: 0 | H112: 0.35059357 | K112: SC | L112: =L61 -> 698 | M112: =M51 -> 548 | N112: =N51 -> 744 | O112: =O51 -> 148 | P112: =P51 -> 0 | Q112: =Q51 -> 0 | R112: =SUM(L112:Q112) -> 2138
B113: SC | C113: 0.18944884 | D113: 0.47524853 | E113: 0.35760356 | F113: 0.35397709 | G113: 0.71888235 | H113: 0 | K113: Total Destino | L113: =SUM(L107:L112) -> 2931 | M113: =SUM(M107:M112) -> 1498 | N113: =SUM(N107:N112) -> 1738 | O113: =SUM(O107:O112) -> 425 | P113: =SUM(P107:P112) -> 2214 | Q113: =SUM(Q107:Q112) -> 407 | R113: =SUM(R107:R112) -> 9213
K116: MOVIMENTAÇÃO LEVADA UNIDADES
K117: Origem/Destino | L117: AM | M117: CE | N117: PE | O117: BA | P117: SP | Q117: SC | R117: Total Origem
...

Sheet __Solver__
A1: 2023681688872554185 | D1: t3JImZndu39Hg58 | J1: 1
A2: =MAX('OTIMIZA ROTA'!AY38) -> 65986446
A3: ='OTIMIZA ROTA'!P90:Q90 -> #VALUE!
A4: OGM=
A6: RQJ7el5pX1VGAA==
A7: ='OTIMIZA ROTA'!L68:Q73 <= 'OTIMIZA ROTA'!L6:Q11 -> #VALUE!
A8: ='OTIMIZA ROTA'!L78:Q83 <= 'OTIMIZA ROTA'!L26:Q31 -> #VALUE!
A9: ='OTIMIZA ROTA'!L88:Q93 <= 'OTIMIZA ROTA'!L36:Q41 -> #VALUE!
A10: ='OTIMIZA ROTA'!L68:Q73 <= 0 -> #VALUE!
A11: ='OTIMIZA ROTA'!L78:Q83 <= 0 -> #VALUE!
A12: ='OTIMIZA ROTA'!L88:Q93 <= 0 -> #VALUE!
A13: ='OTIMIZA ROTA'!AF75:AL75 <= 'OTIMIZA ROTA'!AF76:AL76 -> #VALUE!
A14: ='OTIMIZA ROTA'!AO75:AU75 <= 'OTIMIZA ROTA'!AO76:AU76 -> #VALUE!
A15: ='OTIMIZA ROTA'!AO75:AU75 <= 0 -> #VALUE!
A16: ='OTIMIZA ROTA'!AF75:AL75 <= 0 -> #VALUE!

Sheet __Solver___conflict2099073712

Sheet __Solver___conflict325174676

Sheet __Solver___conflict976500911

Sheet __Solver___conflict1703220588

Sheet __Solver___conflict78492872

Sheet __Solver___conflict342278247

Sheet __Solver___conflict1363959748

Sheet __Solver___conflict1329151324

Sheet Copy of OTIMIZAÇÃO ROTA
AC1: DFVV
B2: ANUAL | K2: SEMANAL | T2: SEMANAL VAZIO
B4: Movimentação de Contêineres na Cabotagem em 2022 - 20DC | K4: MATRIZ OD 20 DC CHEIOS | T4: Imbalance 20DC | W4: MATRIZ OD 20 DC VAZIOS | AF4: MATRIZ OD 20 DC CHEIOS - TONELADAS | AO4: MATRIZ OD 20 DC VAZIOS - TONELADAS | AX4: RESUMO SOMA QNTD CONTÊINERS CHEIOS - 20 DC + 40 DC + 40 RH | BG4: RESUMO SOMA QNTD CONTÊINERS VAZIOS - 20 DC + 40 DC + 40 RH
B5: Origem/Destino | C5: AM | D5: CE | E5: PE | F5: BA | G5: SP | H5: SC | I5: Total Origem | K5: Origem/Destino | L5: AM | M5: CE | N5: PE | O5: BA | P5: SP | Q5: SC | R5: Total Origem | T5: Porto | U5: IMB | W5: Origem/Destino | X5: AM | Y5: CE | Z5: PE | AA5: BA | AB5: SP | AC5: SC | AD5: Total Origem | AF5: Origem/Destino | AG5: AM | AH5: CE | AI5: PE | AJ5: BA | AK5: SP | AL5: SC | AM5: Total Origem | AO5: Origem/Destino | AP5: AM | AQ5: CE | AR5: PE | AS5: BA | AT5: SP | AU5: SC | AV5: Total Origem | AX5: Origem/Destino | AY5: AM | AZ5: CE | BA5: PE | BB5: BA | BC5: SP | BD5: SC | BE5: Total Origem | BG5: Origem/Destino | BH5: AM | BI5: CE | BJ5: PE | BK5: BA | BL5: SP | BM5: SC | BN5: Total Origem
B6: AM | D6: 1747 | E6: 313 | F6: 329 | G6: 2513 | H6: 475 | I6: =SUM(C6:H6) -> 5377 | K6: AM | L6: =INT(C6/52) -> 0 | M6: =INT(D6/52) -> 33 | N6: =INT(E6/52) -> 6 | O6: =INT(F6/52) -> 6 | P6: =INT(G6/52) -> 48 | Q6: =INT(H6/52) -> 9 | R6: =SUM(L6:Q6) -> 102 | T6: AM | U6: =L12-R6 -> 105 | W6: AM | AB6: 56 | AC6: 49 | AD6: =SUM(X6:AC6) -> 105 | AF6: AM | AG6: =L6*28 -> 0 | AH6: =M6*28 -> 924 | AI6: =N6*28 -> 168 | AJ6: =O6*28 -> 168 | AK6: =P6*28 -> 1344 | AL6: =Q6*28 -> 252 | AM6: =SUM(AG6:AL6) -> 2856 | AO6: AM | AP6: =X6*2 -> 0 | AQ6: =Y6*2 -> 0 | AR6: =Z6*2 -> 0 | AS6: =AA6*2 -> 0 | AT6: =AB6*2 -> 112 | AU6: =AC6*2 -> 98 | AV6: =SUM(AP6:AU6) -> 210 | AX6: AM | AY6: =SUM(L6,L26,L46) -> 0 | AZ6: =SUM(M6,M26,M46) -> 149 | BA6: =SUM(N6,N26,N46) -> 164 | BB6: =SUM(O6,O26,O46) -> 66 | BC6: =SUM(P6,P26,P46) -> 1106 | BD6: =SUM(Q6,Q26,Q46) -> 114 | BE6: =SUM(AY6:BD6) -> 1599 | BG6: AM | BH6: =SUM(X6,X26,X46) -> 0 | BI6: =SUM(Y6,Y26,Y46) -> 0 | BJ6: =SUM(Z6,Z26,Z46) -> 0 | BK6: =SUM(AA6,AA26,AA46) -> 0 | BL6: =SUM(AB6,AB26,AB46) -> 56 | BM6: =SUM(AC6,AC26,AC46) -> 246 | BN6: =SUM(BH6:BM6) -> 302
B7: CE | C7: 2926 | E7: 282 | F7: 491 | G7: 9135 | H7: 4055 | I7: =SUM(C7:H7) -> 16889 | K7: CE | L7: =INT(C7/52) -> 56 | M7: =INT(D7/52) -> 0 | N7: =INT(E7/52) -> 5 | O7: =INT(F7/52) -> 9 | P7: =INT(G7/52) -> 175 | Q7: =INT(H7/52) -> 77 | R7: =SUM(L7:Q7) -> 322 | T7: CE | U7: =M12-R7 -> 102 | W7: CE | AC7: =U7 -> 102 | AD7: =SUM(X7:AC7) -> 102 | AF7: CE | AG7: =L7*28 -> 1568 | AH7: =M7*28 -> 0 | AI7: =N7*28 -> 140 | AJ7: =O7*28 -> 252 | AK7: =P7*28 -> 4900 | AL7: =Q7*28 -> 2156 | AM7: =SUM(AG7:AL7) -> 9016 | AO7: CE | AP7: =X7*2 -> 0 | AQ7: =Y7*2 -> 0 | AR7: =Z7*2 -> 0 | AS7: =AA7*2 -> 0 | AT7: =AB7*2 -> 0 | AU7: =AC7*2 -> 204 | AV7: =SUM(AP7:AU7) -> 204 | AX7: CE | AY7: =SUM(L7,L27,L47) -> 256 | AZ7: =SUM(M7,M27,M47) -> 0 | BA7: =SUM(N7,N27,N47) -> 52 | BB7: =SUM(O7,O27,O47) -> 10 | BC7: =SUM(P7,P27,P47) -> 330 | BD7: =SUM(Q7,Q27,Q47) -> 139 | BE7: =SUM(AY7:BD7) -> 787 | BG7: CE | BH7: =SUM(X7,X27,X47) -> 339 | BI7: =SUM(Y7,Y27,Y47) -> 0 | BJ7: =SUM(Z7,Z27,Z47) -> 0 | BK7: =SUM(AA7,AA27,AA47) -> 0 | BL7: =SUM(AB7,AB27,AB47) -> 11 | BM7: =SUM(AC7,AC27,AC47) -> 354 | BN7: =SUM(BH7:BM7) -> 704
B8: PE | C8: 2039 | D8: 1481 | F8: 2967 | G8: 8519 | H8: 827 | I8: =SUM(C8:H8) -> 15833 | K8: PE | L8: =INT(C8/52) -> 39 | M8: =INT(D8/52) -> 28 | N8: =INT(E8/52) -> 0 | O8: =INT(F8/52) -> 57 | P8: =INT(G8/52) -> 163 | Q8: =INT(H8/52) -> 15 | R8: =SUM(L8:Q8) -> 302 | T8: PE | U8: =N12-R8 -> 108 | W8: PE | AC8: =U8 -> 108 | AD8: =SUM(X8:AC8) -> 108 | AF8: PE | AG8: =L8*28 -> 1092 | AH8: =M8*28 -> 784 | AI8: =N8*28 -> 0 | AJ8: =O8*28 -> 1596 | AK8: =P8*28 -> 4564 | AL8: =Q8*28 -> 420 | AM8: =SUM(AG8:AL8) -> 8456 | AO8: PE | AP8: =X8*2 -> 0 | AQ8: =Y8*2 -> 0 | AR8: =Z8*2 -> 0 | AS8: =AA8*2 -> 0 | AT8: =AB8*2 -> 0 | AU8: =AC8*2 -> 216 | AV8: =SUM(AP8:AU8) -> 216 | AX8: PE | AY8: =SUM(L8,L28,L48) -> 405 | AZ8: =SUM(M8,M28,M48) -> 132 | BA8: =SUM(N8,N28,N48) -> 0 | BB8: =SUM(O8,O28,O48) -> 69 | BC8: =SUM(P8,P28,P48) -> 350 | BD8: =SUM(Q8,Q28,Q48) -> 97 | BE8: =SUM(AY8:BD8) -> 1053 | BG8: PE | BH8: =SUM(X8,X28,X48) -> 0 | BI8: =SUM(Y8,Y28,Y48) -> 0 | BJ8: =SUM(Z8,Z28,Z48) -> 0 | BK8: =SUM(AA8,AA28,AA48) -> 1 | BL8: =SUM(AB8,AB28,AB48) -> 285 | BM8: =SUM(AC8,AC28,AC48) -> 396 | BN8: =SUM(BH8:BM8) -> 682
B9: BA | C9: 407 | D9: 779 | E9: 670 | G9: 10907 | H9: 289 | I9: =SUM(C9:H9) -> 13052 | K9: BA | L9: =INT(C9/52) -> 7 | M9: =INT(D9/52) -> 14 | N9: =INT(E9/52) -> 12 | O9: =INT(F9/52) -> 0 | P9: =INT(G9/52) -> 209 | Q9: =INT(H9/52) -> 5 | R9: =SUM(L9:Q9) -> 247 | T9: BA | U9: =O12-R9 -> -56 | W9: BA | AD9: =SUM(X9:AC9) -> 0 | AF9: BA | AG9: =L9*28 -> 196 | AH9: =M9*28 -> 392 | AI9: =N9*28 -> 336 | AJ9: =O9*28 -> 0 | AK9: =P9*28 -> 5852 | AL9: =Q9*28 -> 140 | AM9: =SUM(AG9:AL9) -> 6916 | AO9: BA | AP9: =X9*2 -> 0 | AQ9: =Y9*2 -> 0 | AR9: =Z9*2 -> 0 | AS9: =AA9*2 -> 0 | AT9: =AB9*2 -> 0 | AU9: =AC9*2 -> 0 | AV9: =SUM(AP9:AU9) -> 0 | AX9: BA | AY9: =SUM(L9,L29,L49) -> 73 | AZ9: =SUM(M9,M29,M49) -> 59 | BA9: =SUM(N9,N29,N49) -> 44 | BB9: =SUM(O9,O29,O49) -> 0 | BC9: =SUM(P9,P29,P49) -> 425 | BD9: =SUM(Q9,Q29,Q49) -> 53 | BE9: =SUM(AY9:BD9) -> 654 | BG9: BA | BH9: =SUM(X9,X29,X49) -> 0 | BI9: =SUM(Y9,Y29,Y49) -> 0 | BJ9: =SUM(Z9,Z29,Z49) -> 0 | BK9: =SUM(AA9,AA29,AA49) -> 0 | BL9: =SUM(AB9,AB29,AB49) -> 0 | BM9: =SUM(AC9,AC29,AC49) -> 0 | BN9: =SUM(BH9:BM9) -> 0
B10: SP | C10: 4058 | D10: 6369 | E10: 6570 | F10: 2077 | I10: =SUM(C10:H10) -> 19074 | K10: SP | L10: =INT(C10/52) -> 78 | M10: =INT(D10/52) -> 122 | N10: =INT(E10/52) -> 126 | O10: =INT(F10/52) -> 39 | P10: =INT(G10/52) -> 0 | Q10: =INT(H10/52) -> 0 | R10: =SUM(L10:Q10) -> 365 | T10: SP | U10: =P12-R10 -> 230 | W10: SP | AC10: =U10 -> 230 | AD10: =SUM(X10:AC10) -> 230 | AF10: SP | AG10: =L10*28 -> 2184 | AH10: =M10*28 -> 3416 | AI10: =N10*28 -> 3528 | AJ10: =O10*28 -> 1092 | AK10: =P10*28 -> 0 | AL10: =Q10*28 -> 0 | AM10: =SUM(AG10:AL10) -> 10220 | AO10: SP | AP10: =X10*2 -> 0 | AQ10: =Y10*2 -> 0 | AR10: =Z10*2 -> 0 | AS10: =AA10*2 -> 0 | AT10: =AB10*2 -> 0 | AU10: =AC10*2 -> 460 | AV10: =SUM(AP10:AU10) -> 460 | AX10: SP | AY10: =SUM(L10,L30,L50) -> 468 | AZ10: =SUM(M10,M30,M50) -> 605 | BA10: =SUM(N10,N30,N50) -> 731 | BB10: =SUM(O10,O30,O50) -> 129 | BC10: =SUM(P10,P30,P50) -> 0 | BD10: =SUM(Q10,Q30,Q50) -> 0 | BE10: =SUM(AY10:BD10) -> 1933 | BG10: SP | BH10: =SUM(X10,X30,X50) -> 0 | BI10: =SUM(Y10,Y30,Y50) -> 0 | BJ10: =SUM(Z10,Z30,Z50) -> 0 | BK10: =SUM(AA10,AA30,AA50) -> 0 | BL10: =SUM(AB10,AB30,AB50) -> 0 | BM10: =SUM(AC10,AC30,AC50) -> 398 | BN10: =SUM(BH10:BM10) -> 398
B11: SC | C11: 1452 | D11: 11836 | E11: 13601 | F11: 4203 | I11: =SUM(C11:H11) -> 31092 | K11: SC | L11: =INT(C11/52) -> 27 | M11: =INT(D11/52) -> 227 | N11: =INT(E11/52) -> 261 | O11: =INT(F11/52) -> 80 | P11: =INT(G11/52) -> 0 | Q11: =INT(H11/52) -> 0 | R11: =SUM(L11:Q11) -> 595 | T11: SC | U11: =Q12-R11 -> -489 | W11: SC | AD11: =SUM(X11:AC11) -> 0 | AF11: SC | AG11: =L11*28 -> 756 | AH11: =M11*28 -> 6356 | AI11: =N11*28 -> 7308 | AJ11: =O11*28 -> 2240 | AK11: =P11*28 -> 0 | AL11: =Q11*28 -> 0 | AM11: =SUM(AG11:AL11) -> 16660 | AO11: SC | AP11: =X11*2 -> 0 | AQ11: =Y11*2 -> 0 | AR11: =Z11*2 -> 0 | AS11: =AA11*2 -> 0 | AT11: =AB11*2 -> 0 | AU11: =AC11*2 -> 0 | AV11: =SUM(AP11:AU11) -> 0 | AX11: SC | AY11: =SUM(L11,L31,L51) -> 361 | AZ11: =SUM(M11,M31,M51) -> 546 | BA11: =SUM(N11,N31,N51) -> 743 | BB11: =SUM(O11,O31,O51) -> 147 | BC11: =SUM(P11,P31,P51) -> 0 | BD11: =SUM(Q11,Q31,Q51) -> 0 | BE11: =SUM(AY11:BD11) -> 1797 | BG11: SC | BH11: =SUM(X11,X31,X51) -> 0 | BI11: =SUM(Y11,Y31,Y51) -> 0 | BJ11: =SUM(Z11,Z31,Z51) -> 0 | BK11: =SUM(AA11,AA31,AA51) -> 0 | BL11: =SUM(AB11,AB31,AB51) -> 0 | BM11: =SUM(AC11,AC31,AC51) -> 0 | BN11: =SUM(BH11:BM11) -> 0
B12: Total Destino | C12: =SUM(C6:C11) -> 10882 | D12: =SUM(D6:D11) -> 22212 | E12: =SUM(E6:E11) -> 21436 | F12: =SUM(F6:F11) -> 10067 | G12: =SUM(G6:G11) -> 31074 | H12: =SUM(H6:H11) -> 5646 | I12: =SUM(I6:I11) -> 101317 | K12: Total Destino | L12: =SUM(L6:L11) -> 207 | M12: =SUM(M6:M11) -> 424 | N12: =SUM(N6:N11) -> 410 | O12: =SUM(O6:O11) -> 191 | P12: =SUM(P6:P11) -> 595 | Q12: =SUM(Q6:Q11) -> 106 | R12: =SUM(R6:R11) -> 1933 | T12: Total | U12: =SUM(U6:U11) -> 0 | W12: Total Destino | X12: =SUM(X6:X11) -> 0 | Y12: =SUM(Y6:Y11) -> 0 | Z12: =SUM(Z6:Z11) -> 0 | AA12: =SUM(AA6:AA11) -> 0 | AB12: =SUM(AB6:AB11) -> 56 | AC12: =SUM(AC6:AC11) -> 489 | AD12: =SUM(AD6:AD11) -> 545 | AF12: Total Destino | AG12: =SUM(AG6:AG11) -> 5796 | AH12: =SUM(AH6:AH11) -> 11872 | AI12: =SUM(AI6:AI11) -> 11480 | AJ12: =SUM(AJ6:AJ11) -> 5348 | AK12: =SUM(AK6:AK11) -> 16660 | AL12: =SUM(AL6:AL11) -> 2968 | AM12: 1933 | AO12: Total Destino | AP12: =SUM(AP6:AP11) -> 0 | AQ12: =SUM(AQ6:AQ11) -> 0 | AR12: =SUM(AR6:AR11) -> 0 | AS12: =SUM(AS6:AS11) -> 0 | AT12: =SUM(AT6:AT11) -> 112 | AU12: =SUM(AU6:AU11) -> 978 | AV12: =SUM(AV6:AV11) -> 1090 | AX12: Total Destino | AY12: =SUM(AY6:AY11) -> 1563 | AZ12: =SUM(AZ6:AZ11) -> 1491 | BA12: =SUM(BA6:BA11) -> 1734 | BB12: =SUM(BB6:BB11) -> 421 | BC12: =SUM(BC6:BC11) -> 2211 | BD12: =SUM(BD6:BD11) -> 403 | BE12: =SUM(BE6:BE11) -> 7823 | BG12: Total Destino | BH12: =SUM(BH6:BH11) -> 339 | BI12: =SUM(BI6:BI11) -> 0 | BJ12: =SUM(BJ6:BJ11) -> 0 | BK12: =SUM(BK6:BK11) -> 1 | BL12: =SUM(BL6:BL11) -> 352 | BM12: =SUM(BM6:BM11) -> 1394 | BN12: =SUM(BN6:BN11) -> 2086
B14: Movimentação de Contêineres na Cabotagem em 2022 - 20RF | K14: MATRIZ OD CALCULADA SOLVER 20 DC CHEIO | T14: RECEITA POTENCIAL CABOTAGEM SEMANAL 20 DC | AX14: RESUMO SOMA - CONTEINERS CHEIOS (ton) | BG14: RESUMO SOMA - CONTEINERS VAZIOS (ton)
B15: Origem/Destino | C15: AM | D15: CE | E15: PE | F15: BA | G15: SP | H15: SC | I15: Total Origem | K15: Origem/Destino | L15: AM | M15: CE | N15: PE | O15: BA | P15: SP | Q15: SC | R15: Total Origem | T15: Origem/Destino | U15: AM | V15: CE | W15: PE | X15: BA | Y15: SP | Z15: SC | AX15: Origem/Destino | AY15: AM | AZ15: CE | BA15: PE | BB15: BA | BC15: SP | BD15: SC | BE15: Total Origem | BG15: Origem/Destino | BH15: AM | BI15: CE | BJ15: PE | BK15: BA | BL15: SP | BM15: SC | BN15: Total Origem
B16: AM | E16: 1 | F16: 2 | I16: =SUM(C16:H16) -> 3 | K16: AM | L16: =INT(C16/52) -> 0 | M16: =INT(D16/52) -> 0 | N16: =INT(E16/52) -> 0 | O16: =INT(F16/52) -> 0 | P16: =INT(G16/52) -> 0 | Q16: =INT(H16/52) -> 0 | R16: =SUM(L16:Q16) -> 0 | T16: AM | U16: =L6*C76 -> 0 | V16: =M6*D76 -> #NAME? | W16: =N6*E76 -> #NAME? | X16: =O6*F76 -> #NAME? | Y16: =P6*G76 -> #NAME? | Z16: =Q6*H76 -> #NAME? | AX16: AM | AY16: =SUM(AG6,AG26,AG46) -> 0 | AZ16: =SUM(AH6,AH26,AH46) -> 4172 | BA16: =SUM(AI6,AI26,AI46) -> 4592 | BB16: =SUM(AJ6,AJ26,AJ46) -> 1848 | BC16: =SUM(AK6,AK26,AK46) -> 30968 | BD16: =SUM(AL6,AL26,AL46) -> 3192 | BE16: =SUM(AY16:BD16) -> 44772 | BG16: AM | BH16: =SUM(AP6,AP26,AP46) -> 0 | BI16: =SUM(AQ6,AQ26,AQ46) -> 0 | BJ16: =SUM(AR6,AR26,AR46) -> 0 | BK16: =SUM(AS6,AS26,AS46) -> 0 | BL16: =SUM(AT6,AT26,AT46) -> 112 | BM16: =SUM(AU6,AU26,AU46) -> 886 | BN16: =SUM(BH16:BM16) -> 998
B17: CE | I17: =SUM(C17:H17) -> 0 | K17: CE | L17: =INT(C17/52) -> 0 | M17: =INT(D17/52) -> 0 | N17: =INT(E17/52) -> 0 | O17: =INT(F17/52) -> 0 | P17: =INT(G17/52) -> 0 | Q17: =INT(H17/52) -> 0 | R17: =SUM(L17:Q17) -> 0 | T17: CE | U17: =L7*C77 -> #NAME? | V17: =M7*D77 -> 0 | W17: =N7*E77 -> #NAME? | X17: =O7*F77 -> #NAME? | Y17: =P7*G77 -> #NAME? | Z17: =Q7*H77 -> #NAME? | AX17: CE | AY17: =SUM(AG7,AG27,AG47) -> 7168 | AZ17: =SUM(AH7,AH27,AH47) -> 0 | BA17: =SUM(AI7,AI27,AI47) -> 1456 | BB17: =SUM(AJ7,AJ27,AJ47) -> 280 | BC17: =SUM(AK7,AK27,AK47) -> 9240 | BD17: =SUM(AL7,AL27,AL47) -> 3892 | BE17: =SUM(AY17:BD17) -> 22036 | BG17: CE | BH17: =SUM(AP7,AP27,AP47) -> 1356 | BI17: =SUM(AQ7,AQ27,AQ47) -> 0 | BJ17: =SUM(AR7,AR27,AR47) -> 0 | BK17: =SUM(AS7,AS27,AS47) -> 0 | BL17: =SUM(AT7,AT27,AT47) -> 44 | BM17: =SUM(AU7,AU27,AU47) -> 1212 | BN17: =SUM(BH17:BM17) -> 2612
B18: PE | D18: 3 | G18: 1 | H18: 4 | I18: =SUM(C18:H18) -> 8 | K18: PE | L18: =INT(C18/52) -> 0 | M18: =INT(D18/52) -> 0 | N18: =INT(E18/52) -> 0 | O18: =INT(F18/52) -> 0 | P18: =INT(G18/52) -> 0 | Q18: =INT(H18/52) -> 0 | R18: =SUM(L18:Q18) -> 0 | T18: PE | U18: =L8*C78 -> #NAME? | V18: =M8*D78 -> #NAME? | W18: =N8*E78 -> 0 | X18: =O8*F78 -> #NAME? | Y18: =P8*G78 -> #NAME? | Z18: =Q8*H78 -> #NAME? | AX18: PE | AY18: =SUM(AG8,AG28,AG48) -> 11340 | AZ18: =SUM(AH8,AH28,AH48) -> 3696 | BA18: =SUM(AI8,AI28,AI48) -> 0 | BB18: =SUM(AJ8,AJ28,AJ48) -> 1932 | BC18: =SUM(AK8,AK28,AK48) -> 9800 | BD18: =SUM(AL8,AL28,AL48) -> 2716 | BE18: =SUM(AY18:BD18) -> 29484 | BG18: PE | BH18: =SUM(AP8,AP28,AP48) -> 0 | BI18: =SUM(AQ8,AQ28,AQ48) -> 0 | BJ18: =SUM(AR8,AR28,AR48) -> 0 | BK18: =SUM(AS8,AS28,AS48) -> 4 | BL18: =SUM(AT8,AT28,AT48) -> 1140 | BM18: =SUM(AU8,AU28,AU48) -> 1368 | BN18: =SUM(BH18:BM18) -> 2512
B19: RJ | D19: 4 | E19: 2 | G19: 2 | H19: 2 | I19: =SUM(C19:H19) -> 10 | K19: BA | L19: =INT(C19/52) -> 0 | M19: =INT(D19/52) -> 0 | N19: =INT(E19/52) -> 0 | O19: =INT(F19/52) -> 0 | P19: =INT(G19/52) -> 0 | Q19: =INT(H19/52) -> 0 | R19: =SUM(L19:Q19) -> 0 | T19: BA | U19: =L9*C79 -> #NAME? | V19: =M9*D79 -> #NAME? | W19: =N9*E79 -> #NAME? | X19: =O9*F79 -> 0 | Y19: =P9*G79 -> 0 | Z19: =Q9*H79 -> #NAME? | AX19: BA | AY19: =SUM(AG9,AG29,AG49) -> 2044 | AZ19: =SUM(AH9,AH29,AH49) -> 1652 | BA19: =SUM(AI9,AI29,AI49) -> 1232 | BB19: =SUM(AJ9,AJ29,AJ49) -> 0 | BC19: =SUM(AK9,AK29,AK49) -> 11900 | BD19: =SUM(AL9,AL29,AL49) -> 1484 | BE19: =SUM(AY19:BD19) -> 18312 | BG19: BA | BH19: =SUM(AP9,AP29,AP49) -> 0 | BI19: =SUM(AQ9,AQ29,AQ49) -> 0 | BJ19: =SUM(AR9,AR29,AR49) -> 0 | BK19: =SUM(AS9,AS29,AS49) -> 0 | BL19: =SUM(AT9,AT29,AT49) -> 0 | BM19: =SUM(AU9,AU29,AU49) -> 0 | BN19: =SUM(BH19:BM19) -> 0
B20: SP | D20: 17 | E20: 16 | F20: 2 | I20: =SUM(C20:H20) -> 35 | K20: SP | L20: =INT(C20/52) -> 0 | M20: =INT(D20/52) -> 0 | N20: =INT(E20/52) -> 0 | O20: =INT(F20/52) -> 0 | P20: =INT(G20/52) -> 0 | Q20: =INT(H20/52) -> 0 | R20: =SUM(L20:Q20) -> 0 | T20: SP | U20: =L10*C80 -> #NAME? | V20: =M10*D80 -> #NAME? | W20: =N10*E80 -> #NAME? | X20: =O10*F80 -> #NAME? | Y20: =P10*G80 -> 0 | Z20: =Q10*H80 -> 0 | AX20: SP | AY20: =SUM(AG10,AG30,AG50) -> 13104 | AZ20: =SUM(AH10,AH30,AH50) -> 16940 | BA20: =SUM(AI10,AI30,AI50) -> 20468 | BB20: =SUM(AJ10,AJ30,AJ50) -> 3612 | BC20: =SUM(AK10,AK30,AK50) -> 0 | BD20: =SUM(AL10,AL30,AL50) -> 0 | BE20: =SUM(AY20:BD20) -> 54124 | BG20: SP | BH20: =SUM(AP10,AP30,AP50) -> 0 | BI20: =SUM(AQ10,AQ30,AQ50) -> 0 | BJ20: =SUM(AR10,AR30,AR50) -> 0 | BK20: =SUM(AS10,AS30,AS50) -> 0 | BL20: =SUM(AT10,AT30,AT50) -> 0 | BM20: =SUM(AU10,AU30,AU50) -> 1132 | BN20: =SUM(BH20:BM20) -> 1132
B21: SC | D21: 7 | E21: 9 | I21: =SUM(C21:H21) -> 16 | K21: SC | L21: =INT(C21/52) -> 0 | M21: =INT(D21/52) -> 0 | N21: =INT(E21/52) -> 0 | O21: =INT(F21/52) -> 0 | P21: =INT(G21/52) -> 0 | Q21: =INT(H21/52) -> 0 | R21: =SUM(L21:Q21) -> 0 | T21: SC | U21: =L11*C81 -> #NAME? | V21: =M11*D81 -> #NAME? | W21: =N11*E81 -> #NAME? | X21: =O11*F81 -> #NAME? | Y21: =P11*G81 -> 0 | Z21: =Q11*H81 -> 0 | AX21: SC | AY21: =SUM(AG11,AG31,AG51) -> 10108 | AZ21: =SUM(AH11,AH31,AH51) -> 15288 | BA21: =SUM(AI11,AI31,AI51) -> 20804 | BB21: =SUM(AJ11,AJ31,AJ51) -> 4116 | BC21: =SUM(AK11,AK31,AK51) -> 0 | BD21: =SUM(AL11,AL31,AL51) -> 0 | BE21: =SUM(AY21:BD21) -> 50316 | BG21: SC | BH21: =SUM(AP11,AP31,AP51) -> 0 | BI21: =SUM(AQ11,AQ31,AQ51) -> 0 | BJ21: =SUM(AR11,AR31,AR51) -> 0 | BK21: =SUM(AS11,AS31,AS51) -> 0 | BL21: =SUM(AT11,AT31,AT51) -> 0 | BM21: =SUM(AU11,AU31,AU51) -> 0 | BN21: =SUM(BH21:BM21) -> 0
B22: Total Destino | C22: =SUM(C16:C21) -> 0 | D22: =SUM(D16:D21) -> 31 | E22: =SUM(E16:E21) -> 28 | F22: =SUM(F16:F21) -> 4 | G22: =SUM(G16:G21) -> 3 | H22: =SUM(H16:H21) -> 6 | I22: =SUM(I16:I21) -> 72 | K22: Total Destino | L22: =SUM(L16:L21) -> 0 | M22: =SUM(M16:M21) -> 0 | N22: =SUM(N16:N21) -> 0 | O22: =SUM(O16:O21) -> 0 | P22: =SUM(P16:P21) -> 0 | Q22: =SUM(Q16:Q21) -> 0 | R22: =SUM(R16:R21) -> 0 | Z22: $ RECEITA SEM. | AA22: =SUM(U16:Z21) -> #NAME? | AX22: Total Destino | AY22: =SUM(AY16:AY21) -> 43764 | AZ22: =SUM(AZ16:AZ21) -> 41748 | BA22: =SUM(BA16:BA21) -> 48552 | BB22: =SUM(BB16:BB21) -> 11788 | BC22: =SUM(BC16:BC21) -> 61908 | BD22: =SUM(BD16:BD21) -> 11284 | BE22: =SUM(BE16:BE21) -> 219044 | BG22: Total Destino | BH22: =SUM(BH16:BH21) -> 1356 | BI22: =SUM(BI16:BI21) -> 0 | BJ22: =SUM(BJ16:BJ21) -> 0 | BK22: =SUM(BK16:BK21) -> 4 | BL22: =SUM(BL16:BL21) -> 1296 | BM22: =SUM(BM16:BM21) -> 4598 | BN22: =SUM(BN16:BN21) -> 7254
B24: Movimentação de Contêineres na Cabotagem em 2022 - 40HC | K24: Movimentação de Contêineres na Cabotagem em 2022 - 40HC | T24: Imbalance 40HC | W24: MATRIZ OD 40HC VAZIOS | AF24: MATRIZ OD 40 HC CHEIOS - TONELADAS | AO24: MATRIZ OD 40 HC VAZIOS - TONELADAS | AX24: RESUMO SOMA - CONTEINERS CHEIOS (TEUs) | BG24: RESUMO SOMA - CONTEINERS VAZIOS (TEUs)
B25: Origem/Destino | C25: AM | D25: CE | E25: PE | F25: BA | G25: SP | H25: SC | I25: Total Origem | K25: Origem/Destino | L25: AM | M25: CE | N25: PE | O25: BA | P25: SP | Q25: SC | R25: Total Origem | T25: Porto | U25: IMB | W25: Origem/Destino | X25: AM | Y25: CE | Z25: PE | AA25: BA | AB25: SP | AC25: SC | AD25: Total Origem | AF25: Origem/Destino | AG25: AM | AH25: CE | AI25: PE | AJ25: BA | AK25: SP | AL25: SC | AM25: Total Origem | AO25: Origem/Destino | AP25: AM | AQ25: CE | AR25: PE | AS25: BA | AT25: SP | AU25: SC | AV25: Total Origem | AX25: Origem/Destino | AY25: AM | AZ25: CE | BA25: PE | BB25: BA | BC25: SP | BD25: SC | BE25: Total Origem | BG25: Origem/Destino | BH25: AM | BI25: CE | BJ25: PE | BK25: BA | BL25: SP | BM25: SC | BN25: Total Origem
B26: AM | D26: 6066 | E26: 8232 | F26: 3166 | G26: 54983 | H26: 5501 | I26: =SUM(C26:H26) -> 77948 | K26: AM | L26: =INT(C26/52) -> 0 | M26: =INT(D26/52) -> 116 | N26: =INT(E26/52) -> 158 | O26: =INT(F26/52) -> 60 | P26: =INT(G26/52) -> 1057 | Q26: =INT(H26/52) -> 105 | R26: =SUM(L26:Q26) -> 1496 | T26: AM | U26: =L32-R26 -> -339 | W26: AM | AD26: =SUM(X26:AC26) -> 0 | AF26: AM | AG26: =L26*28 -> 0 | AH26: =M26*28 -> 3248 | AI26: =N26*28 -> 4424 | AJ26: =O26*28 -> 1680 | AK26: =P26*28 -> 29596 | AL26: =Q26*28 -> 2940 | AM26: =SUM(AG26:AL26) -> 41888 | AO26: AM | AP26: =X26*4 -> 0 | AQ26: =Y26*4 -> 0 | AR26: =Z26*4 -> 0 | AS26: =AA26*4 -> 0 | AT26: =AB26*4 -> 0 | AU26: =AC26*4 -> 0 | AV26: =SUM(AP26:AU26) -> 0 | AX26: AM | AY26: =SUM(L6,2*L26,2*L46) -> 0 | AZ26: =SUM(M6,2*M26,2*M46) -> 265 | BA26: =SUM(N6,2*N26,2*N46) -> 322 | BB26: =SUM(O6,2*O26,2*O46) -> 126 | BC26: =SUM(P6,2*P26,2*P46) -> 2164 | BD26: =SUM(Q6,2*Q26,2*Q46) -> 219 | BE26: =SUM(AY26:BD26) -> 3096 | BG26: AM | BH26: =SUM(X6,2*X26,2*X46) -> 0 | BI26: =SUM(Y6,2*Y26,2*Y46) -> 0 | BJ26: =SUM(Z6,2*Z26,2*Z46) -> 0 | BK26: =SUM(AA6,2*AA26,2*AA46) -> 0 | BL26: =SUM(AB6,2*AB26,2*AB46) -> 56 | BM26: =SUM(AC6,2*AC26,2*AC46) -> 443 | BN26: =SUM(BH26:BM26) -> 499
B27: CE | C27: 10303 | E27: 2481 | F27: 101 | G27: 7856 | H27: 3188 | I27: =SUM(C27:H27) -> 23929 | K27: CE | L27: =INT(C27/52) -> 198 | M27: =INT(D27/52) -> 0 | N27: =INT(E27/52) -> 47 | O27: =INT(F27/52) -> 1 | P27: =INT(G27/52) -> 151 | Q27: =INT(H27/52) -> 61 | R27: =SUM(L27:Q27) -> 458 | T27: CE | U27: =M32-R27 -> 486 | W27: CE | X27: 339 | AC27: =U27-X27 -> 147 | AD27: =SUM(X27:AC27) -> 486 | AF27: CE | AG27: =L27*28 -> 5544 | AH27: =M27*28 -> 0 | AI27: =N27*28 -> 1316 | AJ27: =O27*28 -> 28 | AK27: =P27*28 -> 4228 | AL27: =Q27*28 -> 1708 | AM27: =SUM(AG27:AL27) -> 12824 | AO27: CE | AP27: =X27*4 -> 1356 | AQ27: =Y27*2 -> 0 | AR27: =Z27*2 -> 0 | AS27: =AA27*2 -> 0 | AT27: =AB27*4 -> 0 | AU27: =AC27*4 -> 588 | AV27: =SUM(AP27:AU27) -> 1944 | AX27: CE | AY27: =SUM(L7,2*L27,2*L47) -> 456 | AZ27: =SUM(M7,2*M27,2*M47) -> 0 | BA27: =SUM(N7,2*N27,2*N47) -> 99 | BB27: =SUM(O7,2*O27,2*O47) -> 11 | BC27: =SUM(P7,2*P27,2*P47) -> 485 | BD27: =SUM(Q7,2*Q27,2*Q47) -> 201 | BE27: =SUM(AY27:BD27) -> 1252 | BG27: CE | BH27: =SUM(X7,2*X27,2*X47) -> 678 | BI27: =SUM(Y7,2*Y27,2*Y47) -> 0 | BJ27: =SUM(Z7,2*Z27,2*Z47) -> 0 | BK27: =SUM(AA7,2*AA27,2*AA47) -> 0 | BL27: =SUM(AB7,2*AB27,2*AB47) -> 22 | BM27: =SUM(AC7,2*AC27,2*AC47) -> 606 | BN27: =SUM(BH27:BM27) -> 1306
B28: PE | C28: 17515 | D28: 5046 | F28: 652 | G28: 9764 | H28: 4287 | I28: =SUM(C28:H28) -> 37264 | K28: PE | L28: =INT(C28/52) -> 336 | M28: =INT(D28/52) -> 97 | N28: =INT(E28/52) -> 0 | O28: =INT(F28/52) -> 12 | P28: =INT(G28/52) -> 187 | Q28: =INT(H28/52) -> 82 | R28: =SUM(L28:Q28) -> 714 | T28: PE | U28: =N32-R28 -> 464 | W28: PE | AB28: =U28-AC28 -> 176 | AC28: =U29+U28 -> 288 | AD28: =SUM(X28:AC28) -> 464 | AF28: PE | AG28: =L28*28 -> 9408 | AH28: =M28*28 -> 2716 | AI28: =N28*28 -> 0 | AJ28: =O28*28 -> 336 | AK28: =P28*28 -> 5236 | AL28: =Q28*28 -> 2296 | AM28: =SUM(AG28:AL28) -> 19992 | AO28: PE | AP28: =X28*4 -> 0 | AQ28: =Y28*2 -> 0 | AR28: =Z28*2 -> 0 | AS28: =AA28*2 -> 0 | AT28: =AB28*4 -> 704 | AU28: =AC28*4 -> 1152 | AV28: =SUM(AP28:AU28) -> 1856 | AX28: PE | AY28: =SUM(L8,2*L28,2*L48) -> 771 | AZ28: =SUM(M8,2*M28,2*M48) -> 236 | BA28: =SUM(N8,2*N28,2*N48) -> 0 | BB28: =SUM(O8,2*O28,2*O48) -> 81 | BC28: =SUM(P8,2*P28,2*P48) -> 537 | BD28: =SUM(Q8,2*Q28,2*Q48) -> 179 | BE28: =SUM(AY28:BD28) -> 1804 | BG28: PE | BH28: =SUM(X8,2*X28,2*X48) -> 0 | BI28: =SUM(Y8,2*Y28,2*Y48) -> 0 | BJ28: =SUM(Z8,2*Z28,2*Z48) -> 0 | BK28: =SUM(AA8,2*AA28,2*AA48) -> 2 | BL28: =SUM(AB8,2*AB28,2*AB48) -> 570 | BM28: =SUM(AC8,2*AC28,2*AC48) -> 684 | BN28: =SUM(BH28:BM28) -> 1256
B29: BA | C29: 3252 | D29: 2029 | E29: 1364 | G29: 10648 | H29: 2531 | I29: =SUM(C29:H29) -> 19824 | K29: BA | L29: =INT(C29/52) -> 62 | M29: =INT(D29/52) -> 39 | N29: =INT(E29/52) -> 26 | O29: =INT(F29/52) -> 0 | P29: =INT(G29/52) -> 204 | Q29: =INT(H29/52) -> 48 | R29: =SUM(L29:Q29) -> 379 | T29: BA | U29: =O32-R29 -> -176 | W29: BA | AD29: =SUM(X29:AC29) -> 0 | AF29: BA | AG29: =L29*28 -> 1736 | AH29: =M29*28 -> 1092 | AI29: =N29*28 -> 728 | AJ29: =O29*28 -> 0 | AK29: =P29*28 -> 5712 | AL29: =Q29*28 -> 1344 | AM29: =SUM(AG29:AL29) -> 10612 | AO29: BA | AP29: =X29*4 -> 0 | AQ29: =Y29*2 -> 0 | AR29: =Z29*2 -> 0 | AS29: =AA29*2 -> 0 | AT29: =AB29*4 -> 0 | AU29: =AC29*4 -> 0 | AV29: =SUM(AP29:AU29) -> 0 | AX29: BA | AY29: =SUM(L9,2*L29,2*L49) -> 139 | AZ29: =SUM(M9,2*M29,2*M49) -> 104 | BA29: =SUM(N9,2*N29,2*N49) -> 76 | BB29: =SUM(O9,2*O29,2*O49) -> 0 | BC29: =SUM(P9,2*P29,2*P49) -> 641 | BD29: =SUM(Q9,2*Q29,2*Q49) -> 101 | BE29: =SUM(AY29:BD29) -> 1061 | BG29: BA | BH29: =SUM(X9,2*X29,2*X49) -> 0 | BI29: =SUM(Y9,2*Y29,2*Y49) -> 0 | BJ29: =SUM(Z9,2*Z29,2*Z49) -> 0 | BK29: =SUM(AA9,2*AA29,2*AA49) -> 0 | BL29: =SUM(AB9,2*AB29,2*AB49) -> 0 | BM29: =SUM(AC9,2*AC29,2*AC49) -> 0 | BN29: =SUM(BH29:BM29) -> 0
B30: SP | C30: 18041 | D30: 22859 | E30: 29225 | F30: 4383 | I30: =SUM(C30:H30) -> 74508 | K30: SP | L30: =INT(C30/52) -> 346 | M30: =INT(D30/52) -> 439 | N30: =INT(E30/52) -> 562 | O30: =INT(F30/52) -> 84 | P30: =INT(G30/52) -> 0 | Q30: =INT(H30/52) -> 0 | R30: =SUM(L30:Q30) -> 1431 | T30: SP | U30: =P32-R30 -> 168 | W30: SP | AC30: =U30 -> 168 | AD30: =SUM(X30:AC30) -> 168 | AF30: SP | AG30: =L30*28 -> 9688 | AH30: =M30*28 -> 12292 | AI30: =N30*28 -> 15736 | AJ30: =O30*28 -> 2352 | AK30: =P30*28 -> 0 | AL30: =Q30*28 -> 0 | AM30: =SUM(AG30:AL30) -> 40068 | AO30: SP | AP30: =X30*4 -> 0 | AQ30: =Y30*2 -> 0 | AR30: =Z30*2 -> 0 | AS30: =AA30*2 -> 0 | AT30: =AB30*4 -> 0 | AU30: =AC30*4 -> 672 | AV30: =SUM(AP30:AU30) -> 672 | AX30: SP | AY30: =SUM(L10,2*L30,2*L50) -> 858 | AZ30: =SUM(M10,2*M30,2*M50) -> 1088 | BA30: =SUM(N10,2*N30,2*N50) -> 1336 | BB30: =SUM(O10,2*O30,2*O50) -> 219 | BC30: =SUM(P10,2*P30,2*P50) -> 0 | BD30: =SUM(Q10,2*Q30,2*Q50) -> 0 | BE30: =SUM(AY30:BD30) -> 3501 | BG30: SP | BH30: =SUM(X10,2*X30,2*X50) -> 0 | BI30: =SUM(Y10,2*Y30,2*Y50) -> 0 | BJ30: =SUM(Z10,2*Z30,2*Z50) -> 0 | BK30: =SUM(AA10,2*AA30,2*AA50) -> 0 | BL30: =SUM(AB10,2*AB30,2*AB50) -> 0 | BM30: =SUM(AC10,2*AC30,2*AC50) -> 566 | BN30: =SUM(BH30:BM30) -> 566
B31: SC | C31: 11210 | D31: 13198 | E31: 20046 | F31: 2406 | I31: =SUM(C31:H31) -> 46860 | K31: SC | L31: =INT(C31/52) -> 215 | M31: =INT(D31/52) -> 253 | N31: =INT(E31/52) -> 385 | O31: =INT(F31/52) -> 46 | P31: =INT(G31/52) -> 0 | Q31: =INT(H31/52) -> 0 | R31: =SUM(L31:Q31) -> 899 | T31: SC | U31: =Q32-R31 -> -603 | W31: SC | AD31: =SUM(X31:AC31) -> 0 | AF31: SC | AG31: =L31*28 -> 6020 | AH31: =M31*28 -> 7084 | AI31: =N31*28 -> 10780 | AJ31: =O31*28 -> 1288 | AK31: =P31*28 -> 0 | AL31: =Q31*28 -> 0 | AM31: =SUM(AG31:AL31) -> 25172 | AO31: SC | AP31: =X31*4 -> 0 | AQ31: =Y31*2 -> 0 | AR31: =Z31*2 -> 0 | AS31: =AA31*2 -> 0 | AT31: =AB31*4 -> 0 | AU31: =AC31*4 -> 0 | AV31: =SUM(AP31:AU31) -> 0 | AX31: SC | AY31: =SUM(L11,2*L31,2*L51) -> 695 | AZ31: =SUM(M11,2*M31,2*M51) -> 865 | BA31: =SUM(N11,2*N31,2*N51) -> 1225 | BB31: =SUM(O11,2*O31,2*O51) -> 214 | BC31: =SUM(P11,2*P31,2*P51) -> 0 | BD31: =SUM(Q11,2*Q31,2*Q51) -> 0 | BE31: =SUM(AY31:BD31) -> 2999 | BG31: SC | BH31: =SUM(X11,2*X31,2*X51) -> 0 | BI31: =SUM(Y11,2*Y31,2*Y51) -> 0 | BJ31: =SUM(Z11,2*Z31,2*Z51) -> 0 | BK31: =SUM(AA11,2*AA31,2*AA51) -> 0 | BL31: =SUM(AB11,2*AB31,2*AB51) -> 0 | BM31: =SUM(AC11,2*AC31,2*AC51) -> 0 | BN31: =SUM(BH31:BM31) -> 0
B32: Total Destino | C32: =SUM(C26:C31) -> 60321 | D32: =SUM(D26:D31) -> 49198 | E32: =SUM(E26:E31) -> 61348 | F32: =SUM(F26:F31) -> 10708 | G32: =SUM(G26:G31) -> 83251 | H32: =SUM(H26:H31) -> 15507 | I32: =SUM(I26:I31) -> 280333 | K32: Total Destino | L32: =SUM(L26:L31) -> 1157 | M32: =SUM(M26:M31) -> 944 | N32: =SUM(N26:N31) -> 1178 | O32: =SUM(O26:O31) -> 203 | P32: =SUM(P26:P31) -> 1599 | Q32: =SUM(Q26:Q31) -> 296 | R32: =SUM(R26:R31) -> 5377 | T32: Total | U32: =SUM(U26:U31) -> 0 | W32: Total Destino | X32: =SUM(X26:X31) -> 339 | Y32: =SUM(Y26:Y31) -> 0 | Z32: =SUM(Z26:Z31) -> 0 | AA32: =SUM(AA26:AA31) -> 0 | AB32: =SUM(AB26:AB31) -> 176 | AC32: =SUM(AC26:AC31) -> 603 | AD32: =SUM(AD26:AD31) -> 1118 | AF32: Total Destino | AG32: =SUM(AG26:AG31) -> 32396 | AH32: =SUM(AH26:AH31) -> 26432 | AI32: =SUM(AI26:AI31) -> 32984 | AJ32: =SUM(AJ26:AJ31) -> 5684 | AK32: =SUM(AK26:AK31) -> 44772 | AL32: =SUM(AL26:AL31) -> 8288 | AM32: 1933 | AO32: Total Destino | AP32: =SUM(AP26:AP31) -> 1356 | AQ32: =SUM(AQ26:AQ31) -> 0 | AR32: =SUM(AR26:AR31) -> 0 | AS32: =SUM(AS26:AS31) -> 0 | AT32: =SUM(AT26:AT31) -> 704 | AU32: =SUM(AU26:AU31) -> 2412 | AV32: =SUM(AV26:AV31) -> 4472 | AX32: Total Destino | AY32: =SUM(AY26:AY31) -> 2919 | AZ32: =SUM(AZ26:AZ31) -> 2558 | BA32: =SUM(BA26:BA31) -> 3058 | BB32: =SUM(BB26:BB31) -> 651 | BC32: =SUM(BC26:BC31) -> 3827 | BD32: =SUM(BD26:BD31) -> 700 | BE32: =SUM(BE26:BE31) -> 13713 | BG32: Total Destino | BH32: =SUM(BH26:BH31) -> 678 | BI32: =SUM(BI26:BI31) -> 0 | BJ32: =SUM(BJ26:BJ31) -> 0 | BK32: =SUM(BK26:BK31) -> 2 | BL32: =SUM(BL26:BL31) -> 648 | BM32: =SUM(BM26:BM31) -> 2299 | BN32: =SUM(BN26:BN31) -> 3627
B34: Movimentação de Contêineres na Cabotagem em 2022 - 40RH | K34: MATRIZ OD CALCULADA SOLVER 40HC CHEIO | T34: RECEITA POTENCIAL CABOTAGEM SEMANAL 20 DC
B35: Origem/Destino | C35: AM | D35: CE | E35: PE | F35: BA | G35: SP | H35: SC | I35: Total Origem | K35: Origem/Destino | L35: AM | M35: CE | N35: PE | O35: BA | P35: SP | Q35: SC | R35: Total Origem | T35: Origem/Destino | U35: AM | V35: CE | W35: PE | X35: BA | Y35: SP | Z35: SC
B36: AM | D36: 12 | E36: 6 | F36: 1 | G36: 58 | H36: 46 | I36: =SUM(C36:H36) -> 123 | K36: AM | R36: =SUM(L36:Q36) -> 0 | T36: AM | U36: =L26*C76 -> 0 | V36: =M26*D76 -> #NAME? | W36: =N26*E76 -> #NAME? | X36: =O26*F76 -> #NAME? | Y36: =P26*G76 -> #NAME? | Z36: =Q26*H76 -> #NAME?
B37: CE | C37: 155 | E37: 17 | F37: 2 | G37: 215 | H37: 78 | I37: =SUM(C37:H37) -> 467 | K37: CE | R37: =SUM(L37:Q37) -> 0 | T37: CE | U37: =L27*C77 -> #NAME? | V37: =M27*D77 -> 0 | W37: =N27*E77 -> #NAME? | X37: =O27*F77 -> #NAME? | Y37: =P27*G77 -> #NAME? | Z37: =Q27*H77 -> #NAME?
B38: PE | C38: 1593 | D38: 407 | F38: 1 | G38: 40 | H38: 9 | I38: =SUM(C38:H38) -> 2050 | K38: PE | R38: =SUM(L38:Q38) -> 0 | T38: PE | U38: =L28*C78 -> #NAME? | V38: =M28*D78 -> #NAME? | W38: =N28*E78 -> 0 | X38: =O28*F78 -> #NAME? | Y38: =P28*G78 -> #NAME? | Z38: =Q28*H78 -> #NAME?
B39: BA | C39: 214 | D39: 327 | E39: 339 | G39: 644 | H39: 24 | I39: =SUM(C39:H39) -> 1548 | K39: BA | R39: =SUM(L39:Q39) -> 0 | T39: BA | U39: =L29*C79 -> #NAME? | V39: =M29*D79 -> #NAME? | W39: =N29*E79 -> #NAME? | X39: =O29*F79 -> 0 | Y39: =P29*G79 -> 0 | Z39: =Q29*H79 -> #NAME?
B40: SP | C40: 2308 | D40: 2321 | E40: 2268 | F40: 331 | I40: =SUM(C40:H40) -> 7228 | K40: SP | R40: =SUM(L40:Q40) -> 0 | T40: SP | U40: =L30*C80 -> #NAME? | V40: =M30*D80 -> #NAME? | W40: =N30*E80 -> #NAME? | X40: =O30*F80 -> #NAME? | Y40: =P30*G80 -> 0 | Z40: =Q30*H80 -> 0
B41: SC | C41: 6226 | D41: 3479 | E41: 5045 | F41: 1134 | I41: =SUM(C41:H41) -> 15884 | K41: SC | R41: =SUM(L41:Q41) -> 0 | T41: SC | U41: =L31*C81 -> #NAME? | V41: =M31*D81 -> #NAME? | W41: =N31*E81 -> #NAME? | X41: =O31*F81 -> #NAME? | Y41: =P31*G81 -> 0 | Z41: =Q31*H81 -> 0
B42: Total Destino | C42: =SUM(C36:C41) -> 10496 | D42: =SUM(D36:D41) -> 6546 | E42: =SUM(E36:E41) -> 7675 | F42: =SUM(F36:F41) -> 1469 | G42: =SUM(G36:G41) -> 957 | H42: =SUM(H36:H41) -> 157 | I42: =SUM(I36:I41) -> 27300 | K42: Total Destino | L42: =SUM(L36:L41) -> 0 | M42: =SUM(M36:M41) -> 0 | N42: =SUM(N36:N41) -> 0 | O42: =SUM(O36:O41) -> 0 | P42: =SUM(P36:P41) -> 0 | Q42: =SUM(Q36:Q41) -> 0 | R42: =SUM(R36:R41) -> 0 | Z42: $ RECEITA SEM. | AA42: =SUM(U36:Z41) -> #NAME?
B44: Movimentação de Contêineres na Cabotagem em 2022 - unidades | K44: Movimentação de Contêineres na Cabotagem em 2022 - 40RH | T44: Imbalance 40RH | W44: MATRIZ OD 40 RH VAZIOS | AF44: MATRIZ OD 40 RH CHEIOS - TONELADAS | AO44: MATRIZ OD 40 RH VAZIOS - TONELADAS | AX44: MATRIZ TEUs VAZIOS | BG44: MATRIZ TEUs CHEIOS | BP44: MATRIZ TEUs VAZIOS
B45: Origem/Destino | C45: AM | D45: CE | E45: PE | F45: BA | G45: SP | H45: SC | I45: Total Origem | K45: Origem/Destino | L45: AM | M45: CE | N45: PE | O45: BA | P45: SP | Q45: SC | R45: Total Origem | T45: Porto | U45: IMB | W45: Origem/Destino | X45: AM | Y45: CE | Z45: PE | AA45: BA | AB45: SP | AC45: SC | AD45: Total Origem | AF45: Origem/Destino | AG45: AM | AH45: CE | AI45: PE | AJ45: BA | AK45: SP | AL45: SC | AM45: Total Origem | AO45: Origem/Destino | AP45: AM | AQ45: CE | AR45: PE | AS45: BA | AT45: SP | AU45: SC | AV45: Total Origem | AX45: Origem/Destino | AY45: AM | AZ45: CE | BA45: PE | BB45: BA | BC45: SP | BD45: SC | BE45: Total Origem | BG45: Origem/Destino | BH45: AM | BI45: CE | BJ45: PE | BK45: BA | BL45: SP | BM45: SC | BN45: Total Origem | BP45: Origem/Destino | BQ45: AM | BR45: CE | BS45: PE | BT45: BA | BU45: SP | BV45: SC | BW45: Total Origem
B46: AM | C46: =C6+C16+C26+C36 -> 0 | D46: =D6+D16+D26+D36 -> 7825 | E46: =E6+E16+E26+E36 -> 8552 | F46: =F6+F16+F26+F36 -> 3498 | G46: =G6+G16+G26+G36 -> 57554 | H46: =H6+H16+H26+H36 -> 6022 | I46: =SUM(C46:H46) -> 83451 | K46: AM | L46: =INT(C36/52) -> 0 | M46: =INT(D36/52) -> 0 | N46: =INT(E36/52) -> 0 | O46: =INT(F36/52) -> 0 | P46: =INT(G36/52) -> 1 | Q46: =INT(H36/52) -> 0 | R46: =SUM(L46:Q46) -> 1 | T46: AM | U46: =L52-R46 -> 198 | W46: AM | AC46: =U46-1 -> 197 | AD46: =SUM(X46:AC46) -> 197 | AF46: AM | AG46: =L46*28 -> 0 | AH46: =M46*28 -> 0 | AI46: =N46*28 -> 0 | AJ46: =O46*28 -> 0 | AK46: =P46*28 -> 28 | AL46: =Q46*28 -> 0 | AM46: =SUM(AG46:AL46) -> 28 | AO46: AM | AP46: =X46*4 -> 0 | AQ46: =Y46*4 -> 0 | AR46: =Z46*4 -> 0 | AS46: =AA46*4 -> 0 | AT46: =AB46*4 -> 0 | AU46: =AC46*4 -> 788 | AV46: =SUM(AP46:AU46) -> 788 | AX46: AM | BD46: =(AC46-1)*2 -> 392 | BE46: =SUM(AY46:BD46) -> 392 | BG46: AM | BH46: =L46*28*2 -> 0 | BI46: =M46*28*2 -> 0 | BJ46: =N46*28*2 -> 0 | BK46: =O46*28*2 -> 0 | BL46: =P46*28*2 -> 56 | BM46: =Q46*28*2 -> 0 | BN46: =SUM(BH46:BM46) -> 56 | BP46: AM | BQ46: =AY46*4 -> 0 | BR46: =AZ46*4 -> 0 | BS46: =BA46*4 -> 0 | BT46: =BB46*4 -> 0 | BU46: =BC46*4 -> 0 | BV46: =BD46*4 -> 1568 | BW46: =SUM(BQ46:BV46) -> 1568
B47: CE | C47: =C7+C17+C27+C37 -> 13384 | D47: =D7+D17+D27+D37 -> 0 | E47: =E7+E17+E27+E37 -> 2780 | F47: =F7+F17+F27+F37 -> 594 | G47: =G7+G17+G27+G37 -> 17206 | H47: =H7+H17+H27+H37 -> 7321 | I47: =SUM(C47:H47) -> 41285 | K47: CE | L47: =INT(C37/52) -> 2 | M47: =INT(D37/52) -> 0 | N47: =INT(E37/52) -> 0 | O47: =INT(F37/52) -> 0 | P47: =INT(G37/52) -> 4 | Q47: =INT(H37/52) -> 1 | R47: =SUM(L47:Q47) -> 7 | T47: CE | U47: =M52-R47 -> 116 | W47: CE | AB47: 11 | AC47: =U47-AB47 -> 105 | AD47: =SUM(X47:AC47) -> 116 | AF47: CE | AG47: =L47*28 -> 56 | AH47: =M47*28 -> 0 | AI47: =N47*28 -> 0 | AJ47: =O47*28 -> 0 | AK47: =P47*28 -> 112 | AL47: =Q47*28 -> 28 | AM47: =SUM(AG47:AL47) -> 196 | AO47: CE | AP47: =X47*4 -> 0 | AQ47: =Y47*4 -> 0 | AR47: =Z47*4 -> 0 | AS47: =AA47*4 -> 0 | AT47: =AB47*4 -> 44 | AU47: =AC47*4 -> 420 | AV47: =SUM(AP47:AU47) -> 464 | AX47: CE | BC47: =11*2 -> 22 | BD47: =(AC47-1)*2 -> 208 | BE47: =SUM(AY47:BD47) -> 230 | BG47: CE | BH47: =L47*28*2 -> 112 | BI47: =M47*28*2 -> 0 | BJ47: =N47*28*2 -> 0 | BK47: =O47*28*2 -> 0 | BL47: =P47*28*2 -> 224 | BM47: =Q47*28*2 -> 56 | BN47: =SUM(BH47:BM47) -> 392 | BP47: CE | BQ47: =AY47*4 -> 0 | BR47: =AZ47*4 -> 0 | BS47: =BA47*4 -> 0 | BT47: =BB47*4 -> 0 | BU47: =BC47*4 -> 88 | BV47: =BD47*4 -> 832 | BW47: =SUM(BQ47:BV47) -> 920
B48: PE | C48: =C8+C18+C28+C38 -> 21147 | D48: =D8+D18+D28+D38 -> 6937 | E48: =E8+E18+E28+E38 -> 0 | F48: =F8+F18+F28+F38 -> 3620 | G48: =G8+G18+G28+G38 -> 18324 | H48: =H8+H18+H28+H38 -> 5127 | I48: =SUM(C48:H48) -> 55155 | K48: PE | L48: =INT(C38/52) -> 30 | M48: =INT(D38/52) -> 7 | N48: =INT(E38/52) -> 0 | O48: =INT(F38/52) -> 0 | P48: =INT(G38/52) -> 0 | Q48: =INT(H38/52) -> 0 | R48: =SUM(L48:Q48) -> 37 | T48: PE | U48: =N52-R48 -> 109 | W48: PE | AA48: 1 | AB48: 109 | AD48: =SUM(X48:AC48) -> 110 | AF48: PE | AG48: =L48*28 -> 840 | AH48: =M48*28 -> 196 | AI48: =N48*28 -> 0 | AJ48: =O48*28 -> 0 | AK48: =P48*28 -> 0 | AL48: =Q48*28 -> 0 | AM48: =SUM(AG48:AL48) -> 1036 | AO48: PE | AP48: =X48*4 -> 0 | AQ48: =Y48*4 -> 0 | AR48: =Z48*4 -> 0 | AS48: =AA48*4 -> 4 | AT48: =AB48*4 -> 436 | AU48: =AC48*4 -> 0 | AV48: =SUM(AP48:AU48) -> 440 | AX48: PE | BB48: =1*2 -> 2 | BC48: =109*2 -> 218 | BE48: =SUM(AY48:BD48) -> 220 | BG48: PE | BH48: =L48*28*2 -> 1680 | BI48: =M48*28*2 -> 392 | BJ48: =N48*28*2 -> 0 | BK48: =O48*28*2 -> 0 | BL48: =P48*28*2 -> 0 | BM48: =Q48*28*2 -> 0 | BN48: =SUM(BH48:BM48) -> 2072 | BP48: PE | BQ48: =AY48*4 -> 0 | BR48: =AZ48*4 -> 0 | BS48: =BA48*4 -> 0 | BT48: =BB48*4 -> 8 | BU48: =BC48*4 -> 872 | BV48: =BD48*4 -> 0 | BW48: =SUM(BQ48:BV48) -> 880
B49: BA | C49: =C9+C19+C29+C39 -> 3873 | D49: =D9+D19+D29+D39 -> 3139 | E49: =E9+E19+E29+E39 -> 2375 | F49: =F9+F19+F29+F39 -> 0 | G49: =G9+G19+G29+G39 -> 22201 | H49: =H9+H19+H29+H39 -> 2846 | I49: =SUM(C49:H49) -> 34434 | K49: BA | L49: =INT(C39/52) -> 4 | M49: =INT(D39/52) -> 6 | N49: =INT(E39/52) -> 6 | O49: =INT(F39/52) -> 0 | P49: =INT(G39/52) -> 12 | Q49: =INT(H39/52) -> 0 | R49: =SUM(L49:Q49) -> 28 | T49: BA | U49: =O52-R49 -> -1 | W49: BA | AD49: =SUM(X49:AC49) -> 0 | AF49: BA | AG49: =L49*28 -> 112 | AH49: =M49*28 -> 168 | AI49: =N49*28 -> 168 | AJ49: =O49*28 -> 0 | AK49: =P49*28 -> 336 | AL49: =Q49*28 -> 0 | AM49: =SUM(AG49:AL49) -> 784 | AO49: BA | AP49: =X49*4 -> 0 | AQ49: =Y49*4 -> 0 | AR49: =Z49*4 -> 0 | AS49: =AA49*4 -> 0 | AT49: =AB49*4 -> 0 | AU49: =AC49*4 -> 0 | AV49: =SUM(AP49:AU49) -> 0 | AX49: BA | BE49: =SUM(AY49:BD49) -> 0 | BG49: BA | BH49: =L49*28*2 -> 224 | BI49: =M49*28*2 -> 336 | BJ49: =N49*28*2 -> 336 | BK49: =O49*28*2 -> 0 | BL49: =P49*28*2 -> 672 | BM49: =Q49*28*2 -> 0 | BN49: =SUM(BH49:BM49) -> 1568 | BP49: BA | BQ49: =AY49*4 -> 0 | BR49: =AZ49*4 -> 0 | BS49: =BA49*4 -> 0 | BT49: =BB49*4 -> 0 | BU49: =BC49*4 -> 0 | BV49: =BD49*4 -> 0 | BW49: =SUM(BQ49:BV49) -> 0
B50: SP | C50: =C10+C20+C30+C40 -> 24407 | D50: =D10+D20+D30+D40 -> 31566 | E50: =E10+E20+E30+E40 -> 38079 | F50: =F10+F20+F30+F40 -> 6793 | G50: =G10+G20+G30+G40 -> 0 | H50: =H10+H20+H30+H40 -> 0 | I50: =SUM(C50:H50) -> 100845 | K50: SP | L50: =INT(C40/52) -> 44 | M50: =INT(D40/52) -> 44 | N50: =INT(E40/52) -> 43 | O50: =INT(F40/52) -> 6 | P50: =INT(G40/52) -> 0 | Q50: =INT(H40/52) -> 0 | R50: =SUM(L50:Q50) -> 137 | T50: SP | U50: =P52-R50 -> -120 | W50: SP | AD50: =SUM(X50:AC50) -> 0 | AF50: SP | AG50: =L50*28 -> 1232 | AH50: =M50*28 -> 1232 | AI50: =N50*28 -> 1204 | AJ50: =O50*28 -> 168 | AK50: =P50*28 -> 0 | AL50: =Q50*28 -> 0 | AM50: =SUM(AG50:AL50) -> 3836 | AO50: SP | AP50: =X50*4 -> 0 | AQ50: =Y50*4 -> 0 | AR50: =Z50*4 -> 0 | AS50: =AA50*4 -> 0 | AT50: =AB50*4 -> 0 | AU50: =AC50*4 -> 0 | AV50: =SUM(AP50:AU50) -> 0 | AX50: SP | BE50: =SUM(AY50:BD50) -> 0 | BG50: SP | BH50: =L50*28*2 -> 2464 | BI50: =M50*28*2 -> 2464 | BJ50: =N50*28*2 -> 2408 | BK50: =O50*28*2 -> 336 | BL50: =P50*28*2 -> 0 | BM50: =Q50*28*2 -> 0 | BN50: =SUM(BH50:BM50) -> 7672 | BP50: SP | BQ50: =AY50*4 -> 0 | BR50: =AZ50*4 -> 0 | BS50: =BA50*4 -> 0 | BT50: =BB50*4 -> 0 | BU50: =BC50*4 -> 0 | BV50: =BD50*4 -> 0 | BW50: =SUM(BQ50:BV50) -> 0
B51: SC | C51: =C11+C21+C31+C41 -> 18888 | D51: =D11+D21+D31+D41 -> 28520 | E51: =E11+E21+E31+E41 -> 38701 | F51: =F11+F21+F31+F41 -> 7743 | G51: =G11+G21+G31+G41 -> 0 | H51: =H11+H21+H31+H41 -> 0 | I51: =SUM(C51:H51) -> 93852 | K51: SC | L51: =INT(C41/52) -> 119 | M51: =INT(D41/52) -> 66 | N51: =INT(E41/52) -> 97 | O51: =INT(F41/52) -> 21 | P51: =INT(G41/52) -> 0 | Q51: =INT(H41/52) -> 0 | R51: =SUM(L51:Q51) -> 303 | T51: SC | U51: =Q52-R51 -> -302 | W51: SC | AD51: =SUM(X51:AC51) -> 0 | AF51: SC | AG51: =L51*28 -> 3332 | AH51: =M51*28 -> 1848 | AI51: =N51*28 -> 2716 | AJ51: =O51*28 -> 588 | AK51: =P51*28 -> 0 | AL51: =Q51*28 -> 0 | AM51: =SUM(AG51:AL51) -> 8484 | AO51: SC | AP51: =X51*4 -> 0 | AQ51: =Y51*4 -> 0 | AR51: =Z51*4 -> 0 | AS51: =AA51*4 -> 0 | AT51: =AB51*4 -> 0 | AU51: =AC51*4 -> 0 | AV51: =SUM(AP51:AU51) -> 0 | AX51: SC | BE51: =SUM(AY51:BD51) -> 0 | BG51: SC | BH51: =L51*28*2 -> 6664 | BI51: =M51*28*2 -> 3696 | BJ51: =N51*28*2 -> 5432 | BK51: =O51*28*2 -> 1176 | BL51: =P51*28*2 -> 0 | BM51: =Q51*28*2 -> 0 | BN51: =SUM(BH51:BM51) -> 16968 | BP51: SC | BQ51: =AY51*4 -> 0 | BR51: =AZ51*4 -> 0 | BS51: =BA51*4 -> 0 | BT51: =BB51*4 -> 0 | BU51: =BC51*4 -> 0 | BV51: =BD51*4 -> 0 | BW51: =SUM(BQ51:BV51) -> 0
B52: Total Destino | C52: =SUM(C46:C51) -> 81699 | D52: =SUM(D46:D51) -> 77987 | E52: =SUM(E46:E51) -> 90487 | F52: =SUM(F46:F51) -> 22248 | G52: =SUM(G46:G51) -> 115285 | H52: =SUM(H46:H51) -> 21316 | I52: =SUM(I46:I51) -> 409022 | K52: Total Destino | L52: =SUM(L46:L51) -> 199 | M52: =SUM(M46:M51) -> 123 | N52: =SUM(N46:N51) -> 146 | O52: =SUM(O46:O51) -> 27 | P52: =SUM(P46:P51) -> 17 | Q52: =SUM(Q46:Q51) -> 1 | R52: =SUM(R46:R51) -> 513 | T52: Total | U52: =SUM(U46:U51) -> 0 | W52: Total Destino | X52: =SUM(X46:X51) -> 0 | Y52: =SUM(Y46:Y51) -> 0 | Z52: =SUM(Z46:Z51) -> 0 | AA52: =SUM(AA46:AA51) -> 1 | AB52: =SUM(AB46:AB51) -> 120 | AC52: =SUM(AC46:AC51) -> 302 | AD52: =SUM(AD46:AD51) -> 423 | AF52: Total Destino | AG52: =SUM(AG46:AG51) -> 5572 | AH52: =SUM(AH46:AH51) -> 3444 | AI52: =SUM(AI46:AI51) -> 4088 | AJ52: =SUM(AJ46:AJ51) -> 756 | AK52: =SUM(AK46:AK51) -> 476 | AL52: =SUM(AL46:AL51) -> 28 | AM52: 1933 | AO52: Total Destino | AP52: =SUM(AP46:AP51) -> 0 | AQ52: =SUM(AQ46:AQ51) -> 0 | AR52: =SUM(AR46:AR51) -> 0 | AS52: =SUM(AS46:AS51) -> 4 | AT52: =SUM(AT46:AT51) -> 480 | AU52: =SUM(AU46:AU51) -> 1208 | AV52: =SUM(AV46:AV51) -> 1692 | AX52: Total Destino | AY52: =SUM(AY46:AY51) -> 0 | AZ52: =SUM(AZ46:AZ51) -> 0 | BA52: =SUM(BA46:BA51) -> 0 | BB52: =SUM(BB46:BB51) -> 2 | BC52: =SUM(BC46:BC51) -> 240 | BD52: =SUM(BD46:BD51) -> 600 | BE52: =SUM(BE46:BE51) -> 842 | BG52: Total Destino | BH52: =SUM(BH46:BH51) -> 11144 | BI52: =SUM(BI46:BI51) -> 6888 | BJ52: =SUM(BJ46:BJ51) -> 8176 | BK52: =SUM(BK46:BK51) -> 1512 | BL52: =SUM(BL46:BL51) -> 952 | BM52: =SUM(BM46:BM51) -> 56 | BN52: 1933 | BP52: Total Destino | BQ52: =SUM(BQ46:BQ51) -> 0 | BR52: =SUM(BR46:BR51) -> 0 | BS52: =SUM(BS46:BS51) -> 0 | BT52: =SUM(BT46:BT51) -> 8 | BU52: =SUM(BU46:BU51) -> 960 | BV52: =SUM(BV46:BV51) -> 2400 | BW52: =SUM(BW46:BW51) -> 3368
B54: Movimentação de Contêineres na Cabotagem em 2022 - TEU
B55: Origem/Destino | C55: AM | D55: CE | E55: PE | F55: BA | G55: SP | H55: SC | I55: Total Origem
B56: AM | C56: =C46+C26+C36 -> 0 | D56: =D46+D26+D36 -> 13903 | E56: =E46+E26+E36 -> 16790 | F56: =F46+F26+F36 -> 6665 | G56: =G46+G26+G36 -> 112595 | H56: =H46+H26+H36 -> 11569 | I56: =SUM(C56:H56) -> 161522
B57: CE | C57: =C47+C27+C37 -> 23842 | D57: =D47+D27+D37 -> 0 | E57: =E47+E27+E37 -> 5278 | F57: =F47+F27+F37 -> 697 | G57: =G47+G27+G37 -> 25277 | H57: =H47+H27+H37 -> 10587 | I57: =SUM(C57:H57) -> 65681
B58: PE | C58: =C48+C28+C38 -> 40255 | D58: =D48+D28+D38 -> 12390 | E58: =E48+E28+E38 -> 0 | F58: =F48+F28+F38 -> 4273 | G58: =G48+G28+G38 -> 28128 | H58: =H48+H28+H38 -> 9423 | I58: =SUM(C58:H58) -> 94469
B59: BA | C59: =C49+C29+C39 -> 7339 | D59: =D49+D29+D39 -> 5495 | E59: =E49+E29+E39 -> 4078 | F59: =F49+F29+F39 -> 0 | G59: =G49+G29+G39 -> 33493 | H59: =H49+H29+H39 -> 5401 | I59: =SUM(C59:H59) -> 55806
B60: SP | C60: =C50+C30+C40 -> 44756 | D60: =D50+D30+D40 -> 56746 | E60: =E50+E30+E40 -> 69572 | F60: =F50+F30+F40 -> 11507 | G60: =G50+G30+G40 -> 0 | H60: =H50+H30+H40 -> 0 | I60: =SUM(C60:H60) -> 182581
B61: SC | C61: =C51+C31+C41 -> 36324 | D61: =D51+D31+D41 -> 45197 | E61: =E51+E31+E41 -> 63792 | F61: =F51+F31+F41 -> 11283 | G61: =G51+G31+G41 -> 0 | H61: =H51+H31+H41 -> 0 | I61: =SUM(C61:H61) -> 156596
B62: Total Destino | C62: =SUM(C56:C61) -> 152516 | D62: =SUM(D56:D61) -> 133731 | E62: =SUM(E56:E61) -> 159510 | F62: =SUM(F56:F61) -> 34425 | G62: =SUM(G56:G61) -> 199493 | H62: =SUM(H56:H61) -> 36980 | I62: =SUM(I56:I61) -> 716655
AH63: PAR OD | AI63: RESTRIÇÃO TONELAGEM | AK63: MAXIMO | AN63: PAR OD | AO63: RESTRIÇÃO TEU | AQ63: MAXIMO
B64: Distâncias RODO | AA64: DESTINOS DA CARGA | AH64: SP(1) -> SC(2) | AI64: =SUM(AB82:AB86)+AE91+AD86+AE90+AF85+AG84+AF86+AG85+AG86 -> #VALUE! | AK64: 39200 | AN64: SP(1) -> SC(2) | AQ64: 2800
B65: Origem/Destino | C65: MANAUS | D65: FORTALEZA | E65: RECIFE | F65: SALVADOR | G65: SÃO PAULO | H65: FLORIANÓPOLIS | AA65: SP(1) -> SC(2) | AB65: SC(2) -> BA(3) | AC65: BA(3) -> PE(4) | AD65: PE(4) -> CE(5) | AE65: CE(5) -> AM(6) | AF65: AM(6) -> SP(1) | AH65: SC(2) -> BA(3) | AK65: 39200 | AN65: SC(2) -> BA(3) | AQ65: 2800
B66: MANAUS | D66: {=_xludf.XLOOKUP($B66,'Distancias Cidades'!$A$3:$A$28,_xludf.XLOOKUP(D$65,'Distancias Cidades'!$B$2:$AB$2,'Distancias Cidades'!$B$3:$AB$28))} -> #NAME? | E66: {=_xludf.XLOOKUP($B66,'Distancias Cidades'!$A$3:$A$28,_xludf.XLOOKUP(E$65,'Distancias Cidades'!$B$2:$AB$2,'Distancias Cidades'!$B$3:$AB$28))} -> #NAME? | F66: {=_xludf.XLOOKUP($B66,'Distancias Cidades'!$A$3:$A$28,_xludf.XLOOKUP(F$65,'Distancias Cidades'!$B$2:$AB$2,'Distancias Cidades'!$B$3:$AB$28))} -> #NAME? | G66: {=_xludf.XLOOKUP($B66,'Distancias Cidades'!$A$3:$A$28,_xludf.XLOOKUP(G$65,'Distancias Cidades'!$B$2:$AB$2,'Distancias Cidades'!$B$3:$AB$28))} -> #NAME? | H66: {=_xludf.XLOOKUP($B66,'Distancias Cidades'!$A$3:$A$28,_xludf.XLOOKUP(H$65,'Distancias Cidades'!$B$2:$AB$2,'Distancias Cidades'!$B$3:$AB$28))} -> #NAME? | AA66: Embarque SP | AB66: Embarque SC | AC66: Embarque BA | AD66: Embarque PE | AE66: Embarque CE | AF66: Embarque AM | AH66: BA(3) -> PE(4) | AK66: 39200 | AN66: BA(3) -> PE(4) | AQ66: 2800
B67: FORTALEZA | C67: {=(_xludf.XLOOKUP(B67,'Distancias Cidades'!$A$3:$A$28,_xludf.XLOOKUP("BELÉM",'Distancias Cidades'!$B$2:$AB$2,'Distancias Cidades'!$B$3:$AB$28)))+10} -> #NAME? | D67: {=_xludf.XLOOKUP($B67,'Distancias Cidades'!$A$3:$A$28,_xludf.XLOOKUP(D$65,'Distancias Cidades'!$B$2:$AB$2,'Distancias Cidades'!$B$3:$AB$28))} -> #NAME? | E67: {=_xludf.XLOOKUP($B67,'Distancias Cidades'!$A$3:$A$28,_xludf.XLOOKUP(E$65,'Distancias Cidades'!$B$2:$AB$2,'Distancias Cidades'!$B$3:$AB$28))} -> #NAME? | F67: {=_xludf.XLOOKUP($B67,'Distancias Cidades'!$A$3:$A$28,_xludf.XLOOKUP(F$65,'Distancias Cidades'!$B$2:$AB$2,'Distancias Cidades'!$B$3:$AB$28))} -> #NAME? | G67: {=_xludf.XLOOKUP($B67,'Distancias Cidades'!$A$3:$A$28,_xludf.XLOOKUP(G$65,'Distancias Cidades'!$B$2:$AB$2,'Distancias Cidades'!$B$3:$AB$28))} -> #NAME? | H67: {=_xludf.XLOOKUP($B67,'Distancias Cidades'!$A$3:$A$28,_xludf.XLOOKUP(H$65,'Distancias Cidades'!$B$2:$AB$2,'Distancias Cidades'!$B$3:$AB$28))} -> #NAME? | K67: Movimentação de Contêineres na Cabotagem em 2022 - unidades | AA67: 3 -- 2 | AB67: 4 -- 3 | AC67: 5 -- 4 | AD67: 6 -- 5 | AE67: 1 -- 6 | AF67: 2 -- 1 | AH67: PE(4) -> CE(5) | AK67: 39200 | AN67: PE(4) -> CE(5) | AQ67: 2800
B68: RECIFE | C68: {=(_xludf.XLOOKUP(B68,'Distancias Cidades'!$A$3:$A$28,_xludf.XLOOKUP("BELÉM",'Distancias Cidades'!$B$2:$AB$2,'Distancias Cidades'!$B$3:$AB$28)))+10} -> #NAME? | D68: {=_xludf.XLOOKUP($B68,'Distancias Cidades'!$A$3:$A$28,_xludf.XLOOKUP(D$65,'Distancias Cidades'!$B$2:$AB$2,'Distancias Cidades'!$B$3:$AB$28))} -> #NAME? | E68: {=_xludf.XLOOKUP($B68,'Distancias Cidades'!$A$3:$A$28,_xludf.XLOOKUP(E$65,'Distancias Cidades'!$B$2:$AB$2,'Distancias Cidades'!$B$3:$AB$28))} -> #NAME? | F68: {=_xludf.XLOOKUP($B68,'Distancias Cidades'!$A$3:$A$28,_xludf.XLOOKUP(F$65,'Distancias Cidades'!$B$2:$AB$2,'Distancias Cidades'!$B$3:$AB$28))} -> #NAME? | G68: {=_xludf.XLOOKUP($B68,'Distancias Cidades'!$A$3:$A$28,_xludf.XLOOKUP(G$65,'Distancias Cidades'!$B$2:$AB$2,'Distancias Cidades'!$B$3:$AB$28))} -> #NAME? | H68: {=_xludf.XLOOKUP($B68,'Distancias Cidades'!$A$3:$A$28,_xludf.XLOOKUP(H$65,'Distancias Cidades'!$B$2:$AB$2,'Distancias Cidades'!$B$3:$AB$28))} -> #NAME? | K68: Origem/Destino | L68: AM | M68: CE | N68: PE | O68: BA | P68: SP | Q68: SC | R68: Total Origem | AA68: 4 -- 2 | AB68: 5 -- 3 | AC68: 6 -- 4 | AD68: 1 -- 5 | AE68: 2 -- 6 | AF68: 3 -- 1 | AH68: CE(5) -> AM(6) | AK68: 39200 | AN68: CE(5) -> AM(6) | AQ68: 2800
B69: SALVADOR | C69: {=(_xludf.XLOOKUP(B69,'Distancias Cidades'!$A$3:$A$28,_xludf.XLOOKUP("BELÉM",'Distancias Cidades'!$B$2:$AB$2,'Distancias Cidades'!$B$3:$AB$28)))+10} -> #NAME? | D69: {=_xludf.XLOOKUP($B69,'Distancias Cidades'!$A$3:$A$28,_xludf.XLOOKUP(D$65,'Distancias Cidades'!$B$2:$AB$2,'Distancias Cidades'!$B$3:$AB$28))} -> #NAME? | E69: {=_xludf.XLOOKUP($B69,'Distancias Cidades'!$A$3:$A$28,_xludf.XLOOKUP(E$65,'Distancias Cidades'!$B$2:$AB$2,'Distancias Cidades'!$B$3:$AB$28))} -> #NAME? | F69: {=_xludf.XLOOKUP($B69,'Distancias Cidades'!$A$3:$A$28,_xludf.XLOOKUP(F$65,'Distancias Cidades'!$B$2:$AB$2,'Distancias Cidades'!$B$3:$AB$28))} -> #NAME? | G69: {=_xludf.XLOOKUP($B69,'Distancias Cidades'!$A$3:$A$28,_xludf.XLOOKUP(G$65,'Distancias Cidades'!$B$2:$AB$2,'Distancias Cidades'!$B$3:$AB$28))} -> #NAME? | H69: {=_xludf.XLOOKUP($B69,'Distancias Cidades'!$A$3:$A$28,_xludf.XLOOKUP(H$65,'Distancias Cidades'!$B$2:$AB$2,'Distancias Cidades'!$B$3:$AB$28))} -> #NAME? | K69: AM | L69: =INT(C46/52) -> 0 | M69: =INT(D46/52) -> 150 | N69: =INT(E46/52) -> 164 | O69: =INT(F46/52) -> 67 | P69: =INT(G46/52) -> 1106 | Q69: =INT(H46/52) -> 115 | R69: =SUM(L69:Q69) -> 1602 | AA69: 4 -- 3 | AB69: 5 -- 4 | AC69: 6 -- 5 | AD69: 1 -- 6 | AE69: 2 -- 1 | AF69: 3 -- 2 | AH69: AM(6) -> SP(1) | AK69: 39200 | AN69: AM(6) -> SP(1) | AQ69: 2800
B70: SÃO PAULO | C70: {=(_xludf.XLOOKUP(B70,'Distancias Cidades'!$A$3:$A$28,_xludf.XLOOKUP("BELÉM",'Distancias Cidades'!$B$2:$AB$2,'Distancias Cidades'!$B$3:$AB$28)))+10} -> #NAME? | D70: {=_xludf.XLOOKUP($B70,'Distancias Cidades'!$A$3:$A$28,_xludf.XLOOKUP(D$65,'Distancias Cidades'!$B$2:$AB$2,'Distancias Cidades'!$B$3:$AB$28))} -> #NAME? | E70: {=_xludf.XLOOKUP($B70,'Distancias Cidades'!$A$3:$A$28,_xludf.XLOOKUP(E$65,'Distancias Cidades'!$B$2:$AB$2,'Distancias Cidades'!$B$3:$AB$28))} -> #NAME? | F70: {=_xludf.XLOOKUP($B70,'Distancias Cidades'!$A$3:$A$28,_xludf.XLOOKUP(F$65,'Distancias Cidades'!$B$2:$AB$2,'Distancias Cidades'!$B$3:$AB$28))} -> #NAME? | G70: {=_xludf.XLOOKUP($B70,'Distancias Cidades'!$A$3:$A$28,_xludf.XLOOKUP(G$65,'Distancias Cidades'!$B$2:$AB$2,'Distancias Cidades'!$B$3:$AB$28))} -> #NAME? | H70: {=_xludf.XLOOKUP($B70,'Distancias Cidades'!$A$3:$A$28,_xludf.XLOOKUP(H$65,'Distancias Cidades'!$B$2:$AB$2,'Distancias Cidades'!$B$3:$AB$28))} -> #NAME? | K70: CE | L70: =INT(C47/52) -> 257 | M70: =INT(D47/52) -> 0 | N70: =INT(E47/52) -> 53 | O70: =INT(F47/52) -> 11 | P70: =INT(G47/52) -> 330 | Q70: =INT(H47/52) -> 140 | R70: =SUM(L70:Q70) -> 791 | AA70: 5 -- 2 | AB70: 6 -- 3 | AC70: 1 -- 4 | AD70: 2 -- 5 | AE70: 3 -- 6 | AF70: 4 -- 1
B71: FLORIANÓPOLIS | C71: {=(_xludf.XLOOKUP(B71,'Distancias Cidades'!$A$3:$A$28,_xludf.XLOOKUP("BELÉM",'Distancias Cidades'!$B$2:$AB$2,'Distancias Cidades'!$B$3:$AB$28)))+10} -> #NAME? | D71: {=_xludf.XLOOKUP($B71,'Distancias Cidades'!$A$3:$A$28,_xludf.XLOOKUP(D$65,'Distancias Cidades'!$B$2:$AB$2,'Distancias Cidades'!$B$3:$AB$28))} -> #NAME? | E71: {=_xludf.XLOOKUP($B71,'Distancias Cidades'!$A$3:$A$28,_xludf.XLOOKUP(E$65,'Distancias Cidades'!$B$2:$AB$2,'Distancias Cidades'!$B$3:$AB$28))} -> #NAME? | F71: {=_xludf.XLOOKUP($B71,'Distancias Cidades'!$A$3:$A$28,_xludf.XLOOKUP(F$65,'Distancias Cidades'!$B$2:$AB$2,'Distancias Cidades'!$B$3:$AB$28))} -> #NAME? | G71: {=_xludf.XLOOKUP($B71,'Distancias Cidades'!$A$3:$A$28,_xludf.XLOOKUP(G$65,'Distancias Cidades'!$B$2:$AB$2,'Distancias Cidades'!$B$3:$AB$28))} -> #NAME? | H71: {=_xludf.XLOOKUP($B71,'Distancias Cidades'!$A$3:$A$28,_xludf.XLOOKUP(H$65,'Distancias Cidades'!$B$2:$AB$2,'Distancias Cidades'!$B$3:$AB$28))} -> #NAME? | K71: PE | L71: =INT(C48/52) -> 406 | M71: =INT(D48/52) -> 133 | N71: =INT(E48/52) -> 0 | O71: =INT(F48/52) -> 69 | P71: =INT(G48/52) -> 352 | Q71: =INT(H48/52) -> 98 | R71: =SUM(L71:Q71) -> 1058 | AA71: 5 -- 3 | AB71: 6 -- 4 | AC71: 1 -- 5 | AD71: 2 -- 6 | AE71: 3 -- 1 | AF71: 4 -- 2
K72: BA | L72: =INT(C49/52) -> 74 | M72: =INT(D49/52) -> 60 | N72: =INT(E49/52) -> 45 | O72: =INT(F49/52) -> 0 | P72: =INT(G49/52) -> 426 | Q72: =INT(H49/52) -> 54 | R72: =SUM(L72:Q72) -> 659 | AA72: 5 -- 4 | AB72: 6 -- 5 | AC72: 1 -- 6 | AD72: 2 -- 1 | AE72: 3 -- 2 | AF72: 4 -- 3
K73: SP | L73: =INT(C50/52) -> 469 | M73: =INT(D50/52) -> 607 | N73: =INT(E50/52) -> 732 | O73: =INT(F50/52) -> 130 | P73: =INT(G50/52) -> 0 | Q73: =INT(H50/52) -> 0 | R73: =SUM(L73:Q73) -> 1938 | AA73: 6 -- 2 | AB73: 1 -- 3 | AC73: 2 -- 4 | AD73: 3 -- 5 | AE73: 4 -- 6 | AF73: 5 -- 1
B74: Receita CABOTAGEM | K74: SC | L74: =INT(C51/52) -> 363 | M74: =INT(D51/52) -> 548 | N74: =INT(E51/52) -> 744 | O74: =INT(F51/52) -> 148 | P74: =INT(G51/52) -> 0 | Q74: =INT(H51/52) -> 0 | R74: =SUM(L74:Q74) -> 1803 | AA74: 6 -- 3 | AB74: 1 -- 4 | AC74: 2 -- 5 | AD74: 3 -- 6 | AE74: 4 -- 1 | AF74: 5 -- 2
B75: Origem/Destino | C75: AM | D75: CE | E75: PE | F75: BA | G75: SP | H75: SC | K75: Total Destino | L75: =SUM(L69:L74) -> 1569 | M75: =SUM(M69:M74) -> 1498 | N75: =SUM(N69:N74) -> 1738 | O75: =SUM(O69:O74) -> 425 | P75: =SUM(P69:P74) -> 2214 | Q75: =SUM(Q69:Q74) -> 407 | R75: =SUM(R69:R74) -> 7851 | AA75: 6 -- 4 | AB75: 1 -- 5 | AC75: 2 -- 6 | AD75: 3 -- 1 | AE75: 4 -- 2 | AF75: 5 -- 3
B76: AM | D76: =C77 -> #NAME? | E76: =C78 -> #NAME? | F76: =C79 -> #NAME? | G76: =C80 -> #NAME? | H76: =C81 -> #NAME? | AA76: 6 -- 5 | AB76: 1 -- 6 | AC76: 2 -- 1 | AD76: 3 -- 2 | AE76: 4 -- 3 | AF76: 5 -- 4
B77: CE | C77: =(((C67*5.6748+496.5)*1.3)+7000)*0.7 -> #NAME? | E77: =D78 -> #NAME? | F77: =D79 -> #NAME? | G77: =D80 -> #NAME? | H77: =D81 -> #NAME? | K77: Movimentação de Contêineres na Cabotagem em 2022 - TEU
B78: PE | C78: =(((C68*5.6748+496.5)*1.3)+7000)*0.7 -> #NAME? | D78: =(D68*5.6748+496.5)*1.3*0.7 -> #NAME? | F78: =E79 -> #NAME? | G78: =(G68*5.6748+496.5)*1.3*0.7 -> #NAME? | H78: =E81 -> #NAME? | K78: Origem/Destino | L78: AM | M78: CE | N78: PE | O78: BA | P78: SP | Q78: SC | R78: Total Origem
B79: BA | C79: =(((C69*5.6748+496.5)*1.3)+7000)*0.7 -> #NAME? | D79: =(D69*5.6748+496.5)*1.3*0.7 -> #NAME? | E79: =(E69*5.6748+496.5)*1.3*0.7 -> #NAME? | H79: =(H69*5.6748+496.5)*1.3*0.7 -> #NAME? | K79: AM | L79: =INT(C56/52) -> 0 | M79: =INT(D56/52) -> 267 | N79: =INT(E56/52) -> 322 | O79: =INT(F56/52) -> 128 | P79: =INT(G56/52) -> 2165 | Q79: =INT(H56/52) -> 222 | R79: =SUM(L79:Q79) -> 3104 | AB79: SSZ | AC79: IOA | AD79: SSA | AE79: SUA | AF79: PEC | AG79: MAO | AH79: SUA | AI79: SSZ | AM79: SSZ | AN79: IOA | AO79: SSA | AP79: SUA | AQ79: PEC | AR79: MAO | AS79: SUA | AT79: SSZ
B80: SP | C80: =(((C70*5.6748+496.5)*1.3)+7000)*0.7 -> #NAME? | D80: =(D70*5.6748+496.5)*1.3*0.7 -> #NAME? | E80: =(E70*5.6748+496.5)*1.3*0.7 -> #NAME? | F80: =(F70*5.6748+496.5)*1.3*0.7 -> #NAME? | K80: CE | L80: =INT(C57/52) -> 458 | M80: =INT(D57/52) -> 0 | N80: =INT(E57/52) -> 101 | O80: =INT(F57/52) -> 13 | P80: =INT(G57/52) -> 486 | Q80: =INT(H57/52) -> 203 | R80: =SUM(L80:Q80) -> 1261 | AB80: EMBARQUE S | AM80: EMBARQUE S
B81: SC | C81: =(((C71*5.6748+496.5)*1.3)+7000)*0.7 -> #NAME? | D81: =(D71*5.6748+496.5)*1.3*0.7 -> #NAME? | E81: =(E71*5.6748+496.5)*1.3*0.7 -> #NAME? | F81: =(F71*5.6748+496.5)*1.3*0.7 -> #NAME? | K81: PE | L81: =INT(C58/52) -> 774 | M81: =INT(D58/52) -> 238 | N81: =INT(E58/52) -> 0 | O81: =INT(F58/52) -> 82 | P81: =INT(G58/52) -> 540 | Q81: =INT(H58/52) -> 181 | R81: =SUM(L81:Q81) -> 1815 | AB81: PEGAR CHEIOS E VAZIOS | AE81: SUBIDA | AM81: PEGAR CHEIOS E VAZIOS | AP81: SUBIDA
B82: *CONSIDERAR CAMINHÃO DE SEIS EIXOS | K82: BA | L82: =INT(C59/52) -> 141 | M82: =INT(D59/52) -> 105 | N82: =INT(E59/52) -> 78 | O82: =INT(F59/52) -> 0 | P82: =INT(G59/52) -> 644 | Q82: =INT(H59/52) -> 103 | R82: =SUM(L82:Q82) -> 1071 | AB82: SSZ-IOA | AC82: IOA--SSA | AD82: SSA-SUA | AE82: SUA-PEC | AF82: PEC-MAO | AG82: MAO-SUA | AM82: SSZ-IOA | AN82: IOA--SSA | AO82: SSA-SUA | AP82: SUA-PEC | AQ82: PEC-MAO | AR82: MAO-SUA
G83: CABOTAGEM | K83: SP | L83: =INT(C60/52) -> 860 | M83: =INT(D60/52) -> 1091 | N83: =INT(E60/52) -> 1337 | O83: =INT(F60/52) -> 221 | P83: =INT(G60/52) -> 0 | Q83: =INT(H60/52) -> 0 | R83: =SUM(L83:Q83) -> 3509 | AB83: SSZ-SSA | AC83: IOA--SUA | AD83: SSA-PEC | AE83: SUA-MAO | AF83: PEC-SUA | AG83: MAO-SSZ | AM83: SSZ-SSA | AN83: IOA--SUA | AO83: SSA-PEC | AP83: SUA-MAO | AQ83: PEC-SUA | AR83: MAO-SSZ
K84: SC | L84: =INT(C61/52) -> 698 | M84: =INT(D61/52) -> 869 | N84: =INT(E61/52) -> 1226 | O84: =INT(F61/52) -> 216 | P84: =INT(G61/52) -> 0 | Q84: =INT(H61/52) -> 0 | R84: =SUM(L84:Q84) -> 3009 | AB84: SSZ-SUA | AC84: IOA-PEC | AD84: SSA-MAO | AF84: PEC-SSZ | AG84: MAO-IOA | AM84: SSZ-SUA | AN84: IOA-PEC | AO84: SSA-MAO | AQ84: PEC-SSZ | AR84: MAO-IOA
B85: * nosso serviço é porta porta e não porto porto, considerar o custo do rodo ate o porto e do porto pra porta e depois os 70% | K85: Total Destino | L85: =SUM(L79:L84) -> 2931 | M85: =SUM(M79:M84) -> 2570 | N85: =SUM(N79:N84) -> 3064 | O85: =SUM(O79:O84) -> 660 | P85: =SUM(P79:P84) -> 3835 | Q85: =SUM(Q79:Q84) -> 709 | R85: =SUM(R79:R84) -> 13769 | AB85: SSZ-PEC | AC85: IOA-MAO | AD85: SSA-SSZ | AF85: PEC-IOA | AG85: MAO-SSA | AM85: SSZ-PEC | AN85: IOA-MAO | AO85: SSA-SSZ | AQ85: PEC-IOA | AR85: MAO-SSA
AB86: SSZ-MAO | AC86: IOA-SSZ | AD86: SSA-IOA | AF86: PEC-SSA | AG86: MAO-PEC | AM86: SSZ-MAO | AN86: IOA-SSZ | AO86: SSA-IOA | AQ86: PEC-SSA | AR86: MAO-PEC
K87: RECEITA POTENCIAL CABOTAGEM SEMANAL
B88: DESTINOS DA CARGA | K88: Origem/Destino | L88: AM | M88: CE | N88: PE | O88: BA | P88: SP | Q88: SC | T88: DESTINOS DA CARGA | AE88: DESCIDA | AP88: DESCIDA
B89: SP(1) -> SC(2) | C89: SC(2) -> BA(3) | D89: BA(3) -> PE(4) | E89: PE(4) -> CE(5) | F89: CE(5) -> AM(6) | G89: AM(6) -> SP(1) | K89: AM | L89: =C76*L69 -> 0 | M89: =D76*M69 -> #NAME? | N89: =E76*N69 -> #NAME? | O89: =F76*O69 -> #NAME? | P89: =G76*P69 -> #NAME? | Q89: =H76*Q69 -> #NAME? | T89: SP(1) -> SC(2) | U89: SC(2) -> BA(3) | V89: BA(3) -> PE(4) | W89: PE(4) -> CE(5) | X89: CE(5) -> AM(6) | Y89: AM(6) -> SP(1) | AE89: SUA-SSZ | AP89: SUA-SSZ
B90: Embarque SP | C90: Embarque SC | D90: Embarque BA | E90: Embarque PE | F90: Embarque CE | G90: Embarque AM | K90: CE | L90: =C77*L70 -> #NAME? | M90: =D77*M70 -> 0 | N90: =E77*N70 -> #NAME? | O90: =F77*O70 -> #NAME? | P90: =G77*P70 -> #NAME? | Q90: =H77*Q70 -> #NAME? | T90: 16212 | U90: 20636 | V90: 4396 | W90: 14252 | X90: 16296 | Y90: 32648 | AE90: SUA-IOA | AP90: SUA-IOA
B91: 3 -- 2 | C91: 4 -- 3 | D91: 5 -- 4 | E91: 6 -- 5 | F91: 1 -- 6 | G91: 2 -- 1 | K91: PE | L91: =C78*L71 -> #NAME? | M91: =D78*M71 -> #NAME? | N91: =E78*N71 -> 0 | O91: =F78*O71 -> #NAME? | P91: =G78*P71 -> #NAME? | Q91: =H78*Q71 -> #NAME? | T91: 364 | U91: 0 | V91: 0 | W91: 448 | X91: 3976 | Y91: 0 | AE91: SUA-SSA | AP91: SUA-SSA
B92: 4 -- 2 | C92: 5 -- 3 | D92: 6 -- 4 | E92: 1 -- 5 | F92: 2 -- 6 | G92: 3 -- 1 | K92: BA | L92: =C79*L72 -> #NAME? | M92: =D79*M72 -> #NAME? | N92: =E79*N72 -> #NAME? | O92: =F79*O72 -> 0 | P92: =G79*P72 -> 0 | Q92: =H79*Q72 -> #NAME? | T92: 1036 | U92: 112 | V92: 1092 | W92: 4592 | X92: 4788 | Y92: 0
B93: 4 -- 3 | C93: 5 -- 4 | D93: 6 -- 5 | E93: 1 -- 6 | F93: 2 -- 1 | G93: 3 -- 2 | K93: SP | L93: =C80*L73 -> #NAME? | M93: =D80*M73 -> #NAME? | N93: =E80*N73 -> #NAME? | O93: =F80*O73 -> #NAME? | P93: =G80*P73 -> 0 | Q93: =H80*Q73 -> 0 | T93: 0 | U93: 0 | V93: 448 | W93: 3976 | X93: 0 | Y93: 364
B94: 5 -- 2 | C94: 6 -- 3 | D94: 1 -- 4 | E94: 2 -- 5 | F94: 3 -- 6 | G94: 4 -- 1 | K94: SC | L94: =C81*L74 -> #NAME? | M94: =D81*M74 -> #NAME? | N94: =E81*N74 -> #NAME? | O94: =F81*O74 -> #NAME? | P94: =G81*P74 -> 0 | Q94: =H81*Q74 -> 0 | T94: 364 | U94: 700 | V94: 5292 | W94: 7700 | X94: 1484 | Y94: 1456
B95: 5 -- 3 | C95: 6 -- 4 | D95: 1 -- 5 | E95: 2 -- 6 | F95: 3 -- 1 | G95: 4 -- 2 | Q95: SEMANAL | R95: =SUM(L89:Q94) -> #NAME? | T95: 112 | U95: 1092 | V95: 4592 | W95: 4788 | X95: 0 | Y95: 1036
B96: 5 -- 4 | C96: 6 -- 5 | D96: 1 -- 6 | E96: 2 -- 1 | F96: 3 -- 2 | G96: 4 -- 3 | Q96: ANUAL | R96: =R95*52 -> #NAME? | T96: 0 | U96: 448 | V96: 3976 | W96: 0 | X96: 364 | Y96: 0
B97: 6 -- 2 | C97: 1 -- 3 | D97: 2 -- 4 | E97: 3 -- 5 | F97: 4 -- 6 | G97: 5 -- 1 | T97: 3192 | U97: 2352 | V97: 6888 | W97: 1540 | X97: 9744 | Y97: 3192
B98: 6 -- 3 | C98: 1 -- 4 | D98: 2 -- 5 | E98: 3 -- 6 | F98: 4 -- 1 | G98: 5 -- 2 | T98: 700 | U98: 5292 | V98: 7700 | W98: 1484 | X98: 1456 | Y98: 364
B99: 6 -- 4 | C99: 1 -- 5 | D99: 2 -- 6 | E99: 3 -- 1 | F99: 4 -- 2 | G99: 5 -- 3 | T99: 1092 | U99: 4592 | V99: 4788 | W99: 0 | X99: 1036 | Y99: 112
B100: 6 -- 5 | C100: 1 -- 6 | D100: 2 -- 1 | E100: 3 -- 2 | F100: 4 -- 3 | G100: 5 -- 4 | T100: 448 | U100: 3976 | V100: 0 | W100: 364 | X100: 0 | Y100: 0
K101: DESTINOS DA CARGA | T101: 23520 | U101: 39200 | V101: 39172 | W101: 39144 | X101: 39144 | Y101: 39172
K102: SP(1) -> SC(2) | L102: SC(2) -> BA(3) | M102: BA(3) -> PE(4) | N102: PE(4) -> CE(5) | O102: CE(5) -> AM(6) | P102: AM(6) -> SP(1) | T102: TONELAGEM E DESTINOS
K103: =R146+U10*2+AD30*4 -> 18968 | L103: =R147 -> 19880 | M103: =R145+U9*2 -> 4872 | N103: =R144+U8*2+AD28*4+AD38*4 -> 17248 | O103: =R143+U7*2+AD27*4+AD37*4 -> 18528 | P103: =R142+U6*2+AD36*4 -> 33418
K104: =Q145 -> 420 | L104: =O144 -> 0 | M104: =N143 -> 0 | N104: =M142 -> 0 | O104: =L146 -> 3052 | P104: 0
K105: =Q144 -> 1008 | L105: =O143 -> 0 | M105: =N142 -> 616 | N105: =M146 -> 5516 | O105: =L147 -> 3696 | P105: =P145 -> 0
B106: PORCENTAGEM LEVADA | K106: =O144 -> 0 | L106: =N143 -> 0 | M106: =M142 -> 0 | N106: =L146 -> 3052 | O106: 0 | P106: =Q145 -> 420
...

Sheet Detalhe1-AM
A1: Month | B1: Type | C1: UF Origin | D1: UF Destination | E1: TEU | F1: Unit
A2: jan | B2: 40RH | C2: SC | D2: AM | E2: 1328 | F2: 664
A3: jan | B3: 40RH | C3: SP | D3: AM | E3: 332 | F3: 166
A4: jan | B4: 40RH | C4: PE | D4: AM | E4: 320 | F4: 160
A5: jan | B5: 40RH | C5: CE | D5: AM | E5: 14 | F5: 7
A6: jan | B6: 40RH | C6: BA | D6: AM | E6: 4 | F6: 2
A7: fev | B7: 40RH | C7: SC | D7: AM | E7: 832 | F7: 416
A8: fev | B8: 40RH | C8: SP | D8: AM | E8: 434 | F8: 217
A9: fev | B9: 40RH | C9: PE | D9: AM | E9: 290 | F9: 145
A10: fev | B10: 40RH | C10: CE | D10: AM | E10: 14 | F10: 7
A11: fev | B11: 40RH | C11: BA | D11: AM | E11: 10 | F11: 5
A12: fev | B12: 40RH | C12: RJ | D12: AM | E12: 4 | F12: 2
A13: fev | B13: 40RH | C13: RS | D13: AM | E13: 4 | F13: 2
... A79: dez | B79: 40RH | C79: RJ | D79: AM | E79: 2 | F79: 1

Sheet % Movimentação
B3: Ano | C3: % Ano | D3: % Movimentação
B4: 1 | C4: 0.6 | D4: =C4 -> 0.6
B5: 2 | C5: 0.1 | D5: =C5+D4 -> 0.7
B6: 3 | C6: 0.1 | D6: =C6+D5 -> 0.8
B7: 4 | C7: 0.1 | D7: =C7+D6 -> 0.9
B8: 5 | C8: 0.1 | D8: =C8+D7 -> 1

Sheet Portos & Cidades
B3: Estado | C3: Capital | D3: Porto | E3: Nome Porto | F3: Terminal | G3: Distância Capital-Terminal&Depot (km)
B4: AM | C4: Manaus | D4: MAO | E4: Porto Chibatão | F4: PORTO CHIBATAO | G4: 10
B5: PA | C5: Belém | D5: VLC | E5: Porto de Vila do Conde | F5: TECON VILA DO CONDE | G5: 115
B6: MA | C6: São Luís | D6: SLZ | E6: Porto de Itaqui | F6: PORTO DE ITAQUI | G6: 15
B7: CE | C7: Fortaleza | D7: PEC | E7: Porto de Pecém | F7: APMT PECEM | G7: 60
B8: PE | C8: Recife | D8: SUA | E8: Porto de Suape | F8: TECON SUAPE | G8: 51
B9: BA | C9: Salvador | D9: SSA | E9: Porto de Salvador | F9: TECON SALVADOR | G9: 10
B10: ES | C10: Vitória | D10: VIX | E10: Porto de Vitória | F10: TVV | G10: 12
B11: RJ | C11: Rio de Janeiro | D11: IGI | E11: Porto de Itaguaí | F11: SEPETIBA TECON | G11: 100
B12: RJ | C12: Rio de Janeiro | D12: RIO | E12: Porto do Rio de Janeiro | F12: TECON RIO | G12: 10
B13: SP | C13: São Paulo | D13: SSZ | E13: Porto de Santos | F13: TECON SANTOS | G13: 100
B14: PR | C14: Curitiba | D14: PNG | E14: Porto de Paranaguá | F14: TCP | G14: 95
B15: SC | C15: Florianopólis | D15: IOA | E15: Porto de Itapoá | F15: PORTO ITAPOA | G15: 258
... B19: RG | C19: Porto Alegre | D19: RIG | E19: Porto de Rio Grande | F19: TECON RIO GRANDE | G19: 320

Sheet Portos Tempos Operacionais
C2: Tempos Operacionais
B3: Porto | C3: Embarca Prático (h) | D3: Navegação Canal - Entrada (h) | E3: Atracação (h) | F3: Desatracação (h) | G3: Navegação Canal - Saída (h) | H3: Desembarca Prático (h)
B4: MAO | C4: 1 | D4: 1 | E4: 1 | F4: 1 | G4: 1 | H4: 1
B5: VLC | C5: 1 | D5: 2 | E5: 1 | F5: 1 | G5: 2 | H5: 1
B6: SLZ | C6: 1 | D6: 2 | E6: 1 | F6: 1 | G6: 2 | H6: 1
B7: PEC | C7: 1 | D7: 0.5 | E7: 1 | F7: 1 | G7: 0.5 | H7: 1
B8: SUA | C8: 1 | D8: 0.5 | E8: 1 | F8: 1 | G8: 0.5 | H8: 1
B9: SSA | C9: 1 | D9: 0.5 | E9: 1 | F9: 1 | G9: 0.5 | H9: 1
B10: VIX | C10: 1 | D10: 1 | E10: 1 | F10: 1 | G10: 1 | H10: 1
B11: IGI | C11: 1 | D11: 2 | E11: 1 | F11: 1 | G11: 2 | H11: 1
B12: RIO | C12: 1 | D12: 1 | E12: 1 | F12: 1 | G12: 1 | H12: 1
B13: SSZ | C13: 1 | D13: 1 | E13: 1 | F13: 1 | G13: 1 | H13: 1
B14: PNG | C14: 1 | D14: 1 | E14: 1 | F14: 1 | G14: 1 | H14: 1
B15: IOA | C15: 1 | D15: 1 | E15: 1 | F15: 1 | G15: 1 | H15: 1
... B19: RIG | C19: 1 | D19: 1 | E19: 1 | F19: 1 | G19: 1 | H19: 1

Sheet Distancias Cidades
A1: QUADRO DE DISTÂNCIAS RODOVIÁRIAS ENTRE AS PRINCIPAIS CIDADES BRASILEIRAS
B2: ARACAJÚ | C2: BELÉM | D2: BELO HORIZONTE | E2: BOA VISTA | F2: BRASÍLIA | G2: CAMPO GRANDE | H2: CUIABÁ | I2: CURITIBA | J2: FLORIANÓPOLIS | K2: FORTALEZA | L2: GOIÂNIA | M2: JOÃO PESSOA | N2: MACEIÓ | O2: MANAUS | P2: NATAL | Q2: PALMAS | R2: PORTO ALEGRE | S2: PORTO VELHO | T2: RECIFE | U2: RIO BRANCO | V2: RIO DE JANEIRO | W2: SALVADOR | X2: SANTOS | Y2: SÃO LUÍS | Z2: SÃO PAULO | AA2: TERESINA | AB2: VITÓRIA
A3: ARACAJÚ | C3: 2079 | D3: 1578 | E3: 6000 | F3: 1652 | G3: 2765 | H3: 2775 | I3: 2595 | J3: 2892 | K3: 1183 | L3: 1848 | M3: 611 | N3: 294 | O3: 5215 | P3: 788 | Q3: 1662 | R3: 3296 | S3: 4230 | T3: 501 | U3: 4763 | V3: 1855 | W3: 356 | X3: 2249 | Y3: 1578 | Z3: 2187 | AA3: 1142 | AB3: 1408 | AC3: ARACAJÚ
A4: BELÉM | B4: 2079 | D4: 2824 | E4: 6083 | F4: 2120 | G4: 2942 | H4: 2941 | I4: 3193 | J4: 3500 | K4: 1610 | L4: 2017 | M4: 2161 | N4: 2173 | O4: 5298 | P4: 2108 | Q4: 1283 | R4: 3852 | S4: 4397 | T4: 2074 | U4: 4931 | V4: 3250 | W4: 2100 | X4: 3005 | Y4: 806 | Z4: 2933 | AA4: 947 | AB4: 3108 | AC4: BELÉM
A5: BELO HORIZONTE | B5: 1578 | C5: 2824 | E5: 4736 | F5: 716 | G5: 1453 | H5: 1594 | I5: 1004 | J5: 1301 | K5: 2528 | L5: 906 | M5: 2171 | N5: 1854 | O5: 3951 | P5: 2348 | Q5: 1690 | R5: 1712 | S5: 3050 | T5: 2061 | U5: 3584 | V5: 434 | W5: 1372 | X5: 658 | Y5: 2738 | Z5: 586 | AA5: 2302 | AB5: 524 | AC5: BELO HORIZONTE
A6: BRASÍLIA | B6: 1650 | C6: 2140 | D6: 741 | E6: 4275 | G6: 1134 | H6: 1133 | I6: 1366 | J6: 1673 | K6: 2200 | L6: 209 | M6: 2245 | N6: 1930 | O6: 3490 | P6: 2422 | Q6: 973 | R6: 2027 | S6: 2589 | T6: 2135 | U6: 3123 | V6: 1148 | W6: 1446 | X6: 1087 | Y6: 2157 | Z6: 1015 | AA6: 1789 | AB6: 1239 | AC6: BRASÍLIA
A7: CAMPO GRANDE | B7: 2764 | C7: 2942 | D7: 1453 | E7: 3836 | F7: 1134 | H7: 694 | I7: 991 | J7: 1298 | K7: 3407 | L7: 935 | M7: 3357 | N7: 3040 | O7: 3051 | P7: 3534 | Q7: 1785 | R7: 1518 | S7: 2150 | T7: 3247 | U7: 2684 | V7: 1444 | W7: 2568 | X7: 1086 | Y7: 2979 | Z7: 1014 | AA7: 2911 | AB7: 1892 | AC7: CAMPO GRANDE
A8: CUIABÁ | B8: 2773 | C8: 2941 | D8: 1594 | E8: 3142 | F8: 1133 | G8: 694 | I8: 1679 | J8: 1986 | K8: 3406 | L8: 934 | M8: 3366 | N8: 3049 | O8: 2357 | P8: 3543 | Q8: 1784 | R8: 2206 | S8: 1456 | T8: 3255 | U8: 1990 | V8: 2017 | W8: 2566 | X8: 1686 | Y8: 2978 | Z8: 1614 | AA8: 2910 | AB8: 2119 | AC8: CUIABÁ
A9: CURITIBA | B9: 2595 | C9: 3193 | D9: 1004 | E9: 4821 | F9: 1366 | G9: 991 | H9: 1679 | J9: 300 | K9: 3541 | L9: 1186 | M9: 3188 | N9: 2871 | O9: 4036 | P9: 3365 | Q9: 2036 | R9: 711 | S9: 3135 | T9: 3078 | U9: 3669 | V9: 852 | W9: 2385 | X9: 480 | Y9: 3230 | Z9: 408 | AA9: 3143 | AB9: 1300 | AC9: CURITIBA
A10: FLORIANÓPOLIS | B10: 2892 | C10: 3500 | D10: 1301 | E10: 5128 | F10: 1673 | G10: 1298 | H10: 1986 | I10: 300 | K10: 3838 | L10: 1493 | M10: 3485 | N10: 3168 | O10: 4443 | P10: 3662 | Q10: 2336 | R10: 476 | S10: 3442 | T10: 3375 | U10: 3976 | V10: 1144 | W10: 2682 | X10: 777 | Y10: 3537 | Z10: 705 | AA10: 3450 | AB10: 1597 | AC10: FLORIANÓPOLIS
A11: FORTALEZA | B11: 1183 | C11: 1611 | D11: 2528 | E11: 6548 | F11: 2208 | G11: 3407 | H11: 3406 | I11: 3541 | J11: 3838 | L11: 2482 | M11: 688 | N11: 1075 | O11: 5763 | P11: 537 | Q11: 2035 | R11: 4242 | S11: 4862 | T11: 800 | U11: 5396 | V11: 2805 | W11: 1389 | X11: 3199 | Y11: 1070 | Z11: 3127 | AA11: 634 | AB11: 2397 | AC11: FORTALEZA
A12: GOIÂNIA | B12: 1849 | C12: 2017 | D12: 906 | E12: 4076 | F12: 209 | G12: 935 | H12: 934 | I12: 1186 | J12: 1493 | K12: 2482 | M12: 2442 | N12: 2125 | O12: 3291 | P12: 2618 | Q12: 874 | R12: 1847 | S12: 2390 | T12: 2332 | U12: 2924 | V12: 1338 | W12: 1643 | X12: 998 | Y12: 2054 | Z12: 926 | AA12: 1986 | AB12: 1428 | AC12: GOIÂNIA
A13: JOÃO PESSOA | B13: 611 | C13: 2161 | D13: 2171 | E13: 6539 | F13: 2245 | G13: 3357 | H13: 3366 | I13: 3188 | J13: 3485 | K13: 688 | L13: 2442 | N13: 395 | O13: 5808 | P13: 185 | Q13: 2253 | R13: 3889 | S13: 4822 | T13: 120 | U13: 5356 | V13: 2448 | W13: 949 | X13: 2842 | Y13: 1660 | Z13: 2770 | AA13: 1224 | AB13: 2001 | AC13: JOÃO PESSOA
A14: MACEIÓ | B14: 294 | C14: 2173 | D14: 1854 | E14: 6276 | F14: 1928 | G14: 3040 | H14: 3049 | I14: 2871 | J14: 3168 | K14: 1075 | L14: 2105 | M14: 395 | O14: 5491 | P14: 572 | Q14: 1851 | R14: 3572 | S14: 4505 | T14: 285 | U14: 5039 | V14: 2131 | W14: 632 | X14: 2525 | Y14: 1672 | Z14: 2453 | AA14: 1236 | AB14: 1684 | AC14: MACEIÓ
A15: MANAUS | B15: 5215 | C15: 5298 | D15: 3951 | E15: 785 | F15: 3490 | G15: 3051 | H15: 2357 | I15: 4036 | J15: 4343 | K15: 5763 | L15: 3291 | M15: 5808 | N15: 5491 | P15: 5985 | Q15: 4141 | R15: 4563 | S15: 901 | T15: 5698 | U15: 1445 | V15: 4374 | W15: 5009 | X15: 4043 | Y15: 5335 | Z15: 3971 | AA15: 5267 | AB15: 4476 | AC15: MANAUS
A16: NATAL | B16: 788 | C16: 2108 | D16: 2348 | E16: 6770 | F16: 2422 | G16: 3537 | H16: 3543 | I16: 3365 | J16: 3662 | K16: 537 | L16: 2619 | M16: 185 | N16: 572 | O16: 5985 | Q16: 2345 | R16: 4066 | S16: 4998 | T16: 297 | U16: 5533 | V16: 2625 | W16: 1126 | X16: 3019 | Y16: 1607 | Z16: 2947 | AA16: 1171 | AB16: 2178 | AC16: NATAL
A17: PORTO ALEGRE | B17: 3296 | C17: 3854 | D17: 1712 | E17: 5348 | F17: 2027 | G17: 1518 | H17: 2206 | I17: 711 | J17: 476 | K17: 4242 | L17: 1847 | M17: 3889 | N17: 3572 | O17: 4563 | P17: 4066 | Q17: 2747 | S17: 3662 | T17: 3779 | U17: 4196 | V17: 1553 | W17: 3090 | X17: 1181 | Y17: 3891 | Z17: 1109 | AA17: 3804 | AB17: 2001 | AC17: PORTO ALEGRE
A18: PORTO VELHO | B18: 4229 | C18: 4397 | D18: 3050 | E18: 1686 | F18: 2589 | G18: 2150 | H18: 1456 | I18: 3135 | J18: 3442 | K18: 4865 | L18: 2390 | M18: 4822 | N18: 4505 | O18: 901 | P18: 4999 | Q18: 3240 | R18: 3662 | T18: 4712 | U18: 544 | V18: 3473 | W18: 4023 | X18: 3142 | Y18: 4434 | Z18: 3070 | AA18: 4366 | AB18: 3575 | AC18: PORTO VELHO
A19: RECIFE | B19: 501 | C19: 2074 | D19: 2061 | E19: 6483 | F19: 2135 | G19: 3247 | H19: 3256 | I19: 3078 | J19: 3375 | K19: 800 | L19: 2332 | M19: 120 | N19: 285 | O19: 5698 | P19: 297 | Q19: 2058 | R19: 3779 | S19: 4712 | U19: 5243 | V19: 2338 | W19: 839 | X19: 2732 | Y19: 1573 | Z19: 2660 | AA19: 1137 | AB19: 1891 | AC19: RECIFE
A20: RIBEIRÃO PRETO | B20: 2106 | C20: 2622 | D20: 523 | E20: 4445 | F20: 706 | G20: 930 | H20: 1303 | I20: 681 | J20: 988 | K20: 2978 | L20: 615 | M20: 2699 | N20: 2382 | O20: 3660 | P20: 2876 | Q20: 1491 | R20: 1342 | S20: 2759 | T20: 2589 | U20: 3293 | V20: 725 | W20: 1900 | X20: 391 | Y20: 2659 | Z20: 319 | AA20: 2483 | AB20: 1048 | AC20: RIBEIRÃO PRETO
A21: RIO BRANCO | B21: 4763 | C21: 4931 | D21: 3584 | E21: 2230 | F21: 3123 | G21: 2684 | H21: 1990 | I21: 3669 | J21: 3976 | K21: 5396 | L21: 2924 | M21: 5356 | N21: 5039 | O21: 1445 | P21: 5533 | Q21: 3764 | R21: 4196 | S21: 544 | T21: 5243 | V21: 4007 | W21: 4457 | X21: 3673 | Y21: 4968 | Z21: 3604 | AA21: 4900 | AB21: 4109 | AC21: RIO BRANCO
A22: RIO DE JANEIRO | B22: 1855 | C22: 3250 | D22: 434 | E22: 5159 | F22: 1148 | G22: 1444 | H22: 2017 | I22: 852 | J22: 1144 | K22: 2805 | L22: 1338 | M22: 2448 | N22: 2131 | O22: 4374 | P22: 2625 | Q22: 2124 | R22: 1553 | S22: 3473 | T22: 2338 | U22: 4007 | W22: 1649 | X22: 501 | Y22: 3015 | Z22: 429 | AA22: 2579 | AB22: 521 | AC22: RIO DE JANEIRO
A23: RIO VERDE | B23: 2165 | C23: 2248 | D23: 901 | E23: 3841 | F23: 440 | G23: 747 | H23: 699 | I23: 1181 | J23: 1488 | K23: 2713 | L23: 241 | M23: 2758 | N23: 2441 | O23: 3056 | P23: 2935 | Q23: 1091 | R23: 1842 | S23: 2155 | T23: 2648 | U23: 2689 | V23: 1324 | W23: 1959 | X23: 993 | Y23: 2285 | Z23: 921 | AA23: 2217 | AB23: 1426 | AC23: RIO VERDE
A24: SALVADOR | B24: 356 | C24: 2100 | D24: 1372 | E24: 5749 | F24: 1446 | G24: 2568 | H24: 2567 | I24: 2385 | J24: 2682 | K24: 1389 | L24: 1643 | M24: 949 | N24: 632 | O24: 5009 | P24: 1126 | Q24: 1454 | R24: 3090 | S24: 4023 | T24: 839 | U24: 4457 | V24: 1649 | X24: 2034 | Y24: 1599 | Z24: 1962 | AA24: 1163 | AB24: 1202 | AC24: SALVADOR
A25: SÃO LUÍS | B25: 1578 | C25: 806 | D25: 2738 | E25: 6120 | F25: 2157 | G25: 2979 | H25: 2978 | I25: 3230 | J25: 3537 | K25: 1070 | L25: 2054 | M25: 1660 | N25: 1672 | O25: 5335 | P25: 1607 | Q25: 1386 | R25: 3891 | S25: 4434 | T25: 1573 | U25: 4968 | V25: 3015 | W25: 1599 | X25: 3042 | Z25: 2970 | AA25: 446 | AB25: 2607 | AC25: SÃO LUÍS
A26: SÃO PAULO | B26: 2188 | C26: 2933 | D26: 586 | E26: 4756 | F26: 1015 | G26: 1014 | H26: 1614 | I26: 408 | J26: 705 | K26: 3127 | L26: 926 | M26: 2770 | N26: 2453 | O26: 3971 | P26: 2947 | Q26: 1776 | R26: 1109 | S26: 3070 | T26: 2660 | U26: 3604 | V26: 429 | W26: 1962 | X26: 72 | Y26: 2970 | AA26: 2792 | AB26: 882 | AC26: SÃO PAULO
A27: TERESINA | B27: 1142 | C27: 947 | D27: 2302 | E27: 6052 | F27: 1789 | G27: 2911 | H27: 2910 | I27: 3143 | J27: 3450 | K27: 634 | L27: 1986 | M27: 1224 | N27: 1236 | O27: 5267 | P27: 1171 | Q27: 1401 | R27: 3804 | S27: 4366 | T27: 1137 | U27: 4900 | V27: 2579 | W27: 1163 | X27: 2864 | Y27: 446 | Z27: 2792 | AB27: 2171 | AC27: TERESINA
A28: VITÓRIA | B28: 1408 | C28: 3108 | D28: 524 | E28: 5261 | F28: 1238 | G28: 1892 | H28: 2119 | I28: 1300 | J28: 1597 | K28: 2397 | L28: 1428 | M28: 2001 | N28: 1684 | O28: 4476 | P28: 2178 | Q28: 2214 | R28: 2001 | S28: 3575 | T28: 1891 | U28: 4109 | V28: 521 | W28: 1202 | X28: 954 | Y28: 2607 | Z28: 882 | AA28: 2171 | AC28: VITÓRIA
B29: ARACAJÚ | C29: BELÉM | D29: BELO HORIZONTE | E29: BOA VISTA | F29: BRASÍLIA | G29: CAMPO GRANDE | H29: CUIABÁ | I29: CURITIBA | J29: FLORIANÓPOLIS | K29: FORTALEZA | L29: GOIÂNIA | M29: JOÃO PESSOA | N29: MACEIÓ | O29: MANAUS | P29: NATAL | Q29: PALMAS | R29: PORTO ALEGRE | S29: PORTO VELHO | T29: RECIFE | U29: RIO BRANCO | V29: RIO DE JANEIRO | W29: SALVADOR | X29: SANTOS | Y29: SÃO LUÍS | Z29: SÃO PAULO | AA29: TERESINA | AB29: VITÓRIA
A30: DNER/AP/Div. Planejamento - Serv. Coord. e Gerência de Sistemas Rodoviários ---- Sugestões ( 061) 315-4151.
A32: https://www.google.com/search?q=quadro+de+dist%C3%A2ncias+rodovi%C3%A1rias+entre+as+principais+cidades+brasileiras&rlz=1C1CHBF_enUS880US880&oq=distancias+rodoviarias+&aqs=chrome.3.69i57j0i512j0i22i30l2.12778j0j4&sourceid=chrome&ie=UTF-8

Sheet Praticagem & Rebocadores
C2: Custo da Escala por Classe de Navio
B3: Porto | C3: 3500 TEU | D3: 3000 TEU | E3: 2500 TEU | F3: 2000 TEU
B4: MAO | C4: 1600000 | D4: =C4*0.9 -> 1440000 | E4: =D4*0.95 -> 1368000 | F4: =E4*0.9 -> 1231200
B5: VLC | C5: 70000 | D5: =C5*0.9 -> 63000 | E5: =D5*0.95 -> 59850 | F5: =E5*0.9 -> 53865
B6: ITQ | C6: 85000 | D6: =C6*0.9 -> 76500 | E6: =D6*0.95 -> 72675 | F6: =E6*0.9 -> 65407.5
B7: PEC | C7: 120000 | D7: =C7*0.9 -> 108000 | E7: =D7*0.95 -> 102600 | F7: =E7*0.9 -> 92340
B8: SUA | C8: 80000 | D8: =C8*0.9 -> 72000 | E8: =D8*0.95 -> 68400 | F8: =E8*0.9 -> 61560
B9: SSA | C9: 75000 | D9: =C9*0.9 -> 67500 | E9: =D9*0.95 -> 64125 | F9: =E9*0.9 -> 57712.5
B10: VIX | C10: 70000 | D10: =C10*0.9 -> 63000 | E10: =D10*0.95 -> 59850 | F10: =E10*0.9 -> 53865
B11: SPB | C11: 90000 | D11: =C11*0.9 -> 81000 | E11: =D11*0.95 -> 76950 | F11: =E11*0.9 -> 69255
B12: RIO | C12: 90000 | D12: =C12*0.9 -> 81000 | E12: =D12*0.95 -> 76950 | F12: =E12*0.9 -> 69255
B13: SSZ | C13: 190000 | D13: =C13*0.9 -> 171000 | E13: =D13*0.95 -> 162450 | F13: =E13*0.9 -> 146205
B14: PNG | C14: 110000 | D14: =C14*0.9 -> 99000 | E14: =D14*0.95 -> 94050 | F14: =E14*0.9 -> 84645
B15: IOA | C15: 95000 | D15: =C15*0.9 -> 85500 | E15: =D15*0.95 -> 81225 | F15: =E15*0.9 -> 73102.5
... B19: RIG | C19: 110000 | D19: =C19*0.9 -> 99000 | E19: =D19*0.95 -> 94050 | F19: =E19*0.9 -> 84645

Sheet Navios
C3: Dados dos Navios por Classe
C4: Item | D4: 3500 TEU | E4: 3000 TEU | F4: 2500 TEU | G4: 2000 TEU | H4: Unidade
C5: Custo Diário | D5: 25000 | E5: 21000 | F5: 18000 | G5: 15000 | H5: USD/dia
C6: Deadweight carga | D6: =D8*14 -> 39200 | E6: =E8*14 -> 33600 | F6: =F8*14 -> 28000 | G6: =G8*14 -> 22400 | H6: t
C7: Capacidade Nominal | D7: 3500 | E7: 3000 | F7: 2500 | G7: 2000 | H7: TEU
C8: Capacidade @14t | D8: =D7*0.8 -> 2800 | E8: =E7*0.8 -> 2400 | F8: =F7*0.8 -> 2000 | G8: =G7*0.8 -> 1600 | H8: TEU
C9: Plugs | D9: 400 | E9: 350 | F9: 300 | G9: 200 | H9: plug
C10: Consumo MDO viagem | D10: 2 | E10: 2 | F10: 2 | G10: 2 | H10: t/dia
C11: Consumo MDO porto | D11: 3 | E11: 3 | F11: 3 | G11: 3 | H11: t/dia
C12: Calado máximo | D12: =(D6*0.055)^(1/3) -> 12.918624 | E12: =(E6*0.055)^(1/3) -> 12.271585 | F12: =(F6*0.055)^(1/3) -> 11.548004 | G12: =(G6*0.055)^(1/3) -> 10.720217 | H12: m
C13: Velocidade Máxima | D13: 20 | E13: 20 | F13: 19 | G13: 19 | H13: mn/h

Sheet Terminais Contêineres & Depots
C2: Terminais de Contêineres | G2: Depot
B3: Porto | C3: Custo de Movimentação Contêiner Cheio | D3: Custo de Movimentação Contêiner Vazio | E3: Produtividade (contêineres/h) | G3: Porto | H3: Custo de Movimentação de Contêiner Vazio | I3: Custo de Transporte de Contêiner Vazio
B4: MAO | C4: 750 | D4: =C4/3 -> 250 | E4: 35 | G4: MAO | H4: 100 | I4: 210
B5: VLC | C5: 800 | D5: =C5/3 -> 266.66667 | E5: 25 | G5: VLC | H5: 100 | I5: 210
B6: SLZ | C6: 850 | D6: =C6/3 -> 283.33333 | E6: 25 | G6: ITQ | H6: 100 | I6: 210
B7: PEC | C7: 650 | D7: =C7/3 -> 216.66667 | E7: 40 | G7: PEC | H7: 100 | I7: 210
B8: SUA | C8: 1100 | D8: =C8/3 -> 366.66667 | E8: 45 | G8: SUA | H8: 100 | I8: 210
B9: SSA | C9: 750 | D9: =C9/3 -> 250 | E9: 50 | G9: SSA | H9: 100 | I9: 210
B10: VIX | C10: 850 | D10: =C10/3 -> 283.33333 | E10: 35 | G10: VIX | H10: 100 | I10: 210
B11: IGI | C11: 850 | D11: =C11/3 -> 283.33333 | E11: 50 | G11: SPB | H11: 100 | I11: 210
B12: RIO | C12: 850 | D12: =C12/3 -> 283.33333 | E12: 50 | G12: RIO | H12: 100 | I12: 210
B13: SSZ | C13: 750 | D13: =C13/3 -> 250 | E13: 50 | G13: SSZ | H13: 100 | I13: 210
B14: PNG | C14: 750 | D14: =C14/3 -> 250 | E14: 50 | G14: PNG | H14: 100 | I14: 210
B15: IOA | C15: 800 | D15: =C15/3 -> 266.66667 | E15: 50 | G15: IOA | H15: 100 | I15: 210
... B19: RIG | C19: 950 | D19: =C19/3 -> 316.66667 | E19: 50 | G19: RIG | H19: 100 | I19: 210

Sheet Contêiner
C2: Custo de Aluguel de Contêineres
C3: Tipo | D3: Valor (USD/dia)
C4: 20DC | D4: 0.8
C5: 20RF | D5: 12
C6: 40HC | D6: 1.2
C7: 40RH | D7: 17

Sheet Combustíveis & Taxa Câmbio
C2: Combustível | D2: Preço | E2: Unidade
C3: VLSFO | D3: 582 | E3: USD/t
C4: MDO | D4: 788 | E4: USD/t
C7: Item | D7: Valor | E7: Unidade
C8: Taxa de Câmbio | D8: 4.99 | E8: BRL/USD

Sheet Corrente Marítima
B2: Trecho | C2: Corrente Marítima (nós) | E2: Não serão consideradas
B3: IBI/IOA | C3: 0
B4: IOA/PNG | C4: 0
B5: IOA/IGI | C5: 0
B6: SLZ/PEC | C6: 0
B7: PEC/SUA | C7: 0
B8: PNG/SSZ | C8: 0
B9: RIG/IOA | C9: 0
B10: RIO/SUA | C10: 0
B11: IGI/SSA | C11: 0
B12: SSA/SUA | C12: 0
B13: SSA/VIX | C13: 0
B14: SSZ/IOA | C14: 0
... B20: VIX/RIO | C20: 0

Sheet Distancia Portos
C2: orig/dest | D2: Distância entre Portos (mn)
C3: Porto | D3: MAO | E3: VLC | F3: SLZ | G3: PEC | H3: SUA | I3: SSA | J3: VIX | K3: IGI | L3: RIO | M3: SSZ | N3: PNG | O3: IOA | P3: ITJ | Q3: NVT | R3: IBI | S3: RIG
C4: MAO | D4: 0 | E4: 873.11047 | F4: 1300.2165 | G4: 1569 | H4: 2045.8971 | I4: 2408.7482 | J4: 2832.0745 | K4: 3170.0875 | L4: 3102.053 | M4: 3300.2172 | N4: 3429.8069 | O4: 3460.0445 | P4: 3469.2237 | Q4: 3469.2237 | R4: 3537.7983 | S4: 3834.7746
C5: VLC | D5: 873.11047 | E5: 0 | F5: 427.10599 | G5: 696 | H5: 1172.7866 | I5: 1536.1777 | J5: 1958.964 | K5: 2296.9771 | L5: 2228.9425 | M5: 2427.1067 | N5: 2557.2364 | O5: 2586.934 | P5: 2596.1133 | Q5: 2596.1133 | R5: 2665.2278 | S5: 2962.2041
C6: SLZ | D6: 1300.2165 | E6: 427.10599 | F6: 0 | G6: 381 | H6: 836.93335 | I6: 1212.2035 | J6: 1634.9898 | K6: 1973.0029 | L6: 1904.9683 | M6: 2103.1325 | N6: 2233.2622 | O6: 2262.9598 | P6: 2272.1391 | Q6: 2272.1391 | R6: 2341.2536 | S6: 2638.2299
C7: PEC | D7: 1569 | E7: 696 | F7: 381 | G7: 0 | H7: 478 | I7: 853 | J7: 1276 | K7: 1614 | L7: 1546 | M7: 1744 | N7: 1874 | O7: 1876.3506 | P7: 1913 | Q7: 1913 | R7: 1982 | S7: 2282
C8: SUA | D8: 2045.8971 | E8: 1172.7866 | F8: 836.93335 | G8: 478 | H8: 0 | I8: 375.27012 | J8: 798.05645 | K8: 1129.0501 | L8: 1061.0155 | M8: 1259.1797 | N8: 1388.7694 | O8: 1419.007 | P8: 1428.1863 | Q8: 1428.1863 | R8: 1496.7608 | S8: 1843.9532
C9: SSA | D9: 2408.7482 | E9: 1536.1777 | F9: 1212.2035 | G9: 853 | H9: 375.27012 | I9: 0 | J9: 482.1816 | K9: 813.17524 | L9: 745.14066 | M9: 942.76492 | N9: 1072.8946 | O9: 1103.1322 | P9: 1111.7715 | Q9: 1111.7715 | R9: 1180.886 | S9: 1477.8623
C10: VIX | D10: 2832.0745 | E10: 1958.964 | F10: 1634.9898 | G10: 1276 | H10: 798.05645 | I10: 482.1816 | J10: 0 | K10: 349.89214 | L10: 281.85755 | M10: 480.02177 | N10: 610.15141 | O10: 639.84905 | P10: 649.02831 | Q10: 649.02831 | R10: 718.14281 | S10: 1015.1192
C11: IGI | D11: 3170.0875 | E11: 2296.9771 | F11: 1973.0029 | G11: 1614 | H11: 1129.0501 | I11: 813.17524 | J11: 349.89214 | K11: 0 | L11: 68 | M11: 191.14478 | N11: 321.81437 | O11: 349.89214 | P11: 366.09085 | Q11: 366.09085 | R11: 433.04551 | S11: 738.12122
C12: RIO | D12: 3102.053 | E12: 2228.9425 | F12: 1904.9683 | G12: 1546 | H12: 1061.0155 | I12: 745.14066 | J12: 281.85755 | K12: 68 | L12: 0 | M12: 219.7625 | N12: 349.89214 | O12: 380.12973 | P12: 388.76904 | Q12: 388.76904 | R12: 457.88354 | S12: 754.85989
C13: SSZ | D13: 3300.2172 | E13: 2427.1067 | F13: 2103.1325 | G13: 1744 | H13: 1259.1797 | I13: 942.76492 | J13: 480.02177 | K13: 191.14478 | L13: 219.7625 | M13: 0 | N13: 167.92663 | O13: 192.22469 | P13: 226.24198 | Q13: 226.24198 | R13: 286.17721 | S13: 605.83175
C14: PNG | D14: 3430 | E14: 2557.2364 | F14: 2233.2622 | G14: 1874 | H14: 1388.7694 | I14: 1072.8946 | J14: 610.15141 | K14: 321.81437 | L14: 349.89214 | M14: 167.92663 | N14: 0 | O14: 59.935227 | P14: 104.2117 | Q14: 104.2117 | R14: 180.88559 | S14: 498.92027
C15: IOA | D15: 3460.0445 | E15: 2586.934 | F15: 2262.9598 | G15: 1876.3506 | H15: 1419.007 | I15: 1103.1322 | J15: 639.84905 | K15: 349.89214 | L15: 380.12973 | M15: 192.22469 | N15: 59.935227 | O15: 0 | P15: 63.174969 | Q15: 63.174969 | R15: 143.08861 | S15: 461.12328
... C19: RIG | D19: 3834.7746 | E19: 2962.2041 | F19: 2638.2299 | G19: 2282 | H19: 1843.9532 | I19: 1477.8623 | J19: 1015.1192 | K19: 738.12122 | L19: 754.85989 | M19: 605.83175 | N19: 498.92027 | O19: 461.12328 | P19: 410.90728 | Q19: 410.90728 | R19: 321.81437 | S19: 0

Sheet OTIMIZA ROTA
B2: POTENCIAL ANUAL | K2: SEMANAL POTENCIAL ESCOLHIDO CHEIO - ANTAC | T2: SEMANAL POTENCIAL ESCOLHIDO VAZIO | AF2: TONELAGEM SEMANAL ESCOLHIDO | AO2: TEU SEMANAL ESCOLHIDO | AX2: RECEITA SEMANAL
B4: Movimentação de Contêineres na Cabotagem em 2022 - 20DC | K4: Movimentação 2022 - 20DC | T4: Imbalance 20DC | W4: MATRIZ OD 20 DC VAZIOS | AF4: MATRIZ OD 20 DC CHEIOS - TONELADAS | AO4: MATRIZ OD 20 DC CHEIOS - TEU | AX4: RECEITA - 20DC
B5: Origem/Destino | C5: AM | D5: CE | E5: PE | F5: BA | G5: SP | H5: SC | I5: Total Origem | K5: Origem/Destino | L5: AM | M5: CE | N5: PE | O5: BA | P5: SP | Q5: SC | R5: Total Origem | T5: Porto | U5: IMB | W5: Origem/Destino | X5: AM | Y5: CE | Z5: PE | AA5: BA | AB5: SP | AC5: SC | AD5: Total Origem | AF5: Origem/Destino | AG5: AM | AH5: CE | AI5: PE | AJ5: BA | AK5: SP | AL5: SC | AM5: Total Origem | AO5: Origem/Destino | AP5: AM | AQ5: CE | AR5: PE | AS5: BA | AT5: SP | AU5: SC | AV5: Total Origem | AX5: Origem/Destino | AY5: AM | AZ5: CE | BA5: PE | BB5: BA | BC5: SP | BD5: SC | BE5: Total Origem
B6: AM | D6: 1747 | E6: 313 | F6: 329 | G6: 2513 | H6: 475 | I6: =SUM(C6:H6) -> 5377 | K6: AM | L6: =INT(C6/52) -> 0 | M6: 0 | N6: =INT(E6/52) -> 6 | O6: 0 | P6: =INT(G6/52) -> 48 | Q6: =INT(H6/52) -> 9 | R6: =SUM(L6:Q6) -> 63 | T6: AM | U6: =L12-$R6 -> 144 | W6: AM | AC6: =U6 -> 144 | AD6: =SUM(X6:AC6) -> 144 | AF6: AM | AG6: =L68*28 -> 0 | AH6: =M68*28 -> 0 | AI6: =N68*28 -> 168 | AJ6: =O68*28 -> 0 | AK6: =P68*28 -> 1344 | AL6: =Q68*28 -> 252 | AM6: =SUM(AG6:AL6) -> 1764 | AO6: AM | AP6: =L68 -> 0 | AQ6: =M68 -> 0 | AR6: =N68 -> 6 | AS6: =O68 -> 0 | AT6: =P68 -> 48 | AU6: =Q68 -> 9 | AV6: =SUM(AP6:AU6) -> 63 | AX6: AM | AY6: =L68*C76 -> 0 | AZ6: =M68*D76 -> 0 | BA6: =N68*E76 -> 96682.396 | BB6: =O68*F76 -> 0 | BC6: =P68*G76 -> 986384.02 | BD6: =Q68*H76 -> 211299.24 | BE6: =SUM(AY6:BD6) -> 1294365.7
B7: CE | C7: 2926 | E7: 282 | F7: 491 | G7: 9135 | H7: 4055 | I7: =SUM(C7:H7) -> 16889 | K7: CE | L7: =INT(C7/52) -> 56 | M7: =INT(D7/52) -> 0 | N7: 0 | O7: 0 | P7: 0 | Q7: 0 | R7: =SUM(L7:Q7) -> 56 | T7: CE | U7: =M12-$R7 -> 335 | W7: CE | AB7: =U7-(U7+U10+AB9) -> 68 | AC7: =U7-AB7 -> 267 | AD7: =SUM(X7:AC7) -> 335 | AF7: CE | AG7: =L69*28 -> 1568 | AH7: =M69*28 -> 0 | AI7: =N69*28 -> 0 | AJ7: =O69*28 -> 0 | AK7: =P69*28 -> 0 | AL7: =Q69*28 -> 0 | AM7: =SUM(AG7:AL7) -> 1568 | AO7: CE | AP7: =L69 -> 56 | AQ7: =M69 -> 0 | AR7: =N69 -> 0 | AS7: =O69 -> 0 | AT7: =P69 -> 0 | AU7: =Q69 -> 0 | AV7: =SUM(AP7:AU7) -> 56 | AX7: CE | AY7: =L69*C77 -> 768475.08 | AZ7: =M69*D77 -> 0 | BA7: =N69*E77 -> 0 | BB7: =O69*F77 -> 0 | BC7: =P69*G77 -> 0 | BD7: =Q69*H77 -> 0 | BE7: =SUM(AY7:BD7) -> 768475.08
B8: PE | C8: 2039 | D8: 1481 | F8: 2967 | G8: 8519 | H8: 827 | I8: =SUM(C8:H8) -> 15833 | K8: PE | L8: =INT(C8/52) -> 39 | M8: =INT(D8/52) -> 28 | N8: =INT(E8/52) -> 0 | O8: 0 | P8: =INT(G8/52) -> 163 | Q8: =INT(H8/52) -> 15 | R8: =SUM(L8:Q8) -> 245 | T8: PE | U8: =N12-$R8 -> 160 | W8: PE | AC8: =U8 -> 160 | AD8: =SUM(X8:AC8) -> 160 | AF8: PE | AG8: =L70*28 -> 1092 | AH8: =M70*28 -> 784 | AI8: =N70*28 -> 0 | AJ8: =O70*28 -> 0 | AK8: =P70*28 -> 532 | AL8: =Q70*28 -> 420 | AM8: =SUM(AG8:AL8) -> 2828 | AO8: PE | AP8: =L70 -> 39 | AQ8: =M70 -> 28 | AR8: =N70 -> 0 | AS8: =O70 -> 0 | AT8: =P70 -> 19 | AU8: =Q70 -> 15 | AV8: =SUM(AP8:AU8) -> 101 | AX8: PE | AY8: =L70*C78 -> 628435.58 | AZ8: =M70*D78 -> 128325.94 | BA8: =N70*E78 -> 0 | BB8: =O70*F78 -> 0 | BC8: =P70*G78 -> 269576.48 | BD8: =Q70*H78 -> 268208.17 | BE8: =SUM(AY8:BD8) -> 1294546.2
B9: BA | C9: 407 | D9: 779 | E9: 670 | G9: 10907 | H9: 289 | I9: =SUM(C9:H9) -> 13052 | K9: BA | L9: =INT(C9/52) -> 7 | M9: =INT(D9/52) -> 14 | N9: =INT(E9/52) -> 12 | O9: =INT(F9/52) -> 0 | P9: 0 | Q9: 0 | R9: =SUM(L9:Q9) -> 33 | T9: BA | U9: =O12-$R9 -> 86 | W9: BA | AB9: =U9 -> 86 | AD9: =SUM(X9:AC9) -> 86 | AF9: BA | AG9: =L71*28 -> 28 | AH9: =M71*28 -> 392 | AI9: =N71*28 -> 336 | AJ9: =O71*28 -> 0 | AK9: =P71*28 -> 0 | AL9: =Q71*28 -> 0 | AM9: =SUM(AG9:AL9) -> 756 | AO9: BA | AP9: =L71 -> 1 | AQ9: =M71 -> 14 | AR9: =N71 -> 12 | AS9: =O71 -> 0 | AT9: =P71 -> 0 | AU9: =Q71 -> 0 | AV9: =SUM(AP9:AU9) -> 27 | AX9: BA | AY9: =L71*C79 -> 16247.998 | AZ9: =M71*D79 -> 106745.88 | BA9: =N71*E79 -> 57413.617 | BB9: =O71*F79 -> 0 | BC9: =P71*G79 -> 0 | BD9: =Q71*H79 -> 0 | BE9: =SUM(AY9:BD9) -> 180407.49
B10: SP | C10: 4058 | D10: 6369 | E10: 6570 | F10: 2077 | I10: =SUM(C10:H10) -> 19074 | K10: SP | L10: =INT(C10/52) -> 78 | M10: =INT(D10/52) -> 122 | N10: =INT(E10/52) -> 126 | O10: =INT(F10/52) -> 39 | P10: =INT(G10/52) -> 0 | Q10: =INT(H10/52) -> 0 | R10: =SUM(L10:Q10) -> 365 | T10: SP | U10: =P12-$R10 -> -154 | W10: SP | AD10: =SUM(X10:AC10) -> 0 | AF10: SP | AG10: =L72*28 -> 0 | AH10: =M72*28 -> 392 | AI10: =N72*28 -> 1484 | AJ10: =O72*28 -> 0 | AK10: =P72*28 -> 0 | AL10: =Q72*28 -> 0 | AM10: =SUM(AG10:AL10) -> 1876 | AO10: SP | AP10: =L72 -> 0 | AQ10: =M72 -> 14 | AR10: =N72 -> 53 | AS10: =O72 -> 0 | AT10: =P72 -> 0 | AU10: =Q72 -> 0 | AV10: =SUM(AP10:AU10) -> 67 | AX10: SP | AY10: =L72*C80 -> 0 | AZ10: =M72*D80 -> 232397.98 | BA10: =N72*E80 -> 751976.5 | BB10: =O72*F80 -> 0 | BC10: =P72*G80 -> 0 | BD10: =Q72*H80 -> 0 | BE10: =SUM(AY10:BD10) -> 984374.48
B11: SC | C11: 1452 | D11: 11836 | E11: 13601 | F11: 4203 | I11: =SUM(C11:H11) -> 31092 | K11: SC | L11: =INT(C11/52) -> 27 | M11: =INT(D11/52) -> 227 | N11: =INT(E11/52) -> 261 | O11: =INT(F11/52) -> 80 | P11: =INT(G11/52) -> 0 | Q11: =INT(H11/52) -> 0 | R11: =SUM(L11:Q11) -> 595 | T11: SC | U11: =Q12-$R11 -> -571 | W11: SC | AD11: =SUM(X11:AC11) -> 0 | AF11: SC | AG11: =L73*28 -> 0 | AH11: =M73*28 -> 0 | AI11: =N73*28 -> 840 | AJ11: =O73*28 -> 756 | AK11: =P73*28 -> 0 | AL11: =Q73*28 -> 0 | AM11: =SUM(AG11:AL11) -> 1596 | AO11: SC | AP11: =L73 -> 0 | AQ11: =M73 -> 0 | AR11: =N73 -> 30 | AS11: =O73 -> 27 | AT11: =P73 -> 0 | AU11: =Q73 -> 0 | AV11: =SUM(AP11:AU11) -> 57 | AX11: SC | AY11: =L73*C81 -> 0 | AZ11: =M73*D81 -> 0 | BA11: =N73*E81 -> 536416.33 | BB11: =O73*F81 -> 386149.83 | BC11: =P73*G81 -> 0 | BD11: =Q73*H81 -> 0 | BE11: =SUM(AY11:BD11) -> 922566.16
B12: Total Destino | C12: =SUM(C6:C11) -> 10882 | D12: =SUM(D6:D11) -> 22212 | E12: =SUM(E6:E11) -> 21436 | F12: =SUM(F6:F11) -> 10067 | G12: =SUM(G6:G11) -> 31074 | H12: =SUM(H6:H11) -> 5646 | I12: =SUM(I6:I11) -> 101317 | K12: Total Destino | L12: =SUM(L6:L11) -> 207 | M12: =SUM(M6:M11) -> 391 | N12: =SUM(N6:N11) -> 405 | O12: =SUM(O6:O11) -> 119 | P12: =SUM(P6:P11) -> 211 | Q12: =SUM(Q6:Q11) -> 24 | R12: =SUM(R6:R11) -> 1357 | T12: Total | U12: =SUM(U6:U11) -> 0 | W12: Total Destino | X12: =SUM(X6:X11) -> 0 | Y12: =SUM(Y6:Y11) -> 0 | Z12: =SUM(Z6:Z11) -> 0 | AA12: =SUM(AA6:AA11) -> 0 | AB12: =SUM(AB6:AB11) -> 154 | AC12: =SUM(AC6:AC11) -> 571 | AD12: =SUM(AD6:AD11) -> 725 | AF12: Total Destino | AG12: =SUM(AG6:AG11) -> 2688 | AH12: =SUM(AH6:AH11) -> 1568 | AI12: =SUM(AI6:AI11) -> 2828 | AJ12: =SUM(AJ6:AJ11) -> 756 | AK12: =SUM(AK6:AK11) -> 1876 | AL12: =SUM(AL6:AL11) -> 672 | AM12: =SUM(AM6:AM11) -> 10388 | AO12: Total Destino | AP12: =SUM(AP6:AP11) -> 96 | AQ12: =SUM(AQ6:AQ11) -> 56 | AR12: =SUM(AR6:AR11) -> 101 | AS12: =SUM(AS6:AS11) -> 27 | AT12: =SUM(AT6:AT11) -> 67 | AU12: =SUM(AU6:AU11) -> 24 | AV12: =SUM(AV6:AV11) -> 371 | AX12: Total Destino | AY12: =SUM(AY6:AY11) -> 1413158.7 | AZ12: =SUM(AZ6:AZ11) -> 467469.8 | BA12: =SUM(BA6:BA11) -> 1442488.9 | BB12: =SUM(BB6:BB11) -> 386149.83 | BC12: =SUM(BC6:BC11) -> 1255960.5 | BD12: =SUM(BD6:BD11) -> 479507.41 | BE12: =SUM(BE6:BE11) -> 5444735
BD13: REC. SEM. | BE13: =SUM(AY6:BD11) -> 5444735
B14: Movimentação de Contêineres na Cabotagem em 2022 - 20RF | K14: Movimentação 2022 - 20 RF | T14: Imbalance 40RH | W14: MATRIZ OD 40HC VAZIOS | AF14: MATRIZ OD 40 HC CHEIOS - TONELADAS | AO14: MATRIZ OD 40 HC CHEIOS - TEU | AX14: Movimentação 2022 - 40HC
B15: Origem/Destino | C15: AM | D15: CE | E15: PE | F15: BA | G15: SP | H15: SC | I15: Total Origem | K15: Origem/Destino | L15: AM | M15: CE | N15: PE | O15: BA | P15: SP | Q15: SC | R15: Total Origem | T15: Porto | U15: IMB | W15: Origem/Destino | X15: AM | Y15: CE | Z15: PE | AA15: BA | AB15: SP | AC15: SC | AD15: Total Origem | AF15: Origem/Destino | AG15: AM | AH15: CE | AI15: PE | AJ15: BA | AK15: SP | AL15: SC | AM15: Total Origem | AO15: Origem/Destino | AP15: AM | AQ15: CE | AR15: PE | AS15: BA | AT15: SP | AU15: SC | AV15: Total Origem | AX15: Origem/Destino | AY15: AM | AZ15: CE | BA15: PE | BB15: BA | BC15: SP | BD15: SC | BE15: Total Origem
B16: AM | E16: 1 | F16: 2 | I16: =SUM(C16:H16) -> 3 | K16: AM | L16: =INT(C16/52) -> 0 | M16: =INT(D16/52) -> 0 | N16: =INT(E16/52) -> 0 | O16: =INT(F16/52) -> 0 | P16: =INT(G16/52) -> 0 | Q16: =INT(H16/52) -> 0 | R16: =SUM(L16:Q16) -> 0 | T16: AM | U16: =L32-R26 -> -163 | W16: AM | AD16: =SUM(X16:AC16) -> 0 | AF16: AM | AG16: =L78*28 -> 0 | AH16: =M78*28 -> 0 | AI16: =N78*28 -> 4424 | AJ16: =O78*28 -> 0 | AK16: =P78*28 -> 29596 | AL16: =Q78*28 -> 2940 | AM16: =SUM(AG16:AL16) -> 36960 | AO16: AM | AP16: =L78*2 -> 0 | AQ16: =M78*2 -> 0 | AR16: =N78*2 -> 316 | AS16: =O78*2 -> 0 | AT16: =P78*2 -> 2114 | AU16: =Q78*2 -> 210 | AV16: =SUM(AP16:AU16) -> 2640 | AX16: AM | AY16: =L78*C76 -> 0 | AZ16: =M78*D76 -> 0 | BA16: =N78*E76 -> 2545969.8 | BB16: =O78*F76 -> 0 | BC16: =P78*G76 -> 21720998 | BD16: =Q78*H76 -> 2465157.8 | BE16: =SUM(AY16:BD16) -> 26732126
B17: CE | I17: =SUM(C17:H17) -> 0 | K17: CE | L17: =INT(C17/52) -> 0 | M17: =INT(D17/52) -> 0 | N17: =INT(E17/52) -> 0 | O17: =INT(F17/52) -> 0 | P17: =INT(G17/52) -> 0 | Q17: =INT(H17/52) -> 0 | R17: =SUM(L17:Q17) -> 0 | T17: CE | U17: =M32-R27 -> 630 | W17: CE | AC17: =U17 -> 630 | AD17: =SUM(X17:AC17) -> 630 | AF17: CE | AG17: =L79*28 -> 5544 | AH17: =M79*28 -> 0 | AI17: =N79*28 -> 0 | AJ17: =O79*28 -> 0 | AK17: =P79*28 -> 0 | AL17: =Q79*28 -> 0 | AM17: =SUM(AG17:AL17) -> 5544 | AO17: CE | AP17: =L79*2 -> 396 | AQ17: =M79*2 -> 0 | AR17: =N79*2 -> 0 | AS17: =O79*2 -> 0 | AT17: =P79*2 -> 0 | AU17: =Q79*2 -> 0 | AV17: =SUM(AP17:AU17) -> 396 | AX17: CE | AY17: =L79*C77 -> 2717108.3 | AZ17: =M79*D77 -> 0 | BA17: =N79*E77 -> 0 | BB17: =O79*F77 -> 0 | BC17: =P79*G77 -> 0 | BD17: =Q79*H77 -> 0 | BE17: =SUM(AY17:BD17) -> 2717108.3
B18: PE | D18: 3 | G18: 1 | H18: 4 | I18: =SUM(C18:H18) -> 8 | K18: PE | L18: =INT(C18/52) -> 0 | M18: =INT(D18/52) -> 0 | N18: =INT(E18/52) -> 0 | O18: =INT(F18/52) -> 0 | P18: =INT(G18/52) -> 0 | Q18: =INT(H18/52) -> 0 | R18: =SUM(L18:Q18) -> 0 | T18: PE | U18: =N32-R28 -> 429 | W18: PE | X18: =U18-(U18+U16+X19) -> 160 | AB18: =U18-(U18+U20) -> 187 | AC18: =U18-X18-AB18 -> 82 | AD18: =SUM(X18:AC18) -> 429 | AF18: PE | AG18: =L80*28 -> 9408 | AH18: =M80*28 -> 2716 | AI18: =N80*28 -> 0 | AJ18: =O80*28 -> 0 | AK18: =P80*28 -> 0 | AL18: =Q80*28 -> 2296 | AM18: =SUM(AG18:AL18) -> 14420 | AO18: PE | AP18: =L80*2 -> 672 | AQ18: =M80*2 -> 194 | AR18: =N80*2 -> 0 | AS18: =O80*2 -> 0 | AT18: =P80*2 -> 0 | AU18: =Q80*2 -> 164 | AV18: =SUM(AP18:AU18) -> 1030 | AX18: PE | AY18: =L80*C78 -> 5414214.2 | AZ18: =M80*D78 -> 444557.73 | BA18: =N80*E78 -> 0 | BB18: =O80*F78 -> 0 | BC18: =P80*G78 -> 0 | BD18: =Q80*H78 -> 1466204.6 | BE18: =SUM(AY18:BD18) -> 7324976.6
B19: BA | D19: 4 | E19: 2 | G19: 2 | H19: 2 | I19: =SUM(C19:H19) -> 10 | K19: BA | L19: =INT(C19/52) -> 0 | M19: =INT(D19/52) -> 0 | N19: =INT(E19/52) -> 0 | O19: =INT(F19/52) -> 0 | P19: =INT(G19/52) -> 0 | Q19: =INT(H19/52) -> 0 | R19: =SUM(L19:Q19) -> 0 | T19: BA | U19: =O32-R29 -> 3 | W19: BA | X19: =U19 -> 3 | AD19: =SUM(X19:AC19) -> 3 | AF19: BA | AG19: =L81*28 -> 1736 | AH19: =M81*28 -> 616 | AI19: =N81*28 -> 0 | AJ19: =O81*28 -> 0 | AK19: =P81*28 -> 0 | AL19: =Q81*28 -> 0 | AM19: =SUM(AG19:AL19) -> 2352 | AO19: BA | AP19: =L81*2 -> 124 | AQ19: =M81*2 -> 44 | AR19: =N81*2 -> 0 | AS19: =O81*2 -> 0 | AT19: =P81*2 -> 0 | AU19: =Q81*2 -> 0 | AV19: =SUM(AP19:AU19) -> 168 | AX19: BA | AY19: =L81*C79 -> 1007375.9 | AZ19: =M81*D79 -> 167743.52 | BA19: =N81*E79 -> 0 | BB19: =O81*F79 -> 0 | BC19: =P81*G79 -> 0 | BD19: =Q81*H79 -> 0 | BE19: =SUM(AY19:BD19) -> 1175119.4
B20: SP | D20: 17 | E20: 16 | F20: 2 | I20: =SUM(C20:H20) -> 35 | K20: SP | L20: =INT(C20/52) -> 0 | M20: =INT(D20/52) -> 0 | N20: =INT(E20/52) -> 0 | O20: =INT(F20/52) -> 0 | P20: =INT(G20/52) -> 0 | Q20: =INT(H20/52) -> 0 | R20: =SUM(L20:Q20) -> 0 | T20: SP | U20: =P32-R30 -> -187 | W20: SP | AD20: =SUM(X20:AC20) -> 0 | AF20: SP | AG20: =L82*28 -> 9688 | AH20: =M82*28 -> 2212 | AI20: =N82*28 -> 15344 | AJ20: =O82*28 -> 2352 | AK20: =P82*28 -> 0 | AL20: =Q82*28 -> 0 | AM20: =SUM(AG20:AL20) -> 29596 | AO20: SP | AP20: =L82*2 -> 692 | AQ20: =M82*2 -> 158 | AR20: =N82*2 -> 1096 | AS20: =O82*2 -> 168 | AT20: =P82*2 -> 0 | AU20: =Q82*2 -> 0 | AV20: =SUM(AP20:AU20) -> 2114 | AX20: SP | AY20: =L82*C80 -> 7110184.8 | AZ20: =M82*D80 -> 1311388.6 | BA20: =N82*E80 -> 7775153.3 | BB20: =O82*F80 -> 889032.18 | BC20: =P82*G80 -> 0 | BD20: =Q82*H80 -> 0 | BE20: =SUM(AY20:BD20) -> 17085759
B21: SC | D21: 7 | E21: 9 | I21: =SUM(C21:H21) -> 16 | K21: SC | L21: =INT(C21/52) -> 0 | M21: =INT(D21/52) -> 0 | N21: =INT(E21/52) -> 0 | O21: =INT(F21/52) -> 0 | P21: =INT(G21/52) -> 0 | Q21: =INT(H21/52) -> 0 | R21: =SUM(L21:Q21) -> 0 | T21: SC | U21: =Q32-R31 -> -712 | W21: SC | AD21: =SUM(X21:AC21) -> 0 | AF21: SC | AG21: =L83*28 -> 5236 | AH21: =M83*28 -> 0 | AI21: =N83*28 -> 0 | AJ21: =O83*28 -> 0 | AK21: =P83*28 -> 0 | AL21: =Q83*28 -> 0 | AM21: =SUM(AG21:AL21) -> 5236 | AO21: SC | AP21: =L83*2 -> 374 | AQ21: =M83*2 -> 0 | AR21: =N83*2 -> 0 | AS21: =O83*2 -> 0 | AT21: =P83*2 -> 0 | AU21: =Q83*2 -> 0 | AV21: =SUM(AP21:AU21) -> 374 | AX21: SC | AY21: =L83*C81 -> 4390328.7 | AZ21: =M83*D81 -> 0 | BA21: =N83*E81 -> 0 | BB21: =O83*F81 -> 0 | BC21: =P83*G81 -> 0 | BD21: =Q83*H81 -> 0 | BE21: =SUM(AY21:BD21) -> 4390328.7
B22: Total Destino | C22: =SUM(C16:C21) -> 0 | D22: =SUM(D16:D21) -> 31 | E22: =SUM(E16:E21) -> 28 | F22: =SUM(F16:F21) -> 4 | G22: =SUM(G16:G21) -> 3 | H22: =SUM(H16:H21) -> 6 | I22: =SUM(I16:I21) -> 72 | K22: Total Destino | L22: =SUM(L16:L21) -> 0 | M22: =SUM(M16:M21) -> 0 | N22: =SUM(N16:N21) -> 0 | O22: =SUM(O16:O21) -> 0 | P22: =SUM(P16:P21) -> 0 | Q22: =SUM(Q16:Q21) -> 0 | R22: =SUM(R16:R21) -> 0 | T22: Total | U22: =SUM(U16:U21) -> 0 | W22: Total Destino | X22: =SUM(X16:X21) -> 163 | Y22: =SUM(Y16:Y21) -> 0 | Z22: =SUM(Z16:Z21) -> 0 | AA22: =SUM(AA16:AA21) -> 0 | AB22: =SUM(AB16:AB21) -> 187 | AC22: =SUM(AC16:AC21) -> 712 | AD22: =SUM(AD16:AD21) -> 1062 | AF22: Total Destino | AG22: =SUM(AG16:AG21) -> 31612 | AH22: =SUM(AH16:AH21) -> 5544 | AI22: =SUM(AI16:AI21) -> 19768 | AJ22: =SUM(AJ16:AJ21) -> 2352 | AK22: =SUM(AK16:AK21) -> 29596 | AL22: =SUM(AL16:AL21) -> 5236 | AM22: =SUM(AM16:AM21) -> 94108 | AO22: Total Destino | AP22: =SUM(AP16:AP21) -> 2258 | AQ22: =SUM(AQ16:AQ21) -> 396 | AR22: =SUM(AR16:AR21) -> 1412 | AS22: =SUM(AS16:AS21) -> 168 | AT22: =SUM(AT16:AT21) -> 2114 | AU22: =SUM(AU16:AU21) -> 374 | AV22: =SUM(AV16:AV21) -> 6722 | AX22: Total Destino | AY22: =SUM(AY16:AY21) -> 20639212 | AZ22: =SUM(AZ16:AZ21) -> 1923689.8 | BA22: =SUM(BA16:BA21) -> 10321123 | BB22: =SUM(BB16:BB21) -> 889032.18 | BC22: =SUM(BC16:BC21) -> 21720998 | BD22: =SUM(BD16:BD21) -> 3931362.5 | BE22: =SUM(BE16:BE21) -> 59425418
BD23: REC. SEM. | BE23: =SUM(AY16:BD21) -> 59425418
B24: Movimentação de Contêineres na Cabotagem em 2022 - 40HC | K24: Movimentação 2022 - 40HC | T24: Imbalance 40RH | W24: MATRIZ OD 40 RH VAZIOS | AF24: MATRIZ OD 40 RH CHEIOS - TONELADAS | AO24: MATRIZ OD 40 RH CHEIOS - TEU | AX24: Movimentação 2022 - 40RH
B25: Origem/Destino | C25: AM | D25: CE | E25: PE | F25: BA | G25: SP | H25: SC | I25: Total Origem | K25: Origem/Destino | L25: AM | M25: CE | N25: PE | O25: BA | P25: SP | Q25: SC | R25: Total Origem | T25: Porto | U25: IMB | W25: Origem/Destino | X25: AM | Y25: CE | Z25: PE | AA25: BA | AB25: SP | AC25: SC | AD25: Total Origem | AF25: Origem/Destino | AG25: AM | AH25: CE | AI25: PE | AJ25: BA | AK25: SP | AL25: SC | AM25: Total Origem | AO25: Origem/Destino | AP25: AM | AQ25: CE | AR25: PE | AS25: BA | AT25: SP | AU25: SC | AV25: Total Origem | AX25: Origem/Destino | AY25: AM | AZ25: CE | BA25: PE | BB25: BA | BC25: SP | BD25: SC | BE25: Total Origem
B26: AM | D26: 6066 | E26: 8232 | F26: 3166 | G26: 54983 | H26: 5501 | I26: =SUM(C26:H26) -> 77948 | K26: AM | L26: =INT(C26/52) -> 0 | M26: 0 | N26: =INT(E26/52) -> 158 | O26: 0 | P26: =INT(G26/52) -> 1057 | Q26: =INT(H26/52) -> 105 | R26: =SUM(L26:Q26) -> 1320 | T26: AM | U26: =L42-R36 -> 198 | W26: AM | AC26: =U26 -> 198 | AD26: =SUM(X26:AC26) -> 198 | AF26: AM | AG26: =L88*28 -> 0 | AH26: =M88*28 -> 0 | AI26: =N88*28 -> 0 | AJ26: =O88*28 -> 0 | AK26: =P88*28 -> 28 | AL26: =Q88*28 -> 0 | AM26: =SUM(AG26:AL26) -> 28 | AO26: AM | AP26: =L88*2 -> 0 | AQ26: =M88*2 -> 0 | AR26: =N88*2 -> 0 | AS26: =O88*2 -> 0 | AT26: =P88*2 -> 2 | AU26: =Q88*2 -> 0 | AV26: =SUM(AP26:AU26) -> 2 | AX26: AM | AY26: =L88*C76 -> 0 | AZ26: =M88*D76 -> 0 | BA26: =N88*E76 -> 0 | BB26: =O88*F76 -> 0 | BC26: =P88*G76 -> 20549.667 | BD26: =Q88*H76 -> 0 | BE26: =SUM(AY26:BD26) -> 20549.667
B27: CE | C27: 10303 | E27: 2481 | F27: 101 | G27: 7856 | H27: 3188 | I27: =SUM(C27:H27) -> 23929 | K27: CE | L27: =INT(C27/52) -> 198 | M27: =INT(D27/52) -> 0 | N27: 0 | O27: 0 | P27: 0 | Q27: 0 | R27: =SUM(L27:Q27) -> 198 | T27: CE | U27: =M42-R37 -> 121 | W27: CE | AB27: =-(U30+U28+U29) -> 16 | AC27: =U27-AB27 -> 105 | AD27: =SUM(X27:AC27) -> 121 | AF27: CE | AG27: =L89*28 -> 56 | AH27: =M89*28 -> 0 | AI27: =N89*28 -> 0 | AJ27: =O89*28 -> 0 | AK27: =P89*28 -> 0 | AL27: =Q89*28 -> 0 | AM27: =SUM(AG27:AL27) -> 56 | AO27: CE | AP27: =L89*2 -> 4 | AQ27: =M89*2 -> 0 | AR27: =N89*2 -> 0 | AS27: =O89*2 -> 0 | AT27: =P89*2 -> 0 | AU27: =Q89*2 -> 0 | AV27: =SUM(AP27:AU27) -> 4 | AX27: CE | AY27: =L89*C77 -> 27445.538 | AZ27: =M89*D77 -> 0 | BA27: =N89*E77 -> 0 | BB27: =O89*F77 -> 0 | BC27: =P89*G77 -> 0 | BD27: =Q89*H77 -> 0 | BE27: =SUM(AY27:BD27) -> 27445.538
B28: PE | C28: 17515 | D28: 5046 | F28: 652 | G28: 9764 | H28: 4287 | I28: =SUM(C28:H28) -> 37264 | K28: PE | L28: =INT(C28/52) -> 336 | M28: =INT(D28/52) -> 97 | N28: =INT(E28/52) -> 0 | O28: 0 | P28: =INT(G28/52) -> 187 | Q28: =INT(H28/52) -> 82 | R28: =SUM(L28:Q28) -> 702 | T28: PE | U28: =N42-R38 -> 109 | W28: PE | AB28: =U28 -> 109 | AD28: =SUM(X28:AC28) -> 109 | AF28: PE | AG28: =L90*28 -> 840 | AH28: =M90*28 -> 56 | AI28: =N90*28 -> 0 | AJ28: =O90*28 -> 0 | AK28: =P90*28 -> 0 | AL28: =Q90*28 -> 0 | AM28: =SUM(AG28:AL28) -> 896 | AO28: PE | AP28: =L90*2 -> 60 | AQ28: =M90*2 -> 4 | AR28: =N90*2 -> 0 | AS28: =O90*2 -> 0 | AT28: =P90*2 -> 0 | AU28: =Q90*2 -> 0 | AV28: =SUM(AP28:AU28) -> 64 | AX28: PE | AY28: =L90*C78 -> 483411.98 | AZ28: =M90*D78 -> 9166.1388 | BA28: =N90*E78 -> 0 | BB28: =O90*F78 -> 0 | BC28: =P90*G78 -> 0 | BD28: =Q90*H78 -> 0 | BE28: =SUM(AY28:BD28) -> 492578.12
B29: BA | C29: 3252 | D29: 2029 | E29: 1364 | G29: 10648 | H29: 2531 | I29: =SUM(C29:H29) -> 19824 | K29: BA | L29: =INT(C29/52) -> 62 | M29: =INT(D29/52) -> 39 | N29: =INT(E29/52) -> 26 | O29: =INT(F29/52) -> 0 | P29: 0 | Q29: 0 | R29: =SUM(L29:Q29) -> 127 | T29: BA | U29: =O42-R39 -> 11 | W29: BA | AB29: =U29 -> 11 | AD29: =SUM(X29:AC29) -> 11 | AF29: BA | AG29: =L91*28 -> 0 | AH29: =M91*28 -> 0 | AI29: =N91*28 -> 168 | AJ29: =O91*28 -> 0 | AK29: =P91*28 -> 0 | AL29: =Q91*28 -> 0 | AM29: =SUM(AG29:AL29) -> 168 | AO29: BA | AP29: =L91*2 -> 0 | AQ29: =M91*2 -> 0 | AR29: =N91*2 -> 12 | AS29: =O91*2 -> 0 | AT29: =P91*2 -> 0 | AU29: =Q91*2 -> 0 | AV29: =SUM(AP29:AU29) -> 12 | AX29: BA | AY29: =L91*C79 -> 0 | AZ29: =M91*D79 -> 0 | BA29: =N91*E79 -> 28706.808 | BB29: =O91*F79 -> 0 | BC29: =P91*G79 -> 0 | BD29: =Q91*H79 -> 0 | BE29: =SUM(AY29:BD29) -> 28706.808
B30: SP | C30: 18041 | D30: 22859 | E30: 29225 | F30: 4383 | I30: =SUM(C30:H30) -> 74508 | K30: SP | L30: =INT(C30/52) -> 346 | M30: =INT(D30/52) -> 439 | N30: =INT(E30/52) -> 562 | O30: =INT(F30/52) -> 84 | P30: =INT(G30/52) -> 0 | Q30: =INT(H30/52) -> 0 | R30: =SUM(L30:Q30) -> 1431 | T30: SP | U30: =P42-R40 -> -136 | W30: SP | AD30: =SUM(X30:AC30) -> 0 | AF30: SP | AG30: =L92*28 -> 0 | AH30: =M92*28 -> 0 | AI30: =N92*28 -> 28 | AJ30: =O92*28 -> 0 | AK30: =P92*28 -> 0 | AL30: =Q92*28 -> 0 | AM30: =SUM(AG30:AL30) -> 28 | AO30: SP | AP30: =L92*2 -> 0 | AQ30: =M92*2 -> 0 | AR30: =N92*2 -> 2 | AS30: =O92*2 -> 0 | AT30: =P92*2 -> 0 | AU30: =Q92*2 -> 0 | AV30: =SUM(AP30:AU30) -> 2 | AX30: SP | AY30: =L92*C80 -> 0 | AZ30: =M92*D80 -> 0 | BA30: =N92*E80 -> 14188.236 | BB30: =O92*F80 -> 0 | BC30: =P92*G80 -> 0 | BD30: =Q92*H80 -> 0 | BE30: =SUM(AY30:BD30) -> 14188.236
B31: SC | C31: 11210 | D31: 13198 | E31: 20046 | F31: 2406 | I31: =SUM(C31:H31) -> 46860 | K31: SC | L31: =INT(C31/52) -> 215 | M31: =INT(D31/52) -> 253 | N31: =INT(E31/52) -> 385 | O31: =INT(F31/52) -> 46 | P31: =INT(G31/52) -> 0 | Q31: =INT(H31/52) -> 0 | R31: =SUM(L31:Q31) -> 899 | T31: SC | U31: =Q42-R41 -> -303 | W31: SC | AD31: =SUM(X31:AC31) -> 0 | AF31: SC | AG31: =L93*28 -> 0 | AH31: =M93*28 -> 0 | AI31: =N93*28 -> 700 | AJ31: =O93*28 -> 168 | AK31: =P93*28 -> 0 | AL31: =Q93*28 -> 0 | AM31: =SUM(AG31:AL31) -> 868 | AO31: SC | AP31: =L93*2 -> 0 | AQ31: =M93*2 -> 0 | AR31: =N93*2 -> 50 | AS31: =O93*2 -> 12 | AT31: =P93*2 -> 0 | AU31: =Q93*2 -> 0 | AV31: =SUM(AP31:AU31) -> 62 | AX31: SC | AY31: =L93*C81 -> 0 | AZ31: =M93*D81 -> 0 | BA31: =N93*E81 -> 447013.61 | BB31: =O93*F81 -> 85811.072 | BC31: =P93*G81 -> 0 | BD31: =Q93*H81 -> 0 | BE31: =SUM(AY31:BD31) -> 532824.68
B32: Total Destino | C32: =SUM(C26:C31) -> 60321 | D32: =SUM(D26:D31) -> 49198 | E32: =SUM(E26:E31) -> 61348 | F32: =SUM(F26:F31) -> 10708 | G32: =SUM(G26:G31) -> 83251 | H32: =SUM(H26:H31) -> 15507 | I32: =SUM(I26:I31) -> 280333 | K32: Total Destino | L32: =SUM(L26:L31) -> 1157 | M32: =SUM(M26:M31) -> 828 | N32: =SUM(N26:N31) -> 1131 | O32: =SUM(O26:O31) -> 130 | P32: =SUM(P26:P31) -> 1244 | Q32: =SUM(Q26:Q31) -> 187 | R32: =SUM(R26:R31) -> 4677 | T32: Total | U32: =SUM(U26:U31) -> 0 | W32: Total Destino | X32: =SUM(X26:X31) -> 0 | Y32: =SUM(Y26:Y31) -> 0 | Z32: =SUM(Z26:Z31) -> 0 | AA32: =SUM(AA26:AA31) -> 0 | AB32: =SUM(AB26:AB31) -> 136 | AC32: =SUM(AC26:AC31) -> 303 | AD32: =SUM(AD26:AD31) -> 439 | AF32: Total Destino | AG32: =SUM(AG26:AG31) -> 896 | AH32: =SUM(AH26:AH31) -> 56 | AI32: =SUM(AI26:AI31) -> 896 | AJ32: =SUM(AJ26:AJ31) -> 168 | AK32: =SUM(AK26:AK31) -> 28 | AL32: =SUM(AL26:AL31) -> 0 | AM32: =SUM(AM26:AM31) -> 2044 | AO32: Total Destino | AP32: =SUM(AP26:AP31) -> 64 | AQ32: =SUM(AQ26:AQ31) -> 4 | AR32: =SUM(AR26:AR31) -> 64 | AS32: =SUM(AS26:AS31) -> 12 | AT32: =SUM(AT26:AT31) -> 2 | AU32: =SUM(AU26:AU31) -> 0 | AV32: =SUM(AV26:AV31) -> 146 | AX32: Total Destino | AY32: =SUM(AY26:AY31) -> 510857.52 | AZ32: =SUM(AZ26:AZ31) -> 9166.1388 | BA32: =SUM(BA26:BA31) -> 489908.66 | BB32: =SUM(BB26:BB31) -> 85811.072 | BC32: =SUM(BC26:BC31) -> 20549.667 | BD32: =SUM(BD26:BD31) -> 0 | BE32: =SUM(BE26:BE31) -> 1116293.1
BD33: REC. SEM. | BE33: =SUM(AY26:BD31) -> 1116293.1
B34: Movimentação de Contêineres na Cabotagem em 2022 - 40RH | K34: Movimentação 2022 - 40RH | T34: *20RF não apresentou qauntidade significativa, portanto será desconsiderado | AF34: MATRIZ OD 20 DC VAZIOS - TONELADAS | AO34: MATRIZ OD 20 DC VAZIOS - TEU
B35: Origem/Destino | C35: AM | D35: CE | E35: PE | F35: BA | G35: SP | H35: SC | I35: Total Origem | K35: Origem/Destino | L35: AM | M35: CE | N35: PE | O35: BA | P35: SP | Q35: SC | R35: Total Origem | AF35: Origem/Destino | AG35: AM | AH35: CE | AI35: PE | AJ35: BA | AK35: SP | AL35: SC | AM35: Total Origem | AO35: Origem/Destino | AP35: AM | AQ35: CE | AR35: PE | AS35: BA | AT35: SP | AU35: SC | AV35: Total Origem
B36: AM | D36: 12 | E36: 6 | F36: 1 | G36: 58 | H36: 46 | I36: =SUM(C36:H36) -> 123 | K36: AM | L36: =INT(C36/52) -> 0 | M36: 0 | N36: =INT(E36/52) -> 0 | O36: 0 | P36: =INT(G36/52) -> 1 | Q36: =INT(H36/52) -> 0 | R36: =SUM(L36:Q36) -> 1 | AF36: AM | AG36: =X68*2 -> 0 | AH36: =Y68*2 -> 0 | AI36: =Z68*2 -> 0 | AJ36: =AA68*2 -> 0 | AK36: =AB68*2 -> 0 | AL36: =AC68*2 -> 66 | AM36: =SUM(AG36:AL36) -> 66 | AO36: AM | AP36: =X68 | AQ36: =Y68 | AR36: =Z68 | AS36: =AA68 | AT36: =AB68 | AU36: =AC68 -> 33 | AV36: =SUM(AP36:AU36) -> 33
B37: CE | C37: 155 | E37: 17 | F37: 2 | G37: 215 | H37: 78 | I37: =SUM(C37:H37) -> 467 | K37: CE | L37: =INT(C37/52) -> 2 | M37: =INT(D37/52) -> 0 | N37: 0 | O37: 0 | P37: 0 | Q37: 0 | R37: =SUM(L37:Q37) -> 2 | AF37: CE | AG37: =X69*2 -> 0 | AH37: =Y69*2 -> 0 | AI37: =Z69*2 -> 0 | AJ37: =AA69*2 -> 0 | AK37: =AB69*2 -> 0 | AL37: =AC69*2 -> 0 | AM37: =SUM(AG37:AL37) -> 0 | AO37: CE | AP37: =X69 | AQ37: =Y69 | AR37: =Z69 | AS37: =AA69 | AT37: =AB69 -> 0 | AU37: =AC69 -> 0 | AV37: =SUM(AP37:AU37) -> 0 | AX37: RESUMO
B38: PE | C38: 1593 | D38: 407 | F38: 1 | G38: 40 | H38: 9 | I38: =SUM(C38:H38) -> 2050 | K38: PE | L38: =INT(C38/52) -> 30 | M38: =INT(D38/52) -> 7 | N38: =INT(E38/52) -> 0 | O38: 0 | P38: =INT(G38/52) -> 0 | Q38: =INT(H38/52) -> 0 | R38: =SUM(L38:Q38) -> 37 | AF38: PE | AG38: =X70*2 -> 0 | AH38: =Y70*2 -> 0 | AI38: =Z70*2 -> 0 | AJ38: =AA70*2 -> 0 | AK38: =AB70*2 -> 0 | AL38: =AC70*2 -> 0 | AM38: =SUM(AG38:AL38) -> 0 | AO38: PE | AP38: =X70 | AQ38: =Y70 | AR38: =Z70 | AS38: =AA70 | AT38: =AB70 | AU38: =AC70 -> 0 | AV38: =SUM(AP38:AU38) -> 0 | AX38: REC. SEM. | AY38: =BE33+BE23+BE13 -> 65986446
B39: BA | C39: 214 | D39: 327 | E39: 339 | G39: 644 | H39: 24 | I39: =SUM(C39:H39) -> 1548 | K39: BA | L39: =INT(C39/52) -> 4 | M39: =INT(D39/52) -> 6 | N39: =INT(E39/52) -> 6 | O39: =INT(F39/52) -> 0 | P39: 0 | Q39: 0 | R39: =SUM(L39:Q39) -> 16 | AF39: BA | AG39: =X71*2 -> 0 | AH39: =Y71*2 -> 0 | AI39: =Z71*2 -> 0 | AJ39: =AA71*2 -> 0 | AK39: =AB71*2 -> 0 | AL39: =AC71*2 -> 0 | AM39: =SUM(AG39:AL39) -> 0 | AO39: BA | AP39: =X71 | AQ39: =Y71 | AR39: =Z71 | AS39: =AA71 | AT39: =AB71 -> 0 | AU39: =AC71 | AV39: =SUM(AP39:AU39) -> 0
B40: SP | C40: 2308 | D40: 2321 | E40: 2268 | F40: 331 | I40: =SUM(C40:H40) -> 7228 | K40: SP | L40: =INT(C40/52) -> 44 | M40: =INT(D40/52) -> 44 | N40: =INT(E40/52) -> 43 | O40: =INT(F40/52) -> 6 | P40: =INT(G40/52) -> 0 | Q40: =INT(H40/52) -> 0 | R40: =SUM(L40:Q40) -> 137 | AF40: SP | AG40: =X72*2 -> 0 | AH40: =Y72*2 -> 0 | AI40: =Z72*2 -> 0 | AJ40: =AA72*2 -> 0 | AK40: =AB72*2 -> 0 | AL40: =AC72*2 -> 0 | AM40: =SUM(AG40:AL40) -> 0 | AO40: SP | AP40: =X72 | AQ40: =Y72 | AR40: =Z72 | AS40: =AA72 | AT40: =AB72 | AU40: =AC72 | AV40: =SUM(AP40:AU40) -> 0
B41: SC | C41: 6226 | D41: 3479 | E41: 5045 | F41: 1134 | I41: =SUM(C41:H41) -> 15884 | K41: SC | L41: =INT(C41/52) -> 119 | M41: =INT(D41/52) -> 66 | N41: =INT(E41/52) -> 97 | O41: =INT(F41/52) -> 21 | P41: =INT(G41/52) -> 0 | Q41: =INT(H41/52) -> 0 | R41: =SUM(L41:Q41) -> 303 | AF41: SC | AG41: =X73*2 -> 0 | AH41: =Y73*2 -> 0 | AI41: =Z73*2 -> 0 | AJ41: =AA73*2 -> 0 | AK41: =AB73*2 -> 0 | AL41: =AC73*2 -> 0 | AM41: =SUM(AG41:AL41) -> 0 | AO41: SC | AP41: =X73 | AQ41: =Y73 | AR41: =Z73 | AS41: =AA73 | AT41: =AB73 | AU41: =AC73 | AV41: =SUM(AP41:AU41) -> 0 | AX41: =AY38*52 -> 3431295178
B42: Total Destino | C42: =SUM(C36:C41) -> 10496 | D42: =SUM(D36:D41) -> 6546 | E42: =SUM(E36:E41) -> 7675 | F42: =SUM(F36:F41) -> 1469 | G42: =SUM(G36:G41) -> 957 | H42: =SUM(H36:H41) -> 157 | I42: =SUM(I36:I41) -> 27300 | K42: Total Destino | L42: =SUM(L36:L41) -> 199 | M42: =SUM(M36:M41) -> 123 | N42: =SUM(N36:N41) -> 146 | O42: =SUM(O36:O41) -> 27 | P42: =SUM(P36:P41) -> 1 | Q42: =SUM(Q36:Q41) -> 0 | R42: =SUM(R36:R41) -> 496 | AF42: Total Destino | AG42: =SUM(AG36:AG41) -> 0 | AH42: =SUM(AH36:AH41) -> 0 | AI42: =SUM(AI36:AI41) -> 0 | AJ42: =SUM(AJ36:AJ41) -> 0 | AK42: =SUM(AK36:AK41) -> 0 | AL42: =SUM(AL36:AL41) -> 66 | AM42: =SUM(AM36:AM41) -> 66 | AO42: Total Destino | AP42: =SUM(AP36:AP41) -> 0 | AQ42: =SUM(AQ36:AQ41) -> 0 | AR42: =SUM(AR36:AR41) -> 0 | AS42: =SUM(AS36:AS41) -> 0 | AT42: =SUM(AT36:AT41) -> 0 | AU42: =SUM(AU36:AU41) -> 33 | AV42: =SUM(AV36:AV41) -> 33
B44: Movimentação de Contêineres na Cabotagem em 2022 - unidades | K44: Movimentação 2022 - unidades | AF44: MATRIZ OD 40 HC VAZIOS - TONELADAS | AO44: MATRIZ OD 40 HC VAZIOS - TEU
B45: Origem/Destino | C45: AM | D45: CE | E45: PE | F45: BA | G45: SP | H45: SC | I45: Total Origem | K45: Origem/Destino | L45: AM | M45: CE | N45: PE | O45: BA | P45: SP | Q45: SC | R45: Total Origem | AF45: Origem/Destino | AG45: AM | AH45: CE | AI45: PE | AJ45: BA | AK45: SP | AL45: SC | AM45: Total Origem | AO45: Origem/Destino | AP45: AM | AQ45: CE | AR45: PE | AS45: BA | AT45: SP | AU45: SC | AV45: Total Origem
B46: AM | C46: =C6+C16+C26+C36 -> 0 | D46: =D6+D16+D26+D36 -> 7825 | E46: =E6+E16+E26+E36 -> 8552 | F46: =F6+F16+F26+F36 -> 3498 | G46: =G6+G16+G26+G36 -> 57554 | H46: =H6+H16+H26+H36 -> 6022 | I46: =SUM(C46:H46) -> 83451 | K46: AM | L46: =L6+L16+L26+L36 -> 0 | M46: =M6+M16+M26+M36 -> 0 | N46: =N6+N16+N26+N36 -> 164 | O46: =O6+O16+O26+O36 -> 0 | P46: =P6+P16+P26+P36 -> 1106 | Q46: =Q6+Q16+Q26+Q36 -> 114 | R46: =SUM(L46:Q46) -> 1384 | AF46: AM | AG46: =X78*4 -> 0 | AH46: =Y78*4 -> 0 | AI46: =Z78*4 -> 0 | AJ46: =AA78*4 -> 0 | AK46: =AB78*4 -> 0 | AL46: =AC78*4 -> 0 | AM46: =SUM(AG46:AL46) -> 0 | AO46: AM | AP46: =X78*2 -> 0 | AQ46: =Y78*2 -> 0 | AR46: =Z78*2 -> 0 | AS46: =AA78*2 -> 0 | AT46: =AB78*2 -> 0 | AU46: =AC78*2 -> 0 | AV46: =SUM(AP46:AU46) -> 0
B47: CE | C47: =C7+C17+C27+C37 -> 13384 | D47: =D7+D17+D27+D37 -> 0 | E47: =E7+E17+E27+E37 -> 2780 | F47: =F7+F17+F27+F37 -> 594 | G47: =G7+G17+G27+G37 -> 17206 | H47: =H7+H17+H27+H37 -> 7321 | I47: =SUM(C47:H47) -> 41285 | K47: CE | L47: =L7+L17+L27+L37 -> 256 | M47: =M7+M17+M27+M37 -> 0 | N47: =N7+N17+N27+N37 -> 0 | O47: =O7+O17+O27+O37 -> 0 | P47: =P7+P17+P27+P37 -> 0 | Q47: =Q7+Q17+Q27+Q37 -> 0 | R47: =SUM(L47:Q47) -> 256 | AF47: CE | AG47: =X79*4 -> 0 | AH47: =Y79*4 -> 0 | AI47: =Z79*4 -> 0 | AJ47: =AA79*4 -> 0 | AK47: =AB79*4 -> 0 | AL47: =AC79*4 -> 0 | AM47: =SUM(AG47:AL47) -> 0 | AO47: CE | AP47: =X79*2 -> 0 | AQ47: =Y79*2 -> 0 | AR47: =Z79*2 -> 0 | AS47: =AA79*2 -> 0 | AT47: =AB79*2 -> 0 | AU47: =AC79*2 -> 0 | AV47: =SUM(AP47:AU47) -> 0
B48: PE | C48: =C8+C18+C28+C38 -> 21147 | D48: =D8+D18+D28+D38 -> 6937 | E48: =E8+E18+E28+E38 -> 0 | F48: =F8+F18+F28+F38 -> 3620 | G48: =G8+G18+G28+G38 -> 18324 | H48: =H8+H18+H28+H38 -> 5127 | I48: =SUM(C48:H48) -> 55155 | K48: PE | L48: =L8+L18+L28+L38 -> 405 | M48: =M8+M18+M28+M38 -> 132 | N48: =N8+N18+N28+N38 -> 0 | O48: =O8+O18+O28+O38 -> 0 | P48: =P8+P18+P28+P38 -> 350 | Q48: =Q8+Q18+Q28+Q38 -> 97 | R48: =SUM(L48:Q48) -> 984 | AF48: PE | AG48: =X80*4 -> 764 | AH48: =Y80*4 -> 0 | AI48: =Z80*4 -> 0 | AJ48: =AA80*4 -> 0 | AK48: =AB80*4 -> 0 | AL48: =AC80*4 -> 0 | AM48: =SUM(AG48:AL48) -> 764 | AO48: PE | AP48: =X80*2 -> 382 | AQ48: =Y80*2 -> 0 | AR48: =Z80*2 -> 0 | AS48: =AA80*2 -> 0 | AT48: =AB80*2 -> 0 | AU48: =AC80*2 -> 0 | AV48: =SUM(AP48:AU48) -> 382
B49: BA | C49: =C9+C19+C29+C39 -> 3873 | D49: =D9+D19+D29+D39 -> 3139 | E49: =E9+E19+E29+E39 -> 2375 | F49: =F9+F19+F29+F39 -> 0 | G49: =G9+G19+G29+G39 -> 22201 | H49: =H9+H19+H29+H39 -> 2846 | I49: =SUM(C49:H49) -> 34434 | K49: BA | L49: =L9+L19+L29+L39 -> 73 | M49: =M9+M19+M29+M39 -> 59 | N49: =N9+N19+N29+N39 -> 44 | O49: =O9+O19+O29+O39 -> 0 | P49: =P9+P19+P29+P39 -> 0 | Q49: =Q9+Q19+Q29+Q39 -> 0 | R49: =SUM(L49:Q49) -> 176 | AF49: BA | AG49: =X81*4 -> 0 | AH49: =Y81*4 -> 0 | AI49: =Z81*4 -> 0 | AJ49: =AA81*4 -> 0 | AK49: =AB81*4 -> 0 | AL49: =AC81*4 -> 0 | AM49: =SUM(AG49:AL49) -> 0 | AO49: BA | AP49: =X81*2 -> 0 | AQ49: =Y81*2 -> 0 | AR49: =Z81*2 -> 0 | AS49: =AA81*2 -> 0 | AT49: =AB81*2 -> 0 | AU49: =AC81*2 -> 0 | AV49: =SUM(AP49:AU49) -> 0
B50: SP | C50: =C10+C20+C30+C40 -> 24407 | D50: =D10+D20+D30+D40 -> 31566 | E50: =E10+E20+E30+E40 -> 38079 | F50: =F10+F20+F30+F40 -> 6793 | G50: =G10+G20+G30+G40 -> 0 | H50: =H10+H20+H30+H40 -> 0 | I50: =SUM(C50:H50) -> 100845 | K50: SP | L50: =L10+L20+L30+L40 -> 468 | M50: =M10+M20+M30+M40 -> 605 | N50: =N10+N20+N30+N40 -> 731 | O50: =O10+O20+O30+O40 -> 129 | P50: =P10+P20+P30+P40 -> 0 | Q50: =Q10+Q20+Q30+Q40 -> 0 | R50: =SUM(L50:Q50) -> 1933 | AF50: SP | AG50: =X82*4 -> 0 | AH50: =Y82*4 -> 0 | AI50: =Z82*4 -> 0 | AJ50: =AA82*4 -> 0 | AK50: =AB82*4 -> 0 | AL50: =AC82*4 -> 0 | AM50: =SUM(AG50:AL50) -> 0 | AO50: SP | AP50: =X82*2 -> 0 | AQ50: =Y82*2 -> 0 | AR50: =Z82*2 -> 0 | AS50: =AA82*2 -> 0 | AT50: =AB82*2 -> 0 | AU50: =AC82*2 -> 0 | AV50: =SUM(AP50:AU50) -> 0
B51: SC | C51: =C11+C21+C31+C41 -> 18888 | D51: =D11+D21+D31+D41 -> 28520 | E51: =E11+E21+E31+E41 -> 38701 | F51: =F11+F21+F31+F41 -> 7743 | G51: =G11+G21+G31+G41 -> 0 | H51: =H11+H21+H31+H41 -> 0 | I51: =SUM(C51:H51) -> 93852 | K51: SC | L51: =L11+L21+L31+L41 -> 361 | M51: =M11+M21+M31+M41 -> 546 | N51: =N11+N21+N31+N41 -> 743 | O51: =O11+O21+O31+O41 -> 147 | P51: =P11+P21+P31+P41 -> 0 | Q51: =Q11+Q21+Q31+Q41 -> 0 | R51: =SUM(L51:Q51) -> 1797 | AF51: SC | AG51: =X83*4 -> 0 | AH51: =Y83*4 -> 0 | AI51: =Z83*4 -> 0 | AJ51: =AA83*4 -> 0 | AK51: =AB83*4 -> 0 | AL51: =AC83*4 -> 0 | AM51: =SUM(AG51:AL51) -> 0 | AO51: SC | AP51: =X83*2 -> 0 | AQ51: =Y83*2 -> 0 | AR51: =Z83*2 -> 0 | AS51: =AA83*2 -> 0 | AT51: =AB83*2 -> 0 | AU51: =AC83*2 -> 0 | AV51: =SUM(AP51:AU51) -> 0
B52: Total Destino | C52: =SUM(C46:C51) -> 81699 | D52: =SUM(D46:D51) -> 77987 | E52: =SUM(E46:E51) -> 90487 | F52: =SUM(F46:F51) -> 22248 | G52: =SUM(G46:G51) -> 115285 | H52: =SUM(H46:H51) -> 21316 | I52: =SUM(I46:I51) -> 409022 | K52: Total Destino | L52: =SUM(L46:L51) -> 1563 | M52: =SUM(M46:M51) -> 1342 | N52: =SUM(N46:N51) -> 1682 | O52: =SUM(O46:O51) -> 276 | P52: =SUM(P46:P51) -> 1456 | Q52: =SUM(Q46:Q51) -> 211 | R52: =SUM(R46:R51) -> 6530 | AF52: Total Destino | AG52: =SUM(AG46:AG51) -> 764 | AH52: =SUM(AH46:AH51) -> 0 | AI52: =SUM(AI46:AI51) -> 0 | AJ52: =SUM(AJ46:AJ51) -> 0 | AK52: =SUM(AK46:AK51) -> 0 | AL52: =SUM(AL46:AL51) -> 0 | AM52: =SUM(AM46:AM51) -> 764 | AO52: Total Destino | AP52: =SUM(AP46:AP51) -> 382 | AQ52: =SUM(AQ46:AQ51) -> 0 | AR52: =SUM(AR46:AR51) -> 0 | AS52: =SUM(AS46:AS51) -> 0 | AT52: =SUM(AT46:AT51) -> 0 | AU52: =SUM(AU46:AU51) -> 0 | AV52: =SUM(AV46:AV51) -> 382
B54: Movimentação de Contêineres na Cabotagem em 2022 - TEU | K54: Movimentação 2022 - TEU | AF54: MATRIZ OD 40 RH VAZIOS - TONELADAS | AO54: MATRIZ OD 40 RH VAZIOS - TEU
B55: Origem/Destino | C55: AM | D55: CE | E55: PE | F55: BA | G55: SP | H55: SC | I55: Total Origem | K55: Origem/Destino | L55: AM | M55: CE | N55: PE | O55: BA | P55: SP | Q55: SC | R55: Total Origem | AF55: Origem/Destino | AG55: AM | AH55: CE | AI55: PE | AJ55: BA | AK55: SP | AL55: SC | AM55: Total Origem | AO55: Origem/Destino | AP55: AM | AQ55: CE | AR55: PE | AS55: BA | AT55: SP | AU55: SC | AV55: Total Origem
B56: AM | C56: =C46+C26+C36 -> 0 | D56: =D46+D26+D36 -> 13903 | E56: =E46+E26+E36 -> 16790 | F56: =F46+F26+F36 -> 6665 | G56: =G46+G26+G36 -> 112595 | H56: =H46+H26+H36 -> 11569 | I56: =SUM(C56:H56) -> 161522 | K56: AM | L56: =L46+L26+L36 -> 0 | M56: =M46+M26+M36 -> 0 | N56: =N46+N26+N36 -> 322 | O56: =O46+O26+O36 -> 0 | P56: =P46+P26+P36 -> 2164 | Q56: =Q46+Q26+Q36 -> 219 | R56: =SUM(L56:Q56) -> 2705 | AF56: AM | AG56: =X88*4 -> 0 | AH56: =Y88*4 -> 0 | AI56: =Z88*4 -> 0 | AJ56: =AA88*4 -> 0 | AK56: =AB88*4 -> 0 | AL56: =AC88*4 -> 124 | AM56: =SUM(AG56:AL56) -> 124 | AO56: AM | AP56: =X88*2 -> 0 | AQ56: =Y88*2 -> 0 | AR56: =Z88*2 -> 0 | AS56: =AA88*2 -> 0 | AT56: =AB88*2 -> 0 | AU56: =AC88*2 -> 62 | AV56: =SUM(AP56:AU56) -> 62
B57: CE | C57: =C47+C27+C37 -> 23842 | D57: =D47+D27+D37 -> 0 | E57: =E47+E27+E37 -> 5278 | F57: =F47+F27+F37 -> 697 | G57: =G47+G27+G37 -> 25277 | H57: =H47+H27+H37 -> 10587 | I57: =SUM(C57:H57) -> 65681 | K57: CE | L57: =L47+L27+L37 -> 456 | M57: =M47+M27+M37 -> 0 | N57: =N47+N27+N37 -> 0 | O57: =O47+O27+O37 -> 0 | P57: =P47+P27+P37 -> 0 | Q57: =Q47+Q27+Q37 -> 0 | R57: =SUM(L57:Q57) -> 456 | AF57: CE | AG57: =X89*4 -> 0 | AH57: =Y89*4 -> 0 | AI57: =Z89*4 -> 0 | AJ57: =AA89*4 -> 0 | AK57: =AB89*4 -> 0 | AL57: =AC89*4 -> 0 | AM57: =SUM(AG57:AL57) -> 0 | AO57: CE | AP57: =X89*2 -> 0 | AQ57: =Y89*2 -> 0 | AR57: =Z89*2 -> 0 | AS57: =AA89*2 -> 0 | AT57: =AB89*2 -> 0 | AU57: =AC89*2 -> 0 | AV57: =SUM(AP57:AU57) -> 0
B58: PE | C58: =C48+C28+C38 -> 40255 | D58: =D48+D28+D38 -> 12390 | E58: =E48+E28+E38 -> 0 | F58: =F48+F28+F38 -> 4273 | G58: =G48+G28+G38 -> 28128 | H58: =H48+H28+H38 -> 9423 | I58: =SUM(C58:H58) -> 94469 | K58: PE | L58: =L48+L28+L38 -> 771 | M58: =M48+M28+M38 -> 236 | N58: =N48+N28+N38 -> 0 | O58: =O48+O28+O38 -> 0 | P58: =P48+P28+P38 -> 537 | Q58: =Q48+Q28+Q38 -> 179 | R58: =SUM(L58:Q58) -> 1723 | AF58: PE | AG58: =X90*4 -> 0 | AH58: =Y90*4 -> 0 | AI58: =Z90*4 -> 0 | AJ58: =AA90*4 -> 0 | AK58: =AB90*4 -> 0 | AL58: =AC90*4 -> 0 | AM58: =SUM(AG58:AL58) -> 0 | AO58: PE | AP58: =X90*2 -> 0 | AQ58: =Y90*2 -> 0 | AR58: =Z90*2 -> 0 | AS58: =AA90*2 -> 0 | AT58: =AB90*2 -> 0 | AU58: =AC90*2 -> 0 | AV58: =SUM(AP58:AU58) -> 0
B59: BA | C59: =C49+C29+C39 -> 7339 | D59: =D49+D29+D39 -> 5495 | E59: =E49+E29+E39 -> 4078 | F59: =F49+F29+F39 -> 0 | G59: =G49+G29+G39 -> 33493 | H59: =H49+H29+H39 -> 5401 | I59: =SUM(C59:H59) -> 55806 | K59: BA | L59: =L49+L29+L39 -> 139 | M59: =M49+M29+M39 -> 104 | N59: =N49+N29+N39 -> 76 | O59: =O49+O29+O39 -> 0 | P59: =P49+P29+P39 -> 0 | Q59: =Q49+Q29+Q39 -> 0 | R59: =SUM(L59:Q59) -> 319 | U59: comentário sobre a matriz OD de vazios: colocamos uma restrição no solver de modo que as céluas em verde fossem >= a zero, já que não foi observado o imbalance estrutural e se ficasse com um valor negativo, prejudicaria a lógica do restante da planilha. | AF59: BA | AG59: =X91*4 -> 0 | AH59: =Y91*4 -> 0 | AI59: =Z91*4 -> 0 | AJ59: =AA91*4 -> 0 | AK59: =AB91*4 -> 0 | AL59: =AC91*4 -> 0 | AM59: =SUM(AG59:AL59) -> 0 | AO59: BA | AP59: =X91*2 -> 0 | AQ59: =Y91*2 -> 0 | AR59: =Z91*2 -> 0 | AS59: =AA91*2 -> 0 | AT59: =AB91*2 -> 0 | AU59: =AC91*2 -> 0 | AV59: =SUM(AP59:AU59) -> 0
B60: SP | C60: =C50+C30+C40 -> 44756 | D60: =D50+D30+D40 -> 56746 | E60: =E50+E30+E40 -> 69572 | F60: =F50+F30+F40 -> 11507 | G60: =G50+G30+G40 -> 0 | H60: =H50+H30+H40 -> 0 | I60: =SUM(C60:H60) -> 182581 | K60: SP | L60: =L50+L30+L40 -> 858 | M60: =M50+M30+M40 -> 1088 | N60: =N50+N30+N40 -> 1336 | O60: =O50+O30+O40 -> 219 | P60: =P50+P30+P40 -> 0 | Q60: =Q50+Q30+Q40 -> 0 | R60: =SUM(L60:Q60) -> 3501 | AF60: SP | AG60: =X92*4 -> 0 | AH60: =Y92*4 -> 0 | AI60: =Z92*4 -> 0 | AJ60: =AA92*4 -> 0 | AK60: =AB92*4 -> 0 | AL60: =AC92*4 -> 0 | AM60: =SUM(AG60:AL60) -> 0 | AO60: SP | AP60: =X92*2 -> 0 | AQ60: =Y92*2 -> 0 | AR60: =Z92*2 -> 0 | AS60: =AA92*2 -> 0 | AT60: =AB92*2 -> 0 | AU60: =AC92*2 -> 0 | AV60: =SUM(AP60:AU60) -> 0
B61: SC | C61: =C51+C31+C41 -> 36324 | D61: =D51+D31+D41 -> 45197 | E61: =E51+E31+E41 -> 63792 | F61: =F51+F31+F41 -> 11283 | G61: =G51+G31+G41 -> 0 | H61: =H51+H31+H41 -> 0 | I61: =SUM(C61:H61) -> 156596 | K61: SC | L61: =L51+L31+L41 -> 695 | M61: =M51+M31+M41 -> 865 | N61: =N51+N31+N41 -> 1225 | O61: =O51+O31+O41 -> 214 | P61: =P51+P31+P41 -> 0 | Q61: =Q51+Q31+Q41 -> 0 | R61: =SUM(L61:Q61) -> 2999 | AF61: SC | AG61: =X93*4 -> 0 | AH61: =Y93*4 -> 0 | AI61: =Z93*4 -> 0 | AJ61: =AA93*4 -> 0 | AK61: =AB93*4 -> 0 | AL61: =AC93*4 -> 0 | AM61: =SUM(AG61:AL61) -> 0 | AO61: SC | AP61: =X93*2 -> 0 | AQ61: =Y93*2 -> 0 | AR61: =Z93*2 -> 0 | AS61: =AA93*2 -> 0 | AT61: =AB93*2 -> 0 | AU61: =AC93*2 -> 0 | AV61: =SUM(AP61:AU61) -> 0
